Workbook

Sheet 총괄
A1: 학과 | B1: 분반 | C1: 학번 | D1: 이름 | E1: 전화번호 | F1: 이메일 | G1: W07_Q01_응답 | H1: W07_Q02_응답 | I1: W07_Q03_응답 | J1: W07_Q04_응답 | K1: W07_Q05_응답 | L1: W07_Q06_응답 | M1: W07_Q07_응답 | N1: W07_Q08_응답 | O1: W07_Q09_응답 | P1: W07_Q10_응답 | Q1: W07 | R1: W08_Q01_응답 | S1: W08_Q02_응답 | T1: W08_Q03_응답 | U1: W08_Q04_응답 | V1: W08_Q05_응답 | W1: W08_Q06_응답 | X1: W08_Q07_응답 | Y1: W08_Q08_응답 | Z1: W08_Q09_응답 | AA1: W08_Q10_응답 | AB1: W08 | AC1: W09_Q01_응답 | AD1: W09_Q02_응답 | AE1: W09_Q03_응답 | AF1: W09_Q04_응답 | AG1: W09_Q05_응답 | AH1: W09_Q06_응답 | AI1: W09_Q07_응답 | AJ1: W09_Q08_응답 | AK1: W09_Q09_응답 | AL1: W09_Q10_응답 | AM1: W09 | AN1: W10_Q01_응답 | AO1: W10_Q02_응답 | AP1: W10_Q03_응답 | AQ1: W10_Q04_응답 | AR1: W10_Q05_응답 | AS1: W10_Q06_응답 | AT1: W10_Q07_응답 | AU1: W10_Q08_응답 | AV1: W10_Q09_응답 | AW1: W10_Q10_응답 | AX1: W10 | AY1: W11_Q01_응답 | AZ1: W11_Q02_응답 | BA1: W11_Q03_응답 | BB1: W11_Q04_응답 | BC1: W11_Q05_응답 | BD1: W11_Q06_응답 | BE1: W11_Q07_응답 | BF1: W11_Q08_응답 | BG1: W11_Q09_응답 | BH1: W11_Q10_응답 | BI1: W11 | BJ1: 퀴즈합계 | BK1: 퀴즈응답수 | BL1: 퀴즈점수(30) | BM1: 출석점수(30) | BN1: 중간고사(20) | BO1: 기말고사(20) | BP1: 총점(100) | BQ1: 석차(분반) | BR1: 평점 | BS1: 결석수 | BT1: 비고
A2: 경영학부 경영학전공 | B2: 1 | C2: 20220034 | D2: 양곤 | E2: 010-5847-5169 | F2: 3201743705@qq.com | R2: BPR | S2: 遵循日常运营的正式化和标准化程序。 | T2: 企业间流程 | U2: 相同数据在多个部门重复存储，导致不一致。 | V2: 引入企业信息系统（EIS） | W2: 减少不必要的审批环节，从而最大限度地减少时间和资源。 | X2: 整合管理与客户的所有互动，最大限度地提高客户终身价值。 | Y2: 将业务运营整合到一个单一且一致的计算平台。 | Z2: O | AA2: O | AB2: =10*SUMPRODUCT(--(R2:AA2<>""),--(((R2:AA2=정답표!$C$4:$L$4)+(R2:AA2=정답표!$C$5:$L$5))>0)) -> 100 | AC2: 硬件、软件、数据、流程、人员 | AD2: 组织战略决定价值链，价值链决定业务流程，业务流程决定 SMIS 需求。 | AE2: 增加物质资本 | AF2: 直接销售用户数据：通过直接销售用户个人数据获取主要收入。 | AG2: 创新 (Innovation) | AH2: 指通过电子邮件、消息应用等难以追踪的渠道进行的社交分享区域，企业应在此处关注建立信任。 | AI2: 基于兴趣形成，一个用户可以同时属于多个社区。 | AJ2: 财务与会计 | AK2: O | AL2: O | AM2: =10*SUMPRODUCT(--(AC2:AL2<>""),--(((AC2:AL2=정답표!$C$6:$L$6)+(AC2:AL2=정답표!$C$7:$L$7))>0)) -> 100 | AY2: 支持IT技术以实现组织目标，并将其与经营目标相结合。 | AZ2: 有效连接信息系统(IS)战略与企业经营战略。 | BA2: 根据组织的目标和优先顺序，综合考虑战略、预算和风险。 | BB2: 谁来做信息系统相关的决策，谁来承担责任？ | BC2: 综合考虑项目的战略适用性和实际可行性。 | BD2: 将组织的部分IT功能委托给外部专业公司执行。 | BE2: 安全威胁完全消除，信息安全得到加强。 | BF2: O | BG2: O | BH2: X | BI2: =10*SUMPRODUCT(--(AY2:BH2<>""),--(((AY2:BH2=정답표!$C$10:$L$10)+(AY2:BH2=정답표!$C$11:$L$11))>0)) -> 100 | BJ2: =SUM(Q2,AB2,AM2,AX2,BI2) -> 300 | BK2: =COUNT(Q2,AB2,AM2,AX2,BI2) -> 3 | BL2: =IF(QuizMatchTable[[#This Row],[분반]]=1, QuizMatchTable[[#This Row],[퀴즈합계]]/4 *0.3, QuizMatchTable[[#This Row],[퀴즈합계]]/5*0.3) -> 22.5 | BM2: 28 | BN2: 19.2 | BP2: =SUM(QuizMatchTable[[#This Row],[퀴즈점수(30)]],BM2,BN2,BO2) -> 69.7 | BQ2: =IF(OR(BP2="",BP2=0,BT2="결석초과"),"",COUNTIFS($B$2:$B$109,B2,$BP$2:$BP$109,">"&BP2)+1) -> 5 | BR2: A0 | BS2: 3
A3: 경영학부 경영학전공 | B3: 1 | C3: 20220036 | D3: 이가기 | E3: 010-2451-5770 | F3: keeeyo@163.com | R3: BPR | S3: 遵循日常运营的正式化和标准化程序。 | T3: 企业间流程 | U3: 相同数据在多个部门重复存储，导致不一致。 | V3: 引入企业信息系统（EIS） | W3: 减少不必要的审批环节，从而最大限度地减少时间和资源。 | X3: 整合管理与客户的所有互动，最大限度地提高客户终身价值。 | Y3: 将业务运营整合到一个单一且一致的计算平台。 | Z3: O | AA3: O | AB3: =10*SUMPRODUCT(--(R3:AA3<>""),--(((R3:AA3=정답표!$C$4:$L$4)+(R3:AA3=정답표!$C$5:$L$5))>0)) -> 100 | AY3: 支持IT技术以实现组织目标，并将其与经营目标相结合。 | AZ3: 有效连接信息系统(IS)战略与企业经营战略。 | BA3: 根据组织的目标和优先顺序，综合考虑战略、预算和风险。 | BB3: 谁来做信息系统相关的决策，谁来承担责任？ | BC3: 综合考虑项目的战略适用性和实际可行性。 | BD3: 将组织的部分IT功能委托给外部专业公司执行。 | BE3: 安全威胁完全消除，信息安全得到加强。 | BF3: O | BG3: O | BH3: X | BI3: =10*SUMPRODUCT(--(AY3:BH3<>""),--(((AY3:BH3=정답표!$C$10:$L$10)+(AY3:BH3=정답표!$C$11:$L$11))>0)) -> 100 | BJ3: =SUM(Q3,AB3,AM3,AX3,BI3) -> 200 | BK3: =COUNT(Q3,AB3,AM3,AX3,BI3) -> 2 | BL3: =IF(QuizMatchTable[[#This Row],[분반]]=1, QuizMatchTable[[#This Row],[퀴즈합계]]/4 *0.3, QuizMatchTable[[#This Row],[퀴즈합계]]/5*0.3) -> 15 | BM3: 26 | BN3: 19.2 | BP3: =SUM(QuizMatchTable[[#This Row],[퀴즈점수(30)]],BM3,BN3,BO3) -> 60.2 | BQ3: =IF(OR(BP3="",BP3=0,BT3="결석초과"),"",COUNTIFS($B$2:$B$109,B3,$BP$2:$BP$109,">"&BP3)+1) -> 14 | BR3: B0 | BS3: 6
A4: 경영학과 | B4: 1 | C4: 20230421 | D4: 주세남 | E4: 010-8356-9850 | F4: 2488676213@qq.com | R4: BPR | S4: 遵循日常运营的正式化和标准化程序。 | T4: 企业级流程 | U4: 相同数据在多个部门重复存储，导致不一致。 | V4: 引入企业信息系统（EIS） | W4: 减少不必要的审批环节，从而最大限度地减少时间和资源。 | X4: 整合管理与客户的所有互动，最大限度地提高客户终身价值。 | Y4: 将业务运营整合到一个单一且一致的计算平台。 | Z4: O | AA4: O | AB4: =10*SUMPRODUCT(--(R4:AA4<>""),--(((R4:AA4=정답표!$C$4:$L$4)+(R4:AA4=정답표!$C$5:$L$5))>0)) -> 90 | AC4: 硬件、软件、数据、流程、人员 | AD4: 组织战略决定价值链，价值链决定业务流程，业务流程决定 SMIS 需求。 | AE4: 增加物质资本 | AF4: 直接销售用户数据：通过直接销售用户个人数据获取主要收入。 | AG4: 创新 (Innovation) | AH4: 指通过电子邮件、消息应用等难以追踪的渠道进行的社交分享区域，企业应在此处关注建立信任。 | AI4: 基于兴趣形成，一个用户可以同时属于多个社区。 | AJ4: 财务与会计 | AK4: O | AL4: O | AM4: =10*SUMPRODUCT(--(AC4:AL4<>""),--(((AC4:AL4=정답표!$C$6:$L$6)+(AC4:AL4=정답표!$C$7:$L$7))>0)) -> 100 | AY4: 支持IT技术以实现组织目标，并将其与经营目标相结合。 | AZ4: 有效连接信息系统(IS)战略与企业经营战略。 | BA4: 根据组织的目标和优先顺序，综合考虑战略、预算和风险。 | BB4: 谁来做信息系统相关的决策，谁来承担责任？ | BC4: 综合考虑项目的战略适用性和实际可行性。 | BD4: 将组织的部分IT功能委托给外部专业公司执行。 | BE4: 安全威胁完全消除，信息安全得到加强。 | BF4: O | BG4: O | BH4: X | BI4: =10*SUMPRODUCT(--(AY4:BH4<>""),--(((AY4:BH4=정답표!$C$10:$L$10)+(AY4:BH4=정답표!$C$11:$L$11))>0)) -> 100 | BJ4: =SUM(Q4,AB4,AM4,AX4,BI4) -> 290 | BK4: =COUNT(Q4,AB4,AM4,AX4,BI4) -> 3 | BL4: =IF(QuizMatchTable[[#This Row],[분반]]=1, QuizMatchTable[[#This Row],[퀴즈합계]]/4 *0.3, QuizMatchTable[[#This Row],[퀴즈합계]]/5*0.3) -> 21.75 | BM4: 28 | BN4: 18.8 | BP4: =SUM(QuizMatchTable[[#This Row],[퀴즈점수(30)]],BM4,BN4,BO4) -> 68.55 | BQ4: =IF(OR(BP4="",BP4=0,BT4="결석초과"),"",COUNTIFS($B$2:$B$109,B4,$BP$2:$BP$109,">"&BP4)+1) -> 6 | BR4: A0 | BS4: 3
A5: 경영학과 | B5: 1 | C5: 20230422 | D5: 쩐응옥휘 | E5: 010-5727-3028 | F5: huytranngoc1201@gmail.com | G5: B. 피드백 및 반복 (反馈和迭代) | H5: D. 최소한의 비용과 시간 소모 (最低限度的成本和时间消耗) | I5: C. 운영적 의사결정 (运营性决策) | J5: C. 마케팅 전략 (营销策略) | K5: C. 문제해결 (问题解决) | L5: C. 착수 → 계획 → 실행 → 마무리 (启动 → 计划 → 执行 → 结束) | M5: A. 프로젝트 콘텐츠 (项目内容/产出物), B. 프로젝트 메타데이터 (项目元数据) | N5: B. 비동기적 소통 (Asynchronous Communication / 异步沟通) | O5: X (거짓/错) | P5: O (참/对) | Q5: =10*SUMPRODUCT(--(G5:P5<>""),--(((G5:P5=정답표!$C$2:$L$2)+(G5:P5=정답표!$C$3:$L$3))>0)) -> 100 | R5: BPR | S5: 일상적인 운영을 위한 공식적이고 표준화된 절차를 따릅니다. | T5: 기업 간 프로세스 | U5: 동일한 데이터가 여러 부서에 중복 저장되어 불일치가 발생합니다. | V5: 전사적 정보시스템(EIS) 도입 | W5: 불필요한 승인 단계를 축소하여 시간과 자원을 최소화합니다. | X5: 고객과의 모든 상호작용을 통합 관리하여 고객 평생 가치를 극대화하는 것입니다. | Y5: 비즈니스 운영을 단일하고 일관된 컴퓨팅 플랫폼에 통합하는 것입니다. | Z5: O | AA5: O | AB5: =10*SUMPRODUCT(--(R5:AA5<>""),--(((R5:AA5=정답표!$C$4:$L$4)+(R5:AA5=정답표!$C$5:$L$5))>0)) -> 100 | AC5: 하드웨어,소프트웨어,데이터,절차,사람 | AD5: 조직 전략이 가치 사슬을 결정하고, 가치 사슬은 비즈니스 프로세스를, 프로세스는 SMIS 요구 사항을 결정합니다. | AE5: 물적 자본 증대 | AF5: 사용자 데이터 직접 판매: 사용자의 개인 데이터를 직접 판매하여 주된 수익을 얻습니다. | AG5: 혁신 (Innovation) | AH5: 이메일, 메시징 앱 등 추적하기 어려운 채널을 통한 소셜 공유 영역을 의미하며, 비즈니스는 여기서 신뢰 구축에 주목해야 합니다. | AI5: 관심사 기반으로 형성되며, 한 명의 사용자가 여러 커뮤니티에 동시 소속될 수 있습니다. | AJ5: 제조 및 운영 | AK5: O | AL5: O | AM5: =10*SUMPRODUCT(--(AC5:AL5<>""),--(((AC5:AL5=정답표!$C$6:$L$6)+(AC5:AL5=정답표!$C$7:$L$7))>0)) -> 90 | AY5: 조직의 목표 달성을 위해 IT 기술을 지원하고 경영 목표와 연결한다. | AZ5: 정보시스템(IS) 전략과 기업의 경영전략을 효과적으로 연결한다. | BA5: 조직의 목표와 우선순위에 맞춰 전략, 예산, 위험을 함께 고려한다. | BB5: 정보시스템 관련 의사결정을 누가 하고 그에 대한 책임은 누가 지는가? | BC5: 프로젝트의 전략적 적합성과 실제 실행 가능성을 종합적으로 고려한다. | BD5: 조직의 일부 IT 기능을 외부 전문 업체에 위탁하여 수행하게 하는 것이다. | BE5: 보안 위협이 완전히 제거되어 정보 보안이 강화된다. | BF5: O | BG5: O | BH5: X | BI5: =10*SUMPRODUCT(--(AY5:BH5<>""),--(((AY5:BH5=정답표!$C$10:$L$10)+(AY5:BH5=정답표!$C$11:$L$11))>0)) -> 100 | BJ5: =SUM(Q5,AB5,AM5,AX5,BI5) -> 390 | BK5: =COUNT(Q5,AB5,AM5,AX5,BI5) -> 4 | BL5: =IF(QuizMatchTable[[#This Row],[분반]]=1, QuizMatchTable[[#This Row],[퀴즈합계]]/4 *0.3, QuizMatchTable[[#This Row],[퀴즈합계]]/5*0.3) -> 29.25 | BM5: 30 | BN5: 13.2 | BP5: =SUM(QuizMatchTable[[#This Row],[퀴즈점수(30)]],BM5,BN5,BO5) -> 72.45 | BQ5: =IF(OR(BP5="",BP5=0,BT5="결석초과"),"",COUNTIFS($B$2:$B$109,B5,$BP$2:$BP$109,">"&BP5)+1) -> 4 | BR5: A+ | BS5: 0
A6: 경영학과 | B6: 1 | C6: 20230474 | D6: 조동령 | E6: 010-7714-8195 | F6: zdy2002dd@163.com | G6: B. 피드백 및 반복 (反馈和迭代) | H6: D. 최소한의 비용과 시간 소모 (最低限度的成本和时间消耗) | I6: C. 운영적 의사결정 (运营性决策) | J6: C. 마케팅 전략 (营销策略) | K6: C. 문제해결 (问题解决) | L6: C. 착수 → 계획 → 실행 → 마무리 (启动 → 计划 → 执行 → 结束) | M6: A. 프로젝트 콘텐츠 (项目内容/产出物) | N6: B. 비동기적 소통 (Asynchronous Communication / 异步沟通) | O6: X (거짓/错) | P6: O (참/对) | Q6: =10*SUMPRODUCT(--(G6:P6<>""),--(((G6:P6=정답표!$C$2:$L$2)+(G6:P6=정답표!$C$3:$L$3))>0)) -> 90 | R6: BPR | S6: 遵循日常运营的正式化和标准化程序。 | T6: 企业间流程 | U6: 相同数据在多个部门重复存储，导致不一致。 | V6: 引入企业信息系统（EIS） | W6: 减少不必要的审批环节，从而最大限度地减少时间和资源。 | X6: 整合管理与客户的所有互动，最大限度地提高客户终身价值。 | Y6: 实现现有分离系统之间的数据共享和通信。 | Z6: O | AA6: O | AB6: =10*SUMPRODUCT(--(R6:AA6<>""),--(((R6:AA6=정답표!$C$4:$L$4)+(R6:AA6=정답표!$C$5:$L$5))>0)) -> 90 | AC6: 硬件、软件、数据、流程、人员 | AD6: 组织战略决定价值链，价值链决定业务流程，业务流程决定 SMIS 需求。 | AE6: 增加物质资本 | AF6: 直接销售用户数据：通过直接销售用户个人数据获取主要收入。 | AG6: 创新 (Innovation) | AH6: 指通过电子邮件、消息应用等难以追踪的渠道进行的社交分享区域，企业应在此处关注建立信任。 | AI6: 基于兴趣形成，一个用户可以同时属于多个社区。 | AJ6: 财务与会计 | AK6: O | AL6: X | AM6: =10*SUMPRODUCT(--(AC6:AL6<>""),--(((AC6:AL6=정답표!$C$6:$L$6)+(AC6:AL6=정답표!$C$7:$L$7))>0)) -> 90 | AY6: 支持IT技术以实现组织目标，并将其与经营目标相结合。 | AZ6: 有效连接信息系统(IS)战略与企业经营战略。 | BA6: 根据组织的目标和优先顺序，综合考虑战略、预算和风险。 | BB6: 谁来做信息系统相关的决策，谁来承担责任？ | BC6: 综合考虑项目的战略适用性和实际可行性。 | BD6: 将组织的部分IT功能委托给外部专业公司执行。 | BE6: 安全威胁完全消除，信息安全得到加强。 | BF6: O | BG6: O | BH6: X | BI6: =10*SUMPRODUCT(--(AY6:BH6<>""),--(((AY6:BH6=정답표!$C$10:$L$10)+(AY6:BH6=정답표!$C$11:$L$11))>0)) -> 100 | BJ6: =SUM(Q6,AB6,AM6,AX6,BI6) -> 370 | BK6: =COUNT(Q6,AB6,AM6,AX6,BI6) -> 4 | BL6: =IF(QuizMatchTable[[#This Row],[분반]]=1, QuizMatchTable[[#This Row],[퀴즈합계]]/4 *0.3, QuizMatchTable[[#This Row],[퀴즈합계]]/5*0.3) -> 27.75 | BM6: 30 | BN6: 16 | BP6: =SUM(QuizMatchTable[[#This Row],[퀴즈점수(30)]],BM6,BN6,BO6) -> 73.75 | BQ6: =IF(OR(BP6="",BP6=0,BT6="결석초과"),"",COUNTIFS($B$2:$B$109,B6,$BP$2:$BP$109,">"&BP6)+1) -> 3 | BR6: A+ | BS6: 0
A7: 경영학과 | B7: 1 | C7: 20240033 | D7: 양우철 | E7: 010-5781-9370 | F7: snowly2408620437@163.com | G7: B. 피드백 및 반복 (反馈和迭代) | H7: D. 최소한의 비용과 시간 소모 (最低限度的成本和时间消耗) | I7: C. 운영적 의사결정 (运营性决策) | J7: C. 마케팅 전략 (营销策略) | K7: C. 문제해결 (问题解决) | L7: C. 착수 → 계획 → 실행 → 마무리 (启动 → 计划 → 执行 → 结束) | M7: A. 프로젝트 콘텐츠 (项目内容/产出物), B. 프로젝트 메타데이터 (项目元数据) | N7: B. 비동기적 소통 (Asynchronous Communication / 异步沟通) | O7: X (거짓/错) | P7: O (참/对) | Q7: =10*SUMPRODUCT(--(G7:P7<>""),--(((G7:P7=정답표!$C$2:$L$2)+(G7:P7=정답표!$C$3:$L$3))>0)) -> 100 | R7: BPR | S7: 遵循日常运营的正式化和标准化程序。 | T7: 企业间流程 | U7: 相同数据在多个部门重复存储，导致不一致。 | V7: 引入企业信息系统（EIS） | W7: 减少不必要的审批环节，从而最大限度地减少时间和资源。 | X7: 整合管理与客户的所有互动，最大限度地提高客户终身价值。 | Y7: 将业务运营整合到一个单一且一致的计算平台。 | Z7: O | AA7: O | AB7: =10*SUMPRODUCT(--(R7:AA7<>""),--(((R7:AA7=정답표!$C$4:$L$4)+(R7:AA7=정답표!$C$5:$L$5))>0)) -> 100 | AC7: 硬件、软件、数据、流程、人员 | AD7: 组织战略决定价值链，价值链决定业务流程，业务流程决定 SMIS 需求。 | AE7: 增加物质资本 | AF7: 直接销售用户数据：通过直接销售用户个人数据获取主要收入。 | AG7: 创新 (Innovation) | AH7: 指通过电子邮件、消息应用等难以追踪的渠道进行的社交分享区域，企业应在此处关注建立信任。 | AI7: 基于兴趣形成，一个用户可以同时属于多个社区。 | AJ7: 财务与会计 | AK7: O | AL7: O | AM7: =10*SUMPRODUCT(--(AC7:AL7<>""),--(((AC7:AL7=정답표!$C$6:$L$6)+(AC7:AL7=정답표!$C$7:$L$7))>0)) -> 100 | AY7: 支持IT技术以实现组织目标，并将其与经营目标相结合。 | AZ7: 有效连接信息系统(IS)战略与企业经营战略。 | BA7: 根据组织的目标和优先顺序，综合考虑战略、预算和风险。 | BB7: 谁来做信息系统相关的决策，谁来承担责任？ | BC7: 综合考虑项目的战略适用性和实际可行性。 | BD7: 将组织的部分IT功能委托给外部专业公司执行。 | BE7: 安全威胁完全消除，信息安全得到加强。 | BF7: O | BG7: O | BH7: X | BI7: =10*SUMPRODUCT(--(AY7:BH7<>""),--(((AY7:BH7=정답표!$C$10:$L$10)+(AY7:BH7=정답표!$C$11:$L$11))>0)) -> 100 | BJ7: =SUM(Q7,AB7,AM7,AX7,BI7) -> 400 | BK7: =COUNT(Q7,AB7,AM7,AX7,BI7) -> 4 | BL7: =IF(QuizMatchTable[[#This Row],[분반]]=1, QuizMatchTable[[#This Row],[퀴즈합계]]/4 *0.3, QuizMatchTable[[#This Row],[퀴즈합계]]/5*0.3) -> 30 | BM7: 30 | BN7: 18.39 | BP7: =SUM(QuizMatchTable[[#This Row],[퀴즈점수(30)]],BM7,BN7,BO7) -> 78.39 | BQ7: =IF(OR(BP7="",BP7=0,BT7="결석초과"),"",COUNTIFS($B$2:$B$109,B7,$BP$2:$BP$109,">"&BP7)+1) -> 1 | BR7: A+ | BS7: 0
A8: 경영학과 | B8: 1 | C8: 20240665 | D8: 김재환 | E8: 010-3493-7130 | F8: kjhflg@hanmail.net | BL8: =IF(QuizMatchTable[[#This Row],[분반]]=1, QuizMatchTable[[#This Row],[퀴즈합계]]/4 *0.3, QuizMatchTable[[#This Row],[퀴즈합계]]/5*0.3) -> 0 | BM8: 22 | BN8: 18 | BP8: =SUM(QuizMatchTable[[#This Row],[퀴즈점수(30)]],BM8,BN8,BO8) -> 40 | BQ8: =IF(OR(BP8="",BP8=0,BT8="결석초과"),"",COUNTIFS($B$2:$B$109,B8,$BP$2:$BP$109,">"&BP8)+1) -> 19 | BR8: F | BS8: 12
A9: 경영학과 | B9: 1 | C9: 20240666 | D9: 김준환 | E9: 010-8602-1022 | BL9: =IF(QuizMatchTable[[#This Row],[분반]]=1, QuizMatchTable[[#This Row],[퀴즈합계]]/4 *0.3, QuizMatchTable[[#This Row],[퀴즈합계]]/5*0.3) -> 0 | BM9: 0 | BN9: 0 | BP9: =SUM(QuizMatchTable[[#This Row],[퀴즈점수(30)]],BM9,BN9,BO9) -> 0 | BQ9: =IF(OR(BP9="",BP9=0,BT9="결석초과"),"",COUNTIFS($B$2:$B$109,B9,$BP$2:$BP$109,">"&BP9)+1) | BR9: F | BS9: 36 | BT9: 결석초과
A10: 경영학과 | B10: 1 | C10: 20240667 | D10: 송진근 | E10: 010-2509-0173 | F10: song110746@naver.com | R10: BPR | S10: 조직의 변화에 따라 프로세스 구조가 신속하게 적응하고 변경됩니다. | T10: 구조적 프로세스 | U10: 각 부서의 시스템 개발 비용이 절감됩니다. | V10: 전사적 정보시스템(EIS) 도입 | W10: 불필요한 승인 단계를 축소하여 시간과 자원을 최소화합니다. | X10: 고객과의 모든 상호작용을 통합 관리하여 고객 평생 가치를 극대화하는 것입니다. | Y10: 특정 작업 그룹이나 단일 부서의 업무 프로세스를 자동화하는 것입니다. | Z10: O | AA10: O | AB10: =10*SUMPRODUCT(--(R10:AA10<>""),--(((R10:AA10=정답표!$C$4:$L$4)+(R10:AA10=정답표!$C$5:$L$5))>0)) -> 60 | AC10: 하드웨어,소프트웨어,데이터,절차,사람 | AD10: SMIS 요구 사항이 먼저 결정되고, 이는 가치 사슬과 조직 전략에 영향을 미칩니다. | AE10: 개인적 강화 | AF10: 사용자 데이터 직접 판매: 사용자의 개인 데이터를 직접 판매하여 주된 수익을 얻습니다. | AG10: 혁신 (Innovation) | AH10: 인공지능(AI)이 생성한 가짜 뉴스나 딥페이크 콘텐츠가 확산되는 소셜 미디어의 어두운 면을 지칭합니다. | AI10: 관심사 기반으로 형성되며, 한 명의 사용자가 여러 커뮤니티에 동시 소속될 수 있습니다. | AJ10: 재무 및 회계 | AK10: O | AL10: O | AM10: =10*SUMPRODUCT(--(AC10:AL10<>""),--(((AC10:AL10=정답표!$C$6:$L$6)+(AC10:AL10=정답표!$C$7:$L$7))>0)) -> 70 | AY10: 조직의 목표 달성을 위해 IT 기술을 지원하고 경영 목표와 연결한다. | AZ10: 정보시스템(IS) 전략과 기업의 경영전략을 효과적으로 연결한다. | BA10: 조직의 목표와 우선순위에 맞춰 전략, 예산, 위험을 함께 고려한다. | BB10: 정보시스템 관련 의사결정을 누가 하고 그에 대한 책임은 누가 지는가? | BC10: 프로젝트의 전략적 적합성과 실제 실행 가능성을 종합적으로 고려한다. | BD10: 조직의 일부 IT 기능을 외부 전문 업체에 위탁하여 수행하게 하는 것이다. | BE10: 예상보다 장기적인 관점에서 더 높은 비용이 발생할 수 있다. | BF10: O | BG10: O | BH10: X | BI10: =10*SUMPRODUCT(--(AY10:BH10<>""),--(((AY10:BH10=정답표!$C$10:$L$10)+(AY10:BH10=정답표!$C$11:$L$11))>0)) -> 90 | BJ10: =SUM(Q10,AB10,AM10,AX10,BI10) -> 220 | BK10: =COUNT(Q10,AB10,AM10,AX10,BI10) -> 3 | BL10: =IF(QuizMatchTable[[#This Row],[분반]]=1, QuizMatchTable[[#This Row],[퀴즈합계]]/4 *0.3, QuizMatchTable[[#This Row],[퀴즈합계]]/5*0.3) -> 16.5 | BM10: 30 | BN10: 5.2 | BP10: =SUM(QuizMatchTable[[#This Row],[퀴즈점수(30)]],BM10,BN10,BO10) -> 51.7 | BQ10: =IF(OR(BP10="",BP10=0,BT10="결석초과"),"",COUNTIFS($B$2:$B$109,B10,$BP$2:$BP$109,">"&BP10)+1) -> 18 | BR10: F | BS10: 0
A11: 경영학과 | B11: 1 | C11: 20240812 | D11: 응옌 티 쑤언 꾸인 | E11: 010-5948-6027 | F11: xquynh2706@gmail.com | R11: BPR | S11: 일상적인 운영을 위한 공식적이고 표준화된 절차를 따릅니다. | T11: 기업 간 프로세스 | U11: 동일한 데이터가 여러 부서에 중복 저장되어 불일치가 발생합니다. | V11: 전사적 정보시스템(EIS) 도입 | W11: 불필요한 승인 단계를 축소하여 시간과 자원을 최소화합니다. | X11: 고객과의 모든 상호작용을 통합 관리하여 고객 평생 가치를 극대화하는 것입니다. | Y11: 비즈니스 운영을 단일하고 일관된 컴퓨팅 플랫폼에 통합하는 것입니다. | Z11: O | AA11: O | AB11: =10*SUMPRODUCT(--(R11:AA11<>""),--(((R11:AA11=정답표!$C$4:$L$4)+(R11:AA11=정답표!$C$5:$L$5))>0)) -> 100 | AC11: 하드웨어,소프트웨어,커뮤니티,절차,사람 | AD11: 조직 전략이 가치 사슬을 결정하고, 가치 사슬은 비즈니스 프로세스를, 프로세스는 SMIS 요구 사항을 결정합니다. | AE11: 물적 자본 증대 | AF11: 사용자 데이터 직접 판매: 사용자의 개인 데이터를 직접 판매하여 주된 수익을 얻습니다. | AG11: 혁신 (Innovation) | AH11: 이메일, 메시징 앱 등 추적하기 어려운 채널을 통한 소셜 공유 영역을 의미하며, 비즈니스는 여기서 신뢰 구축에 주목해야 합니다. | AI11: 관심사 기반으로 형성되며, 한 명의 사용자가 여러 커뮤니티에 동시 소속될 수 있습니다. | AJ11: 재무 및 회계 | AK11: O | AL11: O | AM11: =10*SUMPRODUCT(--(AC11:AL11<>""),--(((AC11:AL11=정답표!$C$6:$L$6)+(AC11:AL11=정답표!$C$7:$L$7))>0)) -> 90 | AY11: 조직의 목표 달성을 위해 IT 기술을 지원하고 경영 목표와 연결한다. | AZ11: 정보시스템(IS) 전략과 기업의 경영전략을 효과적으로 연결한다. | BA11: 조직의 목표와 우선순위에 맞춰 전략, 예산, 위험을 함께 고려한다. | BB11: 정보시스템 관련 의사결정을 누가 하고 그에 대한 책임은 누가 지는가? | BC11: 프로젝트의 전략적 적합성과 실제 실행 가능성을 종합적으로 고려한다. | BD11: 조직의 일부 IT 기능을 외부 전문 업체에 위탁하여 수행하게 하는 것이다. | BE11: 보안 위협이 완전히 제거되어 정보 보안이 강화된다. | BF11: O | BG11: O | BH11: X | BI11: =10*SUMPRODUCT(--(AY11:BH11<>""),--(((AY11:BH11=정답표!$C$10:$L$10)+(AY11:BH11=정답표!$C$11:$L$11))>0)) -> 100 | BJ11: =SUM(Q11,AB11,AM11,AX11,BI11) -> 290 | BK11: =COUNT(Q11,AB11,AM11,AX11,BI11) -> 3 | BL11: =IF(QuizMatchTable[[#This Row],[분반]]=1, QuizMatchTable[[#This Row],[퀴즈합계]]/4 *0.3, QuizMatchTable[[#This Row],[퀴즈합계]]/5*0.3) -> 21.75 | BM11: 26 | BN11: 19.6 | BP11: =SUM(QuizMatchTable[[#This Row],[퀴즈점수(30)]],BM11,BN11,BO11) -> 67.35 | BQ11: =IF(OR(BP11="",BP11=0,BT11="결석초과"),"",COUNTIFS($B$2:$B$109,B11,$BP$2:$BP$109,">"&BP11)+1) -> 9 | BR11: B+ | BS11: 6
A12: 경영학과 | B12: 1 | C12: 20250935 | D12: 김가민 | E12: 010-4389-0603 | F12: kimgamin0603@gmail.com | AC12: 콘텐츠, 플랫폼, 네트워크,가치사슬,하드웨어 | AD12: 조직 전략이 가치 사슬을 결정하고, 가치 사슬은 비즈니스 프로세스를, 프로세스는 SMIS 요구 사항을 결정합니다. | AE12: 물적 자본 증대 | AF12: 프리미엄 (Freemium): 기본 서비스는 무료로 제공하고, 고급 기능이나 광고 제거에 비용을 부과합니다. | AG12: 투명성 (Disclosure) | AH12: 인공지능(AI)이 생성한 가짜 뉴스나 딥페이크 콘텐츠가 확산되는 소셜 미디어의 어두운 면을 지칭합니다. | AI12: 관심사 기반으로 형성되며, 한 명의 사용자가 여러 커뮤니티에 동시 소속될 수 있습니다. | AJ12: 고객 서비스 | AK12: X | AL12: O | AM12: =10*SUMPRODUCT(--(AC12:AL12<>""),--(((AC12:AL12=정답표!$C$6:$L$6)+(AC12:AL12=정답표!$C$7:$L$7))>0)) -> 40 | BJ12: =SUM(Q12,AB12,AM12,AX12,BI12) -> 40 | BK12: =COUNT(Q12,AB12,AM12,AX12,BI12) -> 1 | BL12: =IF(QuizMatchTable[[#This Row],[분반]]=1, QuizMatchTable[[#This Row],[퀴즈합계]]/4 *0.3, QuizMatchTable[[#This Row],[퀴즈합계]]/5*0.3) -> 3 | BM12: 24 | BN12: 8 | BP12: =SUM(QuizMatchTable[[#This Row],[퀴즈점수(30)]],BM12,BN12,BO12) -> 35 | BQ12: =IF(OR(BP12="",BP12=0,BT12="결석초과"),"",COUNTIFS($B$2:$B$109,B12,$BP$2:$BP$109,">"&BP12)+1) -> 20 | BR12: F | BS12: 9
A13: 경영학과 | B13: 1 | C13: 20250936 | D13: 김상민 | E13: 010-9868-3163 | F13: qlsdlsla4@gmail.com | G13: B. 피드백 및 반복 (反馈和迭代) | H13: D. 최소한의 비용과 시간 소모 (最低限度的成本和时间消耗) | I13: C. 운영적 의사결정 (运营性决策) | J13: C. 마케팅 전략 (营销策略) | K13: C. 문제해결 (问题解决) | L13: C. 착수 → 계획 → 실행 → 마무리 (启动 → 计划 → 执行 → 结束) | M13: A. 프로젝트 콘텐츠 (项目内容/产出物), B. 프로젝트 메타데이터 (项目元数据) | N13: B. 비동기적 소통 (Asynchronous Communication / 异步沟通) | O13: X (거짓/错) | P13: O (참/对) | Q13: =10*SUMPRODUCT(--(G13:P13<>""),--(((G13:P13=정답표!$C$2:$L$2)+(G13:P13=정답표!$C$3:$L$3))>0)) -> 100 | R13: BPR | S13: 일상적인 운영을 위한 공식적이고 표준화된 절차를 따릅니다. | T13: 기업 간 프로세스 | U13: 동일한 데이터가 여러 부서에 중복 저장되어 불일치가 발생합니다. | V13: 전사적 정보시스템(EIS) 도입 | W13: 불필요한 승인 단계를 축소하여 시간과 자원을 최소화합니다. | X13: 고객과의 모든 상호작용을 통합 관리하여 고객 평생 가치를 극대화하는 것입니다. | Y13: 비즈니스 운영을 단일하고 일관된 컴퓨팅 플랫폼에 통합하는 것입니다. | Z13: O | AA13: O | AB13: =10*SUMPRODUCT(--(R13:AA13<>""),--(((R13:AA13=정답표!$C$4:$L$4)+(R13:AA13=정답표!$C$5:$L$5))>0)) -> 100 | AY13: 조직의 목표 달성을 위해 IT 기술을 지원하고 경영 목표와 연결한다. | AZ13: 정보시스템(IS) 전략과 기업의 경영전략을 효과적으로 연결한다. | BA13: 조직의 목표와 우선순위에 맞춰 전략, 예산, 위험을 함께 고려한다. | BB13: 정보시스템 관련 의사결정을 누가 하고 그에 대한 책임은 누가 지는가? | BC13: 프로젝트의 전략적 적합성과 실제 실행 가능성을 종합적으로 고려한다. | BD13: 조직의 일부 IT 기능을 외부 전문 업체에 위탁하여 수행하게 하는 것이다. | BE13: 보안 위협이 완전히 제거되어 정보 보안이 강화된다. | BF13: O | BG13: O | BH13: X | BI13: =10*SUMPRODUCT(--(AY13:BH13<>""),--(((AY13:BH13=정답표!$C$10:$L$10)+(AY13:BH13=정답표!$C$11:$L$11))>0)) -> 100 | BJ13: =SUM(Q13,AB13,AM13,AX13,BI13) -> 300 | BK13: =COUNT(Q13,AB13,AM13,AX13,BI13) -> 3 | BL13: =IF(QuizMatchTable[[#This Row],[분반]]=1, QuizMatchTable[[#This Row],[퀴즈합계]]/4 *0.3, QuizMatchTable[[#This Row],[퀴즈합계]]/5*0.3) -> 22.5 | BM13: 26 | BN13: 20 | BP13: =SUM(QuizMatchTable[[#This Row],[퀴즈점수(30)]],BM13,BN13,BO13) -> 68.5 | BQ13: =IF(OR(BP13="",BP13=0,BT13="결석초과"),"",COUNTIFS($B$2:$B$109,B13,$BP$2:$BP$109,">"&BP13)+1) -> 7 | BR13: A0 | BS13: 6
A14: 경영학과 | B14: 1 | C14: 20250939 | D14: 이동윤 | E14: 010-3429-1571 | G14: B. 피드백 및 반복 (反馈和迭代) | H14: D. 최소한의 비용과 시간 소모 (最低限度的成本和时间消耗) | I14: C. 운영적 의사결정 (运营性决策) | J14: C. 마케팅 전략 (营销策略) | K14: C. 문제해결 (问题解决) | L14: C. 착수 → 계획 → 실행 → 마무리 (启动 → 计划 → 执行 → 结束) | M14: A. 프로젝트 콘텐츠 (项目内容/产出物), B. 프로젝트 메타데이터 (项目元数据) | N14: B. 비동기적 소통 (Asynchronous Communication / 异步沟通) | O14: X (거짓/错) | P14: O (참/对) | Q14: =10*SUMPRODUCT(--(G14:P14<>""),--(((G14:P14=정답표!$C$2:$L$2)+(G14:P14=정답표!$C$3:$L$3))>0)) -> 100 | R14: BPR | S14: 일상적인 운영을 위한 공식적이고 표준화된 절차를 따릅니다. | T14: 기업 간 프로세스 | U14: 동일한 데이터가 여러 부서에 중복 저장되어 불일치가 발생합니다. | V14: 전사적 정보시스템(EIS) 도입 | W14: 불필요한 승인 단계를 축소하여 시간과 자원을 최소화합니다. | X14: 고객과의 모든 상호작용을 통합 관리하여 고객 평생 가치를 극대화하는 것입니다. | Y14: 비즈니스 운영을 단일하고 일관된 컴퓨팅 플랫폼에 통합하는 것입니다. | Z14: O | AA14: O | AB14: =10*SUMPRODUCT(--(R14:AA14<>""),--(((R14:AA14=정답표!$C$4:$L$4)+(R14:AA14=정답표!$C$5:$L$5))>0)) -> 100 | AC14: 하드웨어,소프트웨어,커뮤니티,절차,사람 | AD14: 조직 전략이 가치 사슬을 결정하고, 가치 사슬은 비즈니스 프로세스를, 프로세스는 SMIS 요구 사항을 결정합니다. | AE14: 물적 자본 증대 | AF14: 사용자 데이터 직접 판매: 사용자의 개인 데이터를 직접 판매하여 주된 수익을 얻습니다. | AG14: 혁신 (Innovation) | AH14: 이메일, 메시징 앱 등 추적하기 어려운 채널을 통한 소셜 공유 영역을 의미하며, 비즈니스는 여기서 신뢰 구축에 주목해야 합니다. | AI14: 관심사 기반으로 형성되며, 한 명의 사용자가 여러 커뮤니티에 동시 소속될 수 있습니다. | AJ14: 재무 및 회계 | AK14: O | AL14: O | AM14: =10*SUMPRODUCT(--(AC14:AL14<>""),--(((AC14:AL14=정답표!$C$6:$L$6)+(AC14:AL14=정답표!$C$7:$L$7))>0)) -> 90 | BJ14: =SUM(Q14,AB14,AM14,AX14,BI14) -> 290 | BK14: =COUNT(Q14,AB14,AM14,AX14,BI14) -> 3 | BL14: =IF(QuizMatchTable[[#This Row],[분반]]=1, QuizMatchTable[[#This Row],[퀴즈합계]]/4 *0.3, QuizMatchTable[[#This Row],[퀴즈합계]]/5*0.3) -> 21.75 | BM14: 22 | BN14: 15.2 | BP14: =SUM(QuizMatchTable[[#This Row],[퀴즈점수(30)]],BM14,BN14,BO14) -> 58.95 | BQ14: =IF(OR(BP14="",BP14=0,BT14="결석초과"),"",COUNTIFS($B$2:$B$109,B14,$BP$2:$BP$109,">"&BP14)+1) -> 15 | BR14: B0 | BS14: 12
A15: 경영학과 | B15: 1 | C15: 20250940 | D15: 이성민 | E15: 010-2430-7874 | F15: zxcv4408@naver.com | G15: B. 피드백 및 반복 (反馈和迭代) | H15: C. 의미 있고 만족스러운 경험 (有意义且令人满意的经验) | I15: D. 비구조적 의사결정 (非结构性决策) | J15: A. 하드웨어 (硬件) | K15: C. 문제해결 (问题解决) | L15: B. 실행 → 계획 → 마무리 → 착수 (执行 → 计划 → 结束 → 启动) | M15: D. 팀원들의 개인정보 (团队成员的个人信息) | N15: A. 동기적 소통 (Synchronous Communication / 同步沟通) | O15: O (참/对) | P15: X (거짓/错) | Q15: =10*SUMPRODUCT(--(G15:P15<>""),--(((G15:P15=정답표!$C$2:$L$2)+(G15:P15=정답표!$C$3:$L$3))>0)) -> 20 | R15: CRM | S15: 일상적인 운영을 위한 공식적이고 표준화된 절차를 따릅니다. | T15: 구조적 프로세스 | U15: 각 부서의 시스템 개발 비용이 절감됩니다. | V15: 부서별 독립적인 시스템 유지 | W15: 신제품 출시 기간(TTM)을 단축하여 시장 경쟁력을 확보합니다. | X15: 공급망 파트너사와의 협업을 강화하여 물류 효율성을 높이는 것입니다. | Y15: 비즈니스 운영을 단일하고 일관된 컴퓨팅 플랫폼에 통합하는 것입니다. | Z15: O | AA15: X | AB15: =10*SUMPRODUCT(--(R15:AA15<>""),--(((R15:AA15=정답표!$C$4:$L$4)+(R15:AA15=정답표!$C$5:$L$5))>0)) -> 30 | AC15: 콘텐츠, 플랫폼, 네트워크,가치사슬,하드웨어 | AD15: SMIS 요구 사항이 먼저 결정되고, 이는 가치 사슬과 조직 전략에 영향을 미칩니다. | AE15: 물적 자본 증대 | AF15: 프리미엄 (Freemium): 기본 서비스는 무료로 제공하고, 고급 기능이나 광고 제거에 비용을 부과합니다. | AG15: 상식 (Common Sense) | AH15: 인공지능(AI)이 생성한 가짜 뉴스나 딥페이크 콘텐츠가 확산되는 소셜 미디어의 어두운 면을 지칭합니다. | AI15: 정보의 확산이 느리고, 주로 소수의 리더에 의해 통제되는 경향이 있습니다. | AJ15: 판매 및 마케팅 | AK15: O | AL15: X | AM15: =10*SUMPRODUCT(--(AC15:AL15<>""),--(((AC15:AL15=정답표!$C$6:$L$6)+(AC15:AL15=정답표!$C$7:$L$7))>0)) -> 20 | AY15: 기업의 회계 및 재무 자료만을 전문적으로 관리하고 보고한다. | AZ15: 기업의 영업 활동을 직접적으로 수행하고 성과를 창출한다. | BA15: 모든 업무 기능을 외부 전문 업체에 위탁하는 방안을 고려한다. | BB15: 정보시스템 관련 의사결정을 누가 하고 그에 대한 책임은 누가 지는가? | BC15: 프로젝트 이름의 인지도나 대외적인 홍보 효과를 중요하게 판단한다. | BD15: 조직의 일부 IT 기능을 외부 전문 업체에 위탁하여 수행하게 하는 것이다. | BE15: 보안 위협이 완전히 제거되어 정보 보안이 강화된다. | BF15: O | BG15: X | BH15: O | BI15: =10*SUMPRODUCT(--(AY15:BH15<>""),--(((AY15:BH15=정답표!$C$10:$L$10)+(AY15:BH15=정답표!$C$11:$L$11))>0)) -> 40 | BJ15: =SUM(Q15,AB15,AM15,AX15,BI15) -> 110 | BK15: =COUNT(Q15,AB15,AM15,AX15,BI15) -> 4 | BL15: =IF(QuizMatchTable[[#This Row],[분반]]=1, QuizMatchTable[[#This Row],[퀴즈합계]]/4 *0.3, QuizMatchTable[[#This Row],[퀴즈합계]]/5*0.3) -> 8.25 | BM15: 28 | BN15: 19.2 | BP15: =SUM(QuizMatchTable[[#This Row],[퀴즈점수(30)]],BM15,BN15,BO15) -> 55.45 | BQ15: =IF(OR(BP15="",BP15=0,BT15="결석초과"),"",COUNTIFS($B$2:$B$109,B15,$BP$2:$BP$109,">"&BP15)+1) -> 17 | BR15: F | BS15: 3
A16: 경영학과 | B16: 1 | C16: 20250944 | D16: 정유은 | E16: 010-3581-7557 | F16: yueun917@gmail.com | G16: B. 피드백 및 반복 (反馈和迭代) | H16: D. 최소한의 비용과 시간 소모 (最低限度的成本和时间消耗) | I16: C. 운영적 의사결정 (运营性决策) | J16: C. 마케팅 전략 (营销策略) | K16: C. 문제해결 (问题解决) | L16: C. 착수 → 계획 → 실행 → 마무리 (启动 → 计划 → 执行 → 结束) | M16: A. 프로젝트 콘텐츠 (项目内容/产出物), B. 프로젝트 메타데이터 (项目元数据) | N16: B. 비동기적 소통 (Asynchronous Communication / 异步沟通) | O16: X (거짓/错) | P16: O (참/对) | Q16: =10*SUMPRODUCT(--(G16:P16<>""),--(((G16:P16=정답표!$C$2:$L$2)+(G16:P16=정답표!$C$3:$L$3))>0)) -> 100 | R16: BPR | S16: 일상적인 운영을 위한 공식적이고 표준화된 절차를 따릅니다. | T16: 기업 간 프로세스 | U16: 동일한 데이터가 여러 부서에 중복 저장되어 불일치가 발생합니다. | V16: 전사적 정보시스템(EIS) 도입 | W16: 불필요한 승인 단계를 축소하여 시간과 자원을 최소화합니다. | X16: 고객과의 모든 상호작용을 통합 관리하여 고객 평생 가치를 극대화하는 것입니다. | Y16: 비즈니스 운영을 단일하고 일관된 컴퓨팅 플랫폼에 통합하는 것입니다. | Z16: O | AA16: O | AB16: =10*SUMPRODUCT(--(R16:AA16<>""),--(((R16:AA16=정답표!$C$4:$L$4)+(R16:AA16=정답표!$C$5:$L$5))>0)) -> 100 | AC16: 하드웨어,소프트웨어,데이터,절차,사람 | AD16: 조직 전략이 가치 사슬을 결정하고, 가치 사슬은 비즈니스 프로세스를, 프로세스는 SMIS 요구 사항을 결정합니다. | AE16: 물적 자본 증대 | AF16: 사용자 데이터 직접 판매: 사용자의 개인 데이터를 직접 판매하여 주된 수익을 얻습니다. | AG16: 혁신 (Innovation) | AH16: 이메일, 메시징 앱 등 추적하기 어려운 채널을 통한 소셜 공유 영역을 의미하며, 비즈니스는 여기서 신뢰 구축에 주목해야 합니다. | AI16: 관심사 기반으로 형성되며, 한 명의 사용자가 여러 커뮤니티에 동시 소속될 수 있습니다. | AJ16: 재무 및 회계 | AK16: O | AL16: O | AM16: =10*SUMPRODUCT(--(AC16:AL16<>""),--(((AC16:AL16=정답표!$C$6:$L$6)+(AC16:AL16=정답표!$C$7:$L$7))>0)) -> 100 | AY16: 조직의 목표 달성을 위해 IT 기술을 지원하고 경영 목표와 연결한다. | AZ16: 정보시스템(IS) 전략과 기업의 경영전략을 효과적으로 연결한다. | BA16: 조직의 목표와 우선순위에 맞춰 전략, 예산, 위험을 함께 고려한다. | BB16: 정보시스템 관련 의사결정을 누가 하고 그에 대한 책임은 누가 지는가? | BC16: 프로젝트의 전략적 적합성과 실제 실행 가능성을 종합적으로 고려한다. | BD16: 조직의 일부 IT 기능을 외부 전문 업체에 위탁하여 수행하게 하는 것이다. | BE16: 보안 위협이 완전히 제거되어 정보 보안이 강화된다. | BF16: O | BG16: O | BH16: X | BI16: =10*SUMPRODUCT(--(AY16:BH16<>""),--(((AY16:BH16=정답표!$C$10:$L$10)+(AY16:BH16=정답표!$C$11:$L$11))>0)) -> 100 | BJ16: =SUM(Q16,AB16,AM16,AX16,BI16) -> 400 | BK16: =COUNT(Q16,AB16,AM16,AX16,BI16) -> 4 | BL16: =IF(QuizMatchTable[[#This Row],[분반]]=1, QuizMatchTable[[#This Row],[퀴즈합계]]/4 *0.3, QuizMatchTable[[#This Row],[퀴즈합계]]/5*0.3) -> 30 | BM16: 26 | BN16: 20 | BP16: =SUM(QuizMatchTable[[#This Row],[퀴즈점수(30)]],BM16,BN16,BO16) -> 76 | BQ16: =IF(OR(BP16="",BP16=0,BT16="결석초과"),"",COUNTIFS($B$2:$B$109,B16,$BP$2:$BP$109,">"&BP16)+1) -> 2 | BR16: A+ | BS16: 6
A17: 경영학과 | B17: 1 | C17: 20250945 | D17: 최민주 | E17: 010-5005-8659 | F17: cmj5005@naver.com | R17: BPR | S17: 일상적인 운영을 위한 공식적이고 표준화된 절차를 따릅니다. | T17: 기업 간 프로세스 | U17: 동일한 데이터가 여러 부서에 중복 저장되어 불일치가 발생합니다. | V17: 전사적 정보시스템(EIS) 도입 | W17: 불필요한 승인 단계를 축소하여 시간과 자원을 최소화합니다. | X17: 고객과의 모든 상호작용을 통합 관리하여 고객 평생 가치를 극대화하는 것입니다. | Y17: 비즈니스 운영을 단일하고 일관된 컴퓨팅 플랫폼에 통합하는 것입니다. | Z17: O | AA17: O | AB17: =10*SUMPRODUCT(--(R17:AA17<>""),--(((R17:AA17=정답표!$C$4:$L$4)+(R17:AA17=정답표!$C$5:$L$5))>0)) -> 100 | AC17: 하드웨어,소프트웨어,커뮤니티,절차,사람 | AD17: 조직 전략이 가치 사슬을 결정하고, 가치 사슬은 비즈니스 프로세스를, 프로세스는 SMIS 요구 사항을 결정합니다. | AE17: 개인적 강화 | AF17: 사용자 데이터 직접 판매: 사용자의 개인 데이터를 직접 판매하여 주된 수익을 얻습니다. | AG17: 상식 (Common Sense) | AH17: 인공지능(AI)이 생성한 가짜 뉴스나 딥페이크 콘텐츠가 확산되는 소셜 미디어의 어두운 면을 지칭합니다. | AI17: 일방향 통신을 통해 정보가 전달되며, 사용자 간의 상호작용은 제한적입니다. | AJ17: 제조 및 운영 | AK17: O | AL17: O | AM17: =10*SUMPRODUCT(--(AC17:AL17<>""),--(((AC17:AL17=정답표!$C$6:$L$6)+(AC17:AL17=정답표!$C$7:$L$7))>0)) -> 40 | AY17: 조직의 목표 달성을 위해 IT 기술을 지원하고 경영 목표와 연결한다. | AZ17: 정보시스템(IS) 전략과 기업의 경영전략을 효과적으로 연결한다. | BA17: 조직의 목표와 우선순위에 맞춰 전략, 예산, 위험을 함께 고려한다. | BB17: 정보시스템 관련 의사결정을 누가 하고 그에 대한 책임은 누가 지는가? | BC17: 프로젝트의 전략적 적합성과 실제 실행 가능성을 종합적으로 고려한다. | BD17: 조직의 일부 IT 기능을 외부 전문 업체에 위탁하여 수행하게 하는 것이다. | BE17: 보안 위협이 완전히 제거되어 정보 보안이 강화된다. | BF17: O | BG17: O | BH17: X | BI17: =10*SUMPRODUCT(--(AY17:BH17<>""),--(((AY17:BH17=정답표!$C$10:$L$10)+(AY17:BH17=정답표!$C$11:$L$11))>0)) -> 100 | BJ17: =SUM(Q17,AB17,AM17,AX17,BI17) -> 240 | BK17: =COUNT(Q17,AB17,AM17,AX17,BI17) -> 3 | BL17: =IF(QuizMatchTable[[#This Row],[분반]]=1, QuizMatchTable[[#This Row],[퀴즈합계]]/4 *0.3, QuizMatchTable[[#This Row],[퀴즈합계]]/5*0.3) -> 18 | BM17: 26 | BN17: 19.6 | BP17: =SUM(QuizMatchTable[[#This Row],[퀴즈점수(30)]],BM17,BN17,BO17) -> 63.6 | BQ17: =IF(OR(BP17="",BP17=0,BT17="결석초과"),"",COUNTIFS($B$2:$B$109,B17,$BP$2:$BP$109,">"&BP17)+1) -> 12 | BR17: B+ | BS17: 6
A18: 경영학과 | B18: 1 | C18: 20251606 | D18: 강승회 | E18: 010-5519-9991 | F18: jiangchenghui09@gmail.com | G18: B. 피드백 및 반복 (反馈和迭代) | H18: D. 최소한의 비용과 시간 소모 (最低限度的成本和时间消耗) | I18: C. 운영적 의사결정 (运营性决策) | J18: C. 마케팅 전략 (营销策略) | K18: C. 문제해결 (问题解决) | L18: A. 계획 → 착수 → 실행 → 마무리 (计划 → 启动 → 执行 → 结束) | M18: A. 프로젝트 콘텐츠 (项目内容/产出物) | N18: B. 비동기적 소통 (Asynchronous Communication / 异步沟通) | O18: O (참/对) | P18: O (참/对) | Q18: =10*SUMPRODUCT(--(G18:P18<>""),--(((G18:P18=정답표!$C$2:$L$2)+(G18:P18=정답표!$C$3:$L$3))>0)) -> 70 | AY18: 支持IT技术以实现组织目标，并将其与经营目标相结合。 | AZ18: 有效连接信息系统(IS)战略与企业经营战略。 | BA18: 根据组织的目标和优先顺序，综合考虑战略、预算和风险。 | BB18: 谁最擅长操作电脑并拥有技术专业知识？ | BC18: 综合考虑项目的战略适用性和实际可行性。 | BD18: 将组织的部分IT功能委托给外部专业公司执行。 | BE18: 安全威胁完全消除，信息安全得到加强。 | BF18: O | BG18: O | BH18: X | BI18: =10*SUMPRODUCT(--(AY18:BH18<>""),--(((AY18:BH18=정답표!$C$10:$L$10)+(AY18:BH18=정답표!$C$11:$L$11))>0)) -> 90 | BJ18: =SUM(Q18,AB18,AM18,AX18,BI18) -> 160 | BK18: =COUNT(Q18,AB18,AM18,AX18,BI18) -> 2 | BL18: =IF(QuizMatchTable[[#This Row],[분반]]=1, QuizMatchTable[[#This Row],[퀴즈합계]]/4 *0.3, QuizMatchTable[[#This Row],[퀴즈합계]]/5*0.3) -> 12 | BM18: 22 | BN18: 0 | BP18: =SUM(QuizMatchTable[[#This Row],[퀴즈점수(30)]],BM18,BN18,BO18) -> 34 | BQ18: =IF(OR(BP18="",BP18=0,BT18="결석초과"),"",COUNTIFS($B$2:$B$109,B18,$BP$2:$BP$109,">"&BP18)+1) -> 21 | BR18: F | BS18: 12
A19: 경영학과 | B19: 1 | C19: 20251670 | D19: 김준우 | E19: 010-5541-3529 | F19: jogaehana@gmail.com | G19: B. 피드백 및 반복 (反馈和迭代) | H19: D. 최소한의 비용과 시간 소모 (最低限度的成本和时间消耗) | I19: C. 운영적 의사결정 (运营性决策) | J19: C. 마케팅 전략 (营销策略) | K19: C. 문제해결 (问题解决) | L19: C. 착수 → 계획 → 실행 → 마무리 (启动 → 计划 → 执行 → 结束) | M19: A. 프로젝트 콘텐츠 (项目内容/产出物), B. 프로젝트 메타데이터 (项目元数据) | N19: B. 비동기적 소통 (Asynchronous Communication / 异步沟通) | O19: X (거짓/错) | P19: O (참/对) | Q19: =10*SUMPRODUCT(--(G19:P19<>""),--(((G19:P19=정답표!$C$2:$L$2)+(G19:P19=정답표!$C$3:$L$3))>0)) -> 100 | R19: BPR | S19: 일상적인 운영을 위한 공식적이고 표준화된 절차를 따릅니다. | T19: 기업 간 프로세스 | U19: 동일한 데이터가 여러 부서에 중복 저장되어 불일치가 발생합니다. | V19: 전사적 정보시스템(EIS) 도입 | W19: 불필요한 승인 단계를 축소하여 시간과 자원을 최소화합니다. | X19: 고객과의 모든 상호작용을 통합 관리하여 고객 평생 가치를 극대화하는 것입니다. | Y19: 비즈니스 운영을 단일하고 일관된 컴퓨팅 플랫폼에 통합하는 것입니다. | Z19: O | AA19: O | AB19: =10*SUMPRODUCT(--(R19:AA19<>""),--(((R19:AA19=정답표!$C$4:$L$4)+(R19:AA19=정답표!$C$5:$L$5))>0)) -> 100 | AY19: 조직의 목표 달성을 위해 IT 기술을 지원하고 경영 목표와 연결한다. | AZ19: 정보시스템(IS) 전략과 기업의 경영전략을 효과적으로 연결한다. | BA19: 조직의 목표와 우선순위에 맞춰 전략, 예산, 위험을 함께 고려한다. | BB19: 정보시스템 관련 의사결정을 누가 하고 그에 대한 책임은 누가 지는가? | BC19: 프로젝트의 전략적 적합성과 실제 실행 가능성을 종합적으로 고려한다. | BD19: 조직의 일부 IT 기능을 외부 전문 업체에 위탁하여 수행하게 하는 것이다. | BE19: 보안 위협이 완전히 제거되어 정보 보안이 강화된다. | BF19: O | BG19: O | BH19: X | BI19: =10*SUMPRODUCT(--(AY19:BH19<>""),--(((AY19:BH19=정답표!$C$10:$L$10)+(AY19:BH19=정답표!$C$11:$L$11))>0)) -> 100 | BJ19: =SUM(Q19,AB19,AM19,AX19,BI19) -> 300 | BK19: =COUNT(Q19,AB19,AM19,AX19,BI19) -> 3 | BL19: =IF(QuizMatchTable[[#This Row],[분반]]=1, QuizMatchTable[[#This Row],[퀴즈합계]]/4 *0.3, QuizMatchTable[[#This Row],[퀴즈합계]]/5*0.3) -> 22.5 | BM19: 26 | BN19: 20 | BP19: =SUM(QuizMatchTable[[#This Row],[퀴즈점수(30)]],BM19,BN19,BO19) -> 68.5 | BQ19: =IF(OR(BP19="",BP19=0,BT19="결석초과"),"",COUNTIFS($B$2:$B$109,B19,$BP$2:$BP$109,">"&BP19)+1) -> 7 | BR19: A0 | BS19: 6
A20: 경영학과 | B20: 1 | C20: 20251672 | D20: 박건우 | E20: 010-4398-8123 | F20: gunukingg05@gmail.com | BL20: =IF(QuizMatchTable[[#This Row],[분반]]=1, QuizMatchTable[[#This Row],[퀴즈합계]]/4 *0.3, QuizMatchTable[[#This Row],[퀴즈합계]]/5*0.3) -> 0 | BM20: 0 | BN20: 0 | BP20: =SUM(QuizMatchTable[[#This Row],[퀴즈점수(30)]],BM20,BN20,BO20) -> 0 | BQ20: =IF(OR(BP20="",BP20=0,BT20="결석초과"),"",COUNTIFS($B$2:$B$109,B20,$BP$2:$BP$109,">"&BP20)+1) | BR20: F | BS20: 33 | BT20: 결석초과
A21: 경영학과 | B21: 1 | C21: 20251909 | D21: 고하우 | E21: 010-8267-4006 | F21: 516970470@qq.com | AY21: 支持IT技术以实现组织目标，并将其与经营目标相结合。 | AZ21: 有效连接信息系统(IS)战略与企业经营战略。 | BA21: 根据组织的目标和优先顺序，综合考虑战略、预算和风险。 | BB21: 谁来做信息系统相关的决策，谁来承担责任？ | BC21: 综合考虑项目的战略适用性和实际可行性。 | BD21: 将组织的部分IT功能委托给外部专业公司执行。 | BE21: 安全威胁完全消除，信息安全得到加强。 | BF21: O | BG21: O | BH21: X | BI21: =10*SUMPRODUCT(--(AY21:BH21<>""),--(((AY21:BH21=정답표!$C$10:$L$10)+(AY21:BH21=정답표!$C$11:$L$11))>0)) -> 100 | BJ21: =SUM(Q21,AB21,AM21,AX21,BI21) -> 100 | BK21: =COUNT(Q21,AB21,AM21,AX21,BI21) -> 1 | BL21: =IF(QuizMatchTable[[#This Row],[분반]]=1, QuizMatchTable[[#This Row],[퀴즈합계]]/4 *0.3, QuizMatchTable[[#This Row],[퀴즈합계]]/5*0.3) -> 7.5 | BM21: 0 | BN21: 0 | BP21: =SUM(QuizMatchTable[[#This Row],[퀴즈점수(30)]],BM21,BN21,BO21) -> 7.5 | BQ21: =IF(OR(BP21="",BP21=0,BT21="결석초과"),"",COUNTIFS($B$2:$B$109,B21,$BP$2:$BP$109,">"&BP21)+1) | BR21: F | BS21: 18 | BT21: 결석초과
A22: 경영학과 | B22: 1 | C22: 20251910 | D22: 서만 | E22: 010-7631-6213 | F22: x31_0113@qq.com | R22: BPR | S22: 遵循日常运营的正式化和标准化程序。 | T22: 企业间流程 | U22: 相同数据在多个部门重复存储，导致不一致。 | V22: 引入企业信息系统（EIS） | W22: 减少不必要的审批环节，从而最大限度地减少时间和资源。 | X22: 整合管理与客户的所有互动，最大限度地提高客户终身价值。 | Y22: 将业务运营整合到一个单一且一致的计算平台。 | Z22: O | AA22: O | AB22: =10*SUMPRODUCT(--(R22:AA22<>""),--(((R22:AA22=정답표!$C$4:$L$4)+(R22:AA22=정답표!$C$5:$L$5))>0)) -> 100 | AC22: 硬件、软件、数据、流程、人员 | AD22: 组织战略决定价值链，价值链决定业务流程，业务流程决定 SMIS 需求。 | AE22: 增加物质资本 | AF22: 直接销售用户数据：通过直接销售用户个人数据获取主要收入。 | AG22: 常识 (Common Sense) | AH22: 指通过电子邮件、消息应用等难以追踪的渠道进行的社交分享区域，企业应在此处关注建立信任。 | AI22: 基于兴趣形成，一个用户可以同时属于多个社区。 | AJ22: 财务与会计 | AK22: O | AL22: O | AM22: =10*SUMPRODUCT(--(AC22:AL22<>""),--(((AC22:AL22=정답표!$C$6:$L$6)+(AC22:AL22=정답표!$C$7:$L$7))>0)) -> 90 | AY22: 支持IT技术以实现组织目标，并将其与经营目标相结合。 | AZ22: 有效连接信息系统(IS)战略与企业经营战略。 | BA22: 根据组织的目标和优先顺序，综合考虑战略、预算和风险。 | BB22: 谁来做信息系统相关的决策，谁来承担责任？ | BC22: 综合考虑项目的战略适用性和实际可行性。 | BD22: 将组织的部分IT功能委托给外部专业公司执行。 | BE22: 安全威胁完全消除，信息安全得到加强。 | BF22: O | BG22: O | BH22: X | BI22: =10*SUMPRODUCT(--(AY22:BH22<>""),--(((AY22:BH22=정답표!$C$10:$L$10)+(AY22:BH22=정답표!$C$11:$L$11))>0)) -> 100 | BJ22: =SUM(Q22,AB22,AM22,AX22,BI22) -> 290 | BK22: =COUNT(Q22,AB22,AM22,AX22,BI22) -> 3 | BL22: =IF(QuizMatchTable[[#This Row],[분반]]=1, QuizMatchTable[[#This Row],[퀴즈합계]]/4 *0.3, QuizMatchTable[[#This Row],[퀴즈합계]]/5*0.3) -> 21.75 | BM22: 28 | BN22: 16.8 | BP22: =SUM(QuizMatchTable[[#This Row],[퀴즈점수(30)]],BM22,BN22,BO22) -> 66.55 | BQ22: =IF(OR(BP22="",BP22=0,BT22="결석초과"),"",COUNTIFS($B$2:$B$109,B22,$BP$2:$BP$109,">"&BP22)+1) -> 10 | BR22: B+ | BS22: 3
A23: 경영학과 | B23: 1 | C23: 20251913 | D23: 장호연 | E23: 010-8247-5841 | F23: 516970470@qq.com | R23: BPR | S23: 遵循日常运营的正式化和标准化程序。 | T23: 企业间流程 | U23: 相同数据在多个部门重复存储，导致不一致。 | V23: 引入企业信息系统（EIS） | W23: 减少不必要的审批环节，从而最大限度地减少时间和资源。 | X23: 整合管理与客户的所有互动，最大限度地提高客户终身价值。 | Y23: 将业务运营整合到一个单一且一致的计算平台。 | Z23: O | AA23: O | AB23: =10*SUMPRODUCT(--(R23:AA23<>""),--(((R23:AA23=정답표!$C$4:$L$4)+(R23:AA23=정답표!$C$5:$L$5))>0)) -> 100 | BJ23: =SUM(Q23,AB23,AM23,AX23,BI23) -> 100 | BK23: =COUNT(Q23,AB23,AM23,AX23,BI23) -> 1 | BL23: =IF(QuizMatchTable[[#This Row],[분반]]=1, QuizMatchTable[[#This Row],[퀴즈합계]]/4 *0.3, QuizMatchTable[[#This Row],[퀴즈합계]]/5*0.3) -> 7.5 | BM23: 0 | BN23: 0 | BP23: =SUM(QuizMatchTable[[#This Row],[퀴즈점수(30)]],BM23,BN23,BO23) -> 7.5 | BQ23: =IF(OR(BP23="",BP23=0,BT23="결석초과"),"",COUNTIFS($B$2:$B$109,B23,$BP$2:$BP$109,">"&BP23)+1) | BR23: F | BS23: 24 | BT23: 결석초과
A24: 경영학과 | B24: 1 | C24: 20251915 | D24: 호티안뚜엔 | E24: 010-5592-6663 | F24: anhtuyen0425@gmail.com | G24: B. 피드백 및 반복 (反馈和迭代) | H24: D. 최소한의 비용과 시간 소모 (最低限度的成本和时间消耗) | I24: C. 운영적 의사결정 (运营性决策) | J24: C. 마케팅 전략 (营销策略) | K24: C. 문제해결 (问题解决) | L24: C. 착수 → 계획 → 실행 → 마무리 (启动 → 计划 → 执行 → 结束) | M24: A. 프로젝트 콘텐츠 (项目内容/产出物) | N24: B. 비동기적 소통 (Asynchronous Communication / 异步沟通) | O24: X (거짓/错) | P24: O (참/对) | Q24: =10*SUMPRODUCT(--(G24:P24<>""),--(((G24:P24=정답표!$C$2:$L$2)+(G24:P24=정답표!$C$3:$L$3))>0)) -> 90 | R24: BPR | S24: 일상적인 운영을 위한 공식적이고 표준화된 절차를 따릅니다. | T24: 기업 간 프로세스 | U24: 동일한 데이터가 여러 부서에 중복 저장되어 불일치가 발생합니다. | V24: 전사적 정보시스템(EIS) 도입 | W24: 불필요한 승인 단계를 축소하여 시간과 자원을 최소화합니다. | X24: 고객과의 모든 상호작용을 통합 관리하여 고객 평생 가치를 극대화하는 것입니다. | Y24: 비즈니스 운영을 단일하고 일관된 컴퓨팅 플랫폼에 통합하는 것입니다. | Z24: O | AA24: O | AB24: =10*SUMPRODUCT(--(R24:AA24<>""),--(((R24:AA24=정답표!$C$4:$L$4)+(R24:AA24=정답표!$C$5:$L$5))>0)) -> 100 | AC24: 콘텐츠, 플랫폼, 네트워크,가치사슬,하드웨어 | AD24: 조직 전략이 가치 사슬을 결정하고, 가치 사슬은 비즈니스 프로세스를, 프로세스는 SMIS 요구 사항을 결정합니다. | AE24: 정보 획득 | AF24: 제휴 및 소셜 커머스: 추천 링크를 통한 판매 수수료나 실시간 쇼핑을 통해 수익을 창출합니다. | AG24: 투명성 (Disclosure) | AH24: 인공지능(AI)이 생성한 가짜 뉴스나 딥페이크 콘텐츠가 확산되는 소셜 미디어의 어두운 면을 지칭합니다. | AI24: 주로 지리적 근접성을 기반으로 형성되어 구성원 간의 유대감이 강합니다. | AJ24: 판매 및 마케팅 | AK24: X | AL24: O | AM24: =10*SUMPRODUCT(--(AC24:AL24<>""),--(((AC24:AL24=정답표!$C$6:$L$6)+(AC24:AL24=정답표!$C$7:$L$7))>0)) -> 20 | BJ24: =SUM(Q24,AB24,AM24,AX24,BI24) -> 210 | BK24: =COUNT(Q24,AB24,AM24,AX24,BI24) -> 3 | BL24: =IF(QuizMatchTable[[#This Row],[분반]]=1, QuizMatchTable[[#This Row],[퀴즈합계]]/4 *0.3, QuizMatchTable[[#This Row],[퀴즈합계]]/5*0.3) -> 15.75 | BM24: 26 | BN24: 14.8 | BP24: =SUM(QuizMatchTable[[#This Row],[퀴즈점수(30)]],BM24,BN24,BO24) -> 56.55 | BQ24: =IF(OR(BP24="",BP24=0,BT24="결석초과"),"",COUNTIFS($B$2:$B$109,B24,$BP$2:$BP$109,">"&BP24)+1) -> 16 | BR24: B0 | BS24: 6
A25: 경영학과 | B25: 1 | C25: 23310011 | D25: 김호영 | E25: 010-2041-8336 | F25: khy040722@naver.com | AC25: 하드웨어,소프트웨어,커뮤니티,절차,사람 | AD25: 조직 전략이 가치 사슬을 결정하고, 가치 사슬은 비즈니스 프로세스를, 프로세스는 SMIS 요구 사항을 결정합니다. | AE25: 물적 자본 증대 | AF25: 사용자 데이터 직접 판매: 사용자의 개인 데이터를 직접 판매하여 주된 수익을 얻습니다. | AG25: 혁신 (Innovation) | AH25: 이메일, 메시징 앱 등 추적하기 어려운 채널을 통한 소셜 공유 영역을 의미하며, 비즈니스는 여기서 신뢰 구축에 주목해야 합니다. | AI25: 관심사 기반으로 형성되며, 한 명의 사용자가 여러 커뮤니티에 동시 소속될 수 있습니다. | AJ25: 재무 및 회계 | AK25: O | AL25: O | AM25: =10*SUMPRODUCT(--(AC25:AL25<>""),--(((AC25:AL25=정답표!$C$6:$L$6)+(AC25:AL25=정답표!$C$7:$L$7))>0)) -> 90 | AY25: 조직의 목표 달성을 위해 IT 기술을 지원하고 경영 목표와 연결한다. | AZ25: 정보시스템(IS) 전략과 기업의 경영전략을 효과적으로 연결한다. | BA25: 조직의 목표와 우선순위에 맞춰 전략, 예산, 위험을 함께 고려한다. | BB25: 정보시스템 관련 의사결정을 누가 하고 그에 대한 책임은 누가 지는가? | BC25: 프로젝트의 전략적 적합성과 실제 실행 가능성을 종합적으로 고려한다. | BD25: 조직의 일부 IT 기능을 외부 전문 업체에 위탁하여 수행하게 하는 것이다. | BE25: 보안 위협이 완전히 제거되어 정보 보안이 강화된다. | BF25: O | BG25: O | BH25: X | BI25: =10*SUMPRODUCT(--(AY25:BH25<>""),--(((AY25:BH25=정답표!$C$10:$L$10)+(AY25:BH25=정답표!$C$11:$L$11))>0)) -> 100 | BJ25: =SUM(Q25,AB25,AM25,AX25,BI25) -> 190 | BK25: =COUNT(Q25,AB25,AM25,AX25,BI25) -> 2 | BL25: =IF(QuizMatchTable[[#This Row],[분반]]=1, QuizMatchTable[[#This Row],[퀴즈합계]]/4 *0.3, QuizMatchTable[[#This Row],[퀴즈합계]]/5*0.3) -> 14.25 | BM25: 26 | BN25: 20 | BP25: =SUM(QuizMatchTable[[#This Row],[퀴즈점수(30)]],BM25,BN25,BO25) -> 60.25 | BQ25: =IF(OR(BP25="",BP25=0,BT25="결석초과"),"",COUNTIFS($B$2:$B$109,B25,$BP$2:$BP$109,">"&BP25)+1) -> 13 | BR25: B+ | BS25: 6
A26: 경영학과 | B26: 1 | C26: 24510006 | D26: 송유안 | E26: 010-4995-0377 | F26: sshj8955@naver.com | G26: B. 피드백 및 반복 (反馈和迭代) | H26: D. 최소한의 비용과 시간 소모 (最低限度的成本和时间消耗) | I26: C. 운영적 의사결정 (运营性决策) | J26: C. 마케팅 전략 (营销策略) | K26: C. 문제해결 (问题解决) | L26: C. 착수 → 계획 → 실행 → 마무리 (启动 → 计划 → 执行 → 结束) | M26: A. 프로젝트 콘텐츠 (项目内容/产出物) | N26: B. 비동기적 소통 (Asynchronous Communication / 异步沟通) | O26: X (거짓/错) | P26: O (참/对) | Q26: =10*SUMPRODUCT(--(G26:P26<>""),--(((G26:P26=정답표!$C$2:$L$2)+(G26:P26=정답표!$C$3:$L$3))>0)) -> 90 | R26: BPR | S26: 조직의 변화에 따라 프로세스 구조가 신속하게 적응하고 변경됩니다. | T26: 기업 간 프로세스 | U26: 동일한 데이터가 여러 부서에 중복 저장되어 불일치가 발생합니다. | V26: 전사적 정보시스템(EIS) 도입 | W26: 불필요한 승인 단계를 축소하여 시간과 자원을 최소화합니다. | X26: 고객과의 모든 상호작용을 통합 관리하여 고객 평생 가치를 극대화하는 것입니다. | Y26: 기존에 분리된 시스템들 간의 데이터 공유 및 통신을 가능하게 하는 것입니다. | Z26: X | AA26: O | AB26: =10*SUMPRODUCT(--(R26:AA26<>""),--(((R26:AA26=정답표!$C$4:$L$4)+(R26:AA26=정답표!$C$5:$L$5))>0)) -> 70 | BJ26: =SUM(Q26,AB26,AM26,AX26,BI26) -> 160 | BK26: =COUNT(Q26,AB26,AM26,AX26,BI26) -> 2 | BL26: =IF(QuizMatchTable[[#This Row],[분반]]=1, QuizMatchTable[[#This Row],[퀴즈합계]]/4 *0.3, QuizMatchTable[[#This Row],[퀴즈합계]]/5*0.3) -> 12 | BM26: 0 | BN26: 20 | BP26: =SUM(QuizMatchTable[[#This Row],[퀴즈점수(30)]],BM26,BN26,BO26) -> 32 | BQ26: =IF(OR(BP26="",BP26=0,BT26="결석초과"),"",COUNTIFS($B$2:$B$109,B26,$BP$2:$BP$109,">"&BP26)+1) | BR26: F | BS26: 18 | BT26: 결석초과
A27: 경영학과 | B27: 1 | C27: 24510097 | D27: 이지영 | E27: 010-8839-8874 | F27: 2jy1018@gmail.com | G27: B. 피드백 및 반복 (反馈和迭代) | H27: D. 최소한의 비용과 시간 소모 (最低限度的成本和时间消耗) | I27: C. 운영적 의사결정 (运营性决策) | J27: C. 마케팅 전략 (营销策略) | K27: C. 문제해결 (问题解决) | L27: C. 착수 → 계획 → 실행 → 마무리 (启动 → 计划 → 执行 → 结束) | M27: A. 프로젝트 콘텐츠 (项目内容/产出物), B. 프로젝트 메타데이터 (项目元数据) | N27: B. 비동기적 소통 (Asynchronous Communication / 异步沟通) | O27: X (거짓/错) | P27: O (참/对) | Q27: =10*SUMPRODUCT(--(G27:P27<>""),--(((G27:P27=정답표!$C$2:$L$2)+(G27:P27=정답표!$C$3:$L$3))>0)) -> 100 | AC27: 하드웨어,소프트웨어,데이터,절차,사람 | AD27: 조직 전략이 가치 사슬을 결정하고, 가치 사슬은 비즈니스 프로세스를, 프로세스는 SMIS 요구 사항을 결정합니다. | AE27: 물적 자본 증대 | AF27: 사용자 데이터 직접 판매: 사용자의 개인 데이터를 직접 판매하여 주된 수익을 얻습니다. | AG27: 혁신 (Innovation) | AH27: 이메일, 메시징 앱 등 추적하기 어려운 채널을 통한 소셜 공유 영역을 의미하며, 비즈니스는 여기서 신뢰 구축에 주목해야 합니다. | AI27: 관심사 기반으로 형성되며, 한 명의 사용자가 여러 커뮤니티에 동시 소속될 수 있습니다. | AJ27: 재무 및 회계 | AK27: O | AL27: O | AM27: =10*SUMPRODUCT(--(AC27:AL27<>""),--(((AC27:AL27=정답표!$C$6:$L$6)+(AC27:AL27=정답표!$C$7:$L$7))>0)) -> 100 | AY27: 조직의 목표 달성을 위해 IT 기술을 지원하고 경영 목표와 연결한다. | AZ27: 정보시스템(IS) 전략과 기업의 경영전략을 효과적으로 연결한다. | BA27: 조직의 목표와 우선순위에 맞춰 전략, 예산, 위험을 함께 고려한다. | BB27: 정보시스템 관련 의사결정을 누가 하고 그에 대한 책임은 누가 지는가? | BC27: 프로젝트의 전략적 적합성과 실제 실행 가능성을 종합적으로 고려한다. | BD27: 조직의 일부 IT 기능을 외부 전문 업체에 위탁하여 수행하게 하는 것이다. | BE27: 보안 위협이 완전히 제거되어 정보 보안이 강화된다. | BF27: O | BG27: O | BH27: X | BI27: =10*SUMPRODUCT(--(AY27:BH27<>""),--(((AY27:BH27=정답표!$C$10:$L$10)+(AY27:BH27=정답표!$C$11:$L$11))>0)) -> 100 | BJ27: =SUM(Q27,AB27,AM27,AX27,BI27) -> 300 | BK27: =COUNT(Q27,AB27,AM27,AX27,BI27) -> 3 | BL27: =IF(QuizMatchTable[[#This Row],[분반]]=1, QuizMatchTable[[#This Row],[퀴즈합계]]/4 *0.3, QuizMatchTable[[#This Row],[퀴즈합계]]/5*0.3) -> 22.5 | BM27: 22 | BN27: 20 | BP27: =SUM(QuizMatchTable[[#This Row],[퀴즈점수(30)]],BM27,BN27,BO27) -> 64.5 | BQ27: =IF(OR(BP27="",BP27=0,BT27="결석초과"),"",COUNTIFS($B$2:$B$109,B27,$BP$2:$BP$109,">"&BP27)+1) -> 11 | BR27: B+ | BS27: 12
A28: 경영학과 | B28: 2 | C28: 20220130 | D28: 가경란 | E28: 010-7617-6878 | F28: 2068609058@qq.com | G28: B. 피드백 및 반복 (反馈和迭代) | H28: D. 최소한의 비용과 시간 소모 (最低限度的成本和时间消耗) | I28: C. 운영적 의사결정 (运营性决策) | J28: C. 마케팅 전략 (营销策略) | K28: C. 문제해결 (问题解决) | L28: C. 착수 → 계획 → 실행 → 마무리 (启动 → 计划 → 执行 → 结束) | M28: A. 프로젝트 콘텐츠 (项目内容/产出物) | N28: B. 비동기적 소통 (Asynchronous Communication / 异步沟通) | O28: X (거짓/错) | P28: O (참/对) | Q28: 90 | R28: BPR | S28: 遵循日常运营的正式化和标准化程序。 | T28: 企业间流程 | U28: 相同数据在多个部门重复存储，导致不一致。 | V28: 引入企业信息系统（EIS） | W28: 减少不必要的审批环节，从而最大限度地减少时间和资源。 | X28: 整合管理与客户的所有互动，最大限度地提高客户终身价值。 | Y28: 将业务运营整合到一个单一且一致的计算平台。 | Z28: O | AA28: O | AB28: 100 | AC28: 硬件、软件、社区、流程、人员 | AD28: 组织战略决定价值链，价值链决定业务流程，业务流程决定 SMIS 需求。 | AE28: 增加物质资本 | AF28: 直接销售用户数据：通过直接销售用户个人数据获取主要收入。 | AG28: 创新 (Innovation) | AH28: 指通过电子邮件、消息应用等难以追踪的渠道进行的社交分享区域，企业应在此处关注建立信任。 | AI28: 基于兴趣形成，一个用户可以同时属于多个社区。 | AJ28: 财务与会计 | AK28: O | AL28: O | AM28: 90 | AN28: 在风险、成本和便利性之间找到适当的平衡。 | AO28: 因为将所有安全风险降至零在现实中是不可能且低效的。 | AP28: 未应用安全补丁的旧软件 | AQ28: 威胁能够访问系统或数据并造成损害的弱点。 | AR28: 将数据转换为未经授权的人无法理解的形式以进行保护的技术。 | AS28: 根据预设规则允许或阻止网络流量。 | AT28: 主要是技术部门制定和执行的技术问题。 | AU28: 定期测试备份数据是否能实际恢复非常重要。 | AV28: O | AW28: O | AX28: 100 | AY28: 支持IT技术以实现组织目标，并将其与经营目标相结合。 | AZ28: 有效连接信息系统(IS)战略与企业经营战略。 | BA28: 根据组织的目标和优先顺序，综合考虑战略、预算和风险。 | BB28: 谁来做信息系统相关的决策，谁来承担责任？ | BC28: 综合考虑项目的战略适用性和实际可行性。 | BD28: 将组织的部分IT功能委托给外部专业公司执行。 | BE28: 安全威胁完全消除，信息安全得到加强。 | BF28: O | BG28: O | BH28: X | BI28: 100 | BJ28: 480 | BK28: 5 | BL28: =IF(QuizMatchTable[[#This Row],[분반]]=1, QuizMatchTable[[#This Row],[퀴즈합계]]/4 *0.3, QuizMatchTable[[#This Row],[퀴즈합계]]/5*0.3) -> 28.8 | BM28: 30 | BN28: 18.8 | BP28: =SUM(QuizMatchTable[[#This Row],[퀴즈점수(30)]],BM28,BN28,BO28) -> 77.6 | BQ28: =IF(OR(BP28="",BP28=0,BT28="결석초과"),"",COUNTIFS($B$2:$B$109,B28,$BP$2:$BP$109,">"&BP28)+1) -> 9 | BR28: B+ | BS28: 0
A29: 경영학과 | B29: 2 | C29: 20220131 | D29: 강합문호 | E29: 010-2249-1040 | F29: 2024117631@qq.com | G29: B. 피드백 및 반복 (反馈和迭代) | H29: D. 최소한의 비용과 시간 소모 (最低限度的成本和时间消耗) | I29: D. 비구조적 의사결정 (非结构性决策) | J29: C. 마케팅 전략 (营销策略) | K29: B. 의사결정 (决策制定) | L29: C. 착수 → 계획 → 실행 → 마무리 (启动 → 计划 → 执行 → 结束) | M29: B. 프로젝트 메타데이터 (项目元数据) | N29: B. 비동기적 소통 (Asynchronous Communication / 异步沟通) | O29: O (참/对) | P29: O (참/对) | Q29: =10*SUMPRODUCT(--(G29:P29<>""),--(((G29:P29=정답표!$C$2:$L$2)+(G29:P29=정답표!$C$3:$L$3))>0)) -> 60 | R29: CRM | S29: 频繁发生例外情况，并被设计为能够适应这些情况。 | T29: 工作组流程 | U29: 相同数据在多个部门重复存储，导致不一致。 | V29: 加强安全以防止数据泄露 | W29: 减少不必要的审批环节，从而最大限度地减少时间和资源。 | X29: 在单一平台上自动化企业的财务、会计和制造流程。 | Y29: 实现现有分离系统之间的数据共享和通信。 | Z29: O | AA29: X | AB29: =10*SUMPRODUCT(--(R29:AA29<>""),--(((R29:AA29=정답표!$C$4:$L$4)+(R29:AA29=정답표!$C$5:$L$5))>0)) -> 30 | AC29: 内容、平台、网络、价值链、硬件 | AD29: 业务流程决定 SMIS 需求，然后反过来塑造组织战略和价值链。 | AE29: 个人赋能 | AF29: 直接销售用户数据：通过直接销售用户个人数据获取主要收入。 | AG29: 创新 (Innovation) | AH29: 指人工智能 (AI) 生成的假新闻或深度伪造内容在社交媒体上传播的阴暗面。 | AI29: 基于兴趣形成，一个用户可以同时属于多个社区。 | AJ29: 销售与营销 | AK29: X | AL29: X | AM29: =10*SUMPRODUCT(--(AC29:AL29<>""),--(((AC29:AL29=정답표!$C$6:$L$6)+(AC29:AL29=정답표!$C$7:$L$7))>0)) -> 30 | AN29: 在风险、成本和便利性之间找到适当的平衡。 | AO29: 因为信息系统的复杂性增加，导致安全管理的难度提高。 | AP29: 存储重要客户信息的数据库 | AQ29: 外部试图绕过安全系统进行非法访问的行为。 | AR29: 将数据转换为未经授权的人无法理解的形式以进行保护的技术。 | AS29: 根据预设规则允许或阻止网络流量。 | AT29: 主要是技术部门制定和执行的技术问题。 | AU29: 定期测试备份数据是否能实际恢复非常重要。 | AV29: O | AW29: X | AX29: =10*SUMPRODUCT(--(AN29:AW29<>""),--(((AN29:AW29=정답표!$C$8:$L$8)+(AN29:AW29=정답표!$C$9:$L$9))>0)) -> 60 | AY29: 直接执行和管理组织内的所有业务流程。 | AZ29: 有效连接信息系统(IS)战略与企业经营战略。 | BA29: 根据组织的目标和优先顺序，综合考虑战略、预算和风险。 | BB29: 哪个部门使用的信息系统相关预算最多？ | BC29: 综合考虑项目的战略适用性和实际可行性。 | BD29: 将组织的部分IT功能委托给外部专业公司执行。 | BE29: 安全威胁完全消除，信息安全得到加强。 | BF29: X | BG29: X | BH29: X | BI29: =10*SUMPRODUCT(--(AY29:BH29<>""),--(((AY29:BH29=정답표!$C$10:$L$10)+(AY29:BH29=정답표!$C$11:$L$11))>0)) -> 60 | BJ29: =SUM(Q29,AB29,AM29,AX29,BI29) -> 240 | BK29: =COUNT(Q29,AB29,AM29,AX29,BI29) -> 5 | BL29: =IF(QuizMatchTable[[#This Row],[분반]]=1, QuizMatchTable[[#This Row],[퀴즈합계]]/4 *0.3, QuizMatchTable[[#This Row],[퀴즈합계]]/5*0.3) -> 14.4 | BM29: 30 | BN29: 9.6 | BP29: =SUM(QuizMatchTable[[#This Row],[퀴즈점수(30)]],BM29,BN29,BO29) -> 54 | BQ29: =IF(OR(BP29="",BP29=0,BT29="결석초과"),"",COUNTIFS($B$2:$B$109,B29,$BP$2:$BP$109,">"&BP29)+1) -> 32 | BR29: F | BS29: 0
A30: 경영학과 | B30: 2 | C30: 20220132 | D30: 고천양 | E30: 010-8232-2903 | F30: 3340777498@qq.com | G30: C. 분업 및 전문화 (分工和专业化) | H30: D. 최소한의 비용과 시간 소모 (最低限度的成本和时间消耗) | I30: C. 운영적 의사결정 (运营性决策) | J30: C. 마케팅 전략 (营销策略) | K30: C. 문제해결 (问题解决) | L30: C. 착수 → 계획 → 실행 → 마무리 (启动 → 计划 → 执行 → 结束) | M30: B. 프로젝트 메타데이터 (项目元数据) | N30: B. 비동기적 소통 (Asynchronous Communication / 异步沟通) | O30: X (거짓/错) | P30: O (참/对) | Q30: =10*SUMPRODUCT(--(G30:P30<>""),--(((G30:P30=정답표!$C$2:$L$2)+(G30:P30=정답표!$C$3:$L$3))>0)) -> 80 | R30: BPR | S30: 遵循日常运营的正式化和标准化程序。 | T30: 企业级流程 | U30: 相同数据在多个部门重复存储，导致不一致。 | V30: 引入企业信息系统（EIS） | W30: 减少不必要的审批环节，从而最大限度地减少时间和资源。 | X30: 整合管理与客户的所有互动，最大限度地提高客户终身价值。 | Y30: 将业务运营整合到一个单一且一致的计算平台。 | Z30: O | AA30: O | AB30: =10*SUMPRODUCT(--(R30:AA30<>""),--(((R30:AA30=정답표!$C$4:$L$4)+(R30:AA30=정답표!$C$5:$L$5))>0)) -> 90 | AC30: 硬件、软件、数据、流程、人员 | AD30: 组织战略决定价值链，价值链决定业务流程，业务流程决定 SMIS 需求。 | AE30: 增加物质资本 | AF30: 直接销售用户数据：通过直接销售用户个人数据获取主要收入。 | AG30: 创新 (Innovation) | AH30: 指通过电子邮件、消息应用等难以追踪的渠道进行的社交分享区域，企业应在此处关注建立信任。 | AI30: 基于兴趣形成，一个用户可以同时属于多个社区。 | AJ30: 制造与运营 | AK30: O | AL30: O | AM30: =10*SUMPRODUCT(--(AC30:AL30<>""),--(((AC30:AL30=정답표!$C$6:$L$6)+(AC30:AL30=정답표!$C$7:$L$7))>0)) -> 90 | AN30: 在风险、成本和便利性之间找到适当的平衡。 | AO30: 因为将所有安全风险降至零在现实中是不可能且低效的。 | AP30: 未应用安全补丁的旧软件 | AQ30: 威胁能够访问系统或数据并造成损害的弱点。 | AR30: 将数据转换为未经授权的人无法理解的形式以进行保护的技术。 | AS30: 根据预设规则允许或阻止网络流量。 | AT30: 主要是技术部门制定和执行的技术问题。 | AU30: 定期测试备份数据是否能实际恢复非常重要。 | AV30: O | AW30: O | AX30: =10*SUMPRODUCT(--(AN30:AW30<>""),--(((AN30:AW30=정답표!$C$8:$L$8)+(AN30:AW30=정답표!$C$9:$L$9))>0)) -> 100 | AY30: 支持IT技术以实现组织目标，并将其与经营目标相结合。 | AZ30: 有效连接信息系统(IS)战略与企业经营战略。 | BA30: 根据组织的目标和优先顺序，综合考虑战略、预算和风险。 | BB30: 谁来做信息系统相关的决策，谁来承担责任？ | BC30: 综合考虑项目的战略适用性和实际可行性。 | BD30: 将组织的部分IT功能委托给外部专业公司执行。 | BE30: 安全威胁完全消除，信息安全得到加强。 | BF30: O | BG30: O | BH30: X | BI30: =10*SUMPRODUCT(--(AY30:BH30<>""),--(((AY30:BH30=정답표!$C$10:$L$10)+(AY30:BH30=정답표!$C$11:$L$11))>0)) -> 100 | BJ30: =SUM(Q30,AB30,AM30,AX30,BI30) -> 460 | BK30: =COUNT(Q30,AB30,AM30,AX30,BI30) -> 5 | BL30: =IF(QuizMatchTable[[#This Row],[분반]]=1, QuizMatchTable[[#This Row],[퀴즈합계]]/4 *0.3, QuizMatchTable[[#This Row],[퀴즈합계]]/5*0.3) -> 27.6 | BM30: 26 | BN30: 12.8 | BP30: =SUM(QuizMatchTable[[#This Row],[퀴즈점수(30)]],BM30,BN30,BO30) -> 66.4 | BQ30: =IF(OR(BP30="",BP30=0,BT30="결석초과"),"",COUNTIFS($B$2:$B$109,B30,$BP$2:$BP$109,">"&BP30)+1) -> 28 | BR30: F | BS30: 6
A31: 경영학과 | B31: 2 | C31: 20220133 | D31: 고흔이 | E31: 010-2118-2811 | F31: 1691190544@qq.com | G31: B. 피드백 및 반복 (反馈和迭代) | H31: D. 최소한의 비용과 시간 소모 (最低限度的成本和时间消耗) | I31: C. 운영적 의사결정 (运营性决策) | J31: C. 마케팅 전략 (营销策略) | K31: C. 문제해결 (问题解决) | L31: C. 착수 → 계획 → 실행 → 마무리 (启动 → 计划 → 执行 → 结束) | M31: A. 프로젝트 콘텐츠 (项目内容/产出物), B. 프로젝트 메타데이터 (项目元数据) | N31: B. 비동기적 소통 (Asynchronous Communication / 异步沟通) | O31: O (참/对) | P31: O (참/对) | Q31: =10*SUMPRODUCT(--(G31:P31<>""),--(((G31:P31=정답표!$C$2:$L$2)+(G31:P31=정답표!$C$3:$L$3))>0)) -> 90 | R31: BPR | S31: 遵循日常运营的正式化和标准化程序。 | T31: 企业间流程 | U31: 相同数据在多个部门重复存储，导致不一致。 | V31: 引入企业信息系统（EIS） | W31: 减少不必要的审批环节，从而最大限度地减少时间和资源。 | X31: 整合管理与客户的所有互动，最大限度地提高客户终身价值。 | Y31: 将业务运营整合到一个单一且一致的计算平台。 | Z31: O | AA31: O | AB31: =10*SUMPRODUCT(--(R31:AA31<>""),--(((R31:AA31=정답표!$C$4:$L$4)+(R31:AA31=정답표!$C$5:$L$5))>0)) -> 100 | AC31: 硬件、软件、数据、流程、人员 | AD31: 组织战略决定价值链，价值链决定业务流程，业务流程决定 SMIS 需求。 | AE31: 增加物质资本 | AF31: 直接销售用户数据：通过直接销售用户个人数据获取主要收入。 | AG31: 创新 (Innovation) | AH31: 指通过电子邮件、消息应用等难以追踪的渠道进行的社交分享区域，企业应在此处关注建立信任。 | AI31: 基于兴趣形成，一个用户可以同时属于多个社区。 | AJ31: 财务与会计 | AK31: O | AL31: O | AM31: =10*SUMPRODUCT(--(AC31:AL31<>""),--(((AC31:AL31=정답표!$C$6:$L$6)+(AC31:AL31=정답표!$C$7:$L$7))>0)) -> 100 | AN31: 在风险、成本和便利性之间找到适当的平衡。 | AO31: 因为将所有安全风险降至零在现实中是不可能且低效的。 | AP31: 未应用安全补丁的旧软件 | AQ31: 威胁能够访问系统或数据并造成损害的弱点。 | AR31: 将数据转换为未经授权的人无法理解的形式以进行保护的技术。 | AS31: 根据预设规则允许或阻止网络流量。 | AT31: 主要是技术部门制定和执行的技术问题。 | AU31: 定期测试备份数据是否能实际恢复非常重要。 | AV31: O | AW31: O | AX31: =10*SUMPRODUCT(--(AN31:AW31<>""),--(((AN31:AW31=정답표!$C$8:$L$8)+(AN31:AW31=정답표!$C$9:$L$9))>0)) -> 100 | AY31: 支持IT技术以实现组织目标，并将其与经营目标相结合。 | AZ31: 有效连接信息系统(IS)战略与企业经营战略。 | BA31: 根据组织的目标和优先顺序，综合考虑战略、预算和风险。 | BB31: 谁来做信息系统相关的决策，谁来承担责任？ | BC31: 综合考虑项目的战略适用性和实际可行性。 | BD31: 将组织的部分IT功能委托给外部专业公司执行。 | BE31: 安全威胁完全消除，信息安全得到加强。 | BF31: O | BG31: O | BH31: X | BI31: =10*SUMPRODUCT(--(AY31:BH31<>""),--(((AY31:BH31=정답표!$C$10:$L$10)+(AY31:BH31=정답표!$C$11:$L$11))>0)) -> 100 | BJ31: =SUM(Q31,AB31,AM31,AX31,BI31) -> 490 | BK31: =COUNT(Q31,AB31,AM31,AX31,BI31) -> 5 | BL31: =IF(QuizMatchTable[[#This Row],[분반]]=1, QuizMatchTable[[#This Row],[퀴즈합계]]/4 *0.3, QuizMatchTable[[#This Row],[퀴즈합계]]/5*0.3) -> 29.4 | BM31: 30 | BN31: 19.6 | BP31: =SUM(QuizMatchTable[[#This Row],[퀴즈점수(30)]],BM31,BN31,BO31) -> 79 | BQ31: =IF(OR(BP31="",BP31=0,BT31="결석초과"),"",COUNTIFS($B$2:$B$109,B31,$BP$2:$BP$109,">"&BP31)+1) -> 2 | BR31: A+ | BS31: 0
A32: 경영학과 | B32: 2 | C32: 20220134 | D32: 곽우봉 | E32: 010-7512-8967 | F32: 2454108044@QQ.COM | G32: B. 피드백 및 반복 (反馈和迭代) | H32: D. 최소한의 비용과 시간 소모 (最低限度的成本和时间消耗) | I32: C. 운영적 의사결정 (运营性决策) | J32: C. 마케팅 전략 (营销策略) | K32: C. 문제해결 (问题解决) | L32: C. 착수 → 계획 → 실행 → 마무리 (启动 → 计划 → 执行 → 结束) | M32: A. 프로젝트 콘텐츠 (项目内容/产出物), B. 프로젝트 메타데이터 (项目元数据) | N32: B. 비동기적 소통 (Asynchronous Communication / 异步沟通) | O32: X (거짓/错) | P32: O (참/对) | Q32: =10*SUMPRODUCT(--(G32:P32<>""),--(((G32:P32=정답표!$C$2:$L$2)+(G32:P32=정답표!$C$3:$L$3))>0)) -> 100 | R32: BPR | S32: 遵循日常运营的正式化和标准化程序。 | T32: 企业级流程 | U32: 相同数据在多个部门重复存储，导致不一致。 | V32: 引入企业信息系统（EIS） | W32: 减少不必要的审批环节，从而最大限度地减少时间和资源。 | X32: 整合管理与客户的所有互动，最大限度地提高客户终身价值。 | Y32: 将业务运营整合到一个单一且一致的计算平台。 | Z32: O | AA32: O | AB32: =10*SUMPRODUCT(--(R32:AA32<>""),--(((R32:AA32=정답표!$C$4:$L$4)+(R32:AA32=정답표!$C$5:$L$5))>0)) -> 90 | AC32: 硬件、软件、社区、流程、人员 | AD32: 价值链直接设计动态流程流以推导出 SMIS 需求。 | AE32: 增加物质资本 | AF32: 直接销售用户数据：通过直接销售用户个人数据获取主要收入。 | AG32: 创新 (Innovation) | AH32: 指通过电子邮件、消息应用等难以追踪的渠道进行的社交分享区域，企业应在此处关注建立信任。 | AI32: 基于兴趣形成，一个用户可以同时属于多个社区。 | AJ32: 财务与会计 | AK32: O | AL32: O | AM32: =10*SUMPRODUCT(--(AC32:AL32<>""),--(((AC32:AL32=정답표!$C$6:$L$6)+(AC32:AL32=정답표!$C$7:$L$7))>0)) -> 80 | AN32: 在风险、成本和便利性之间找到适当的平衡。 | AO32: 因为将所有安全风险降至零在现实中是不可能且低效的。 | AP32: 未应用安全补丁的旧软件 | AQ32: 威胁能够访问系统或数据并造成损害的弱点。 | AR32: 将数据转换为未经授权的人无法理解的形式以进行保护的技术。 | AS32: 根据预设规则允许或阻止网络流量。 | AT32: 与管理层、管理者、员工等所有组织成员的责任相关。 | AU32: 只需执行一次备份就足够了，之后不需要额外的管理。 | AV32: O | AW32: O | AX32: =10*SUMPRODUCT(--(AN32:AW32<>""),--(((AN32:AW32=정답표!$C$8:$L$8)+(AN32:AW32=정답표!$C$9:$L$9))>0)) -> 80 | AY32: 支持IT技术以实现组织目标，并将其与经营目标相结合。 | AZ32: 有效连接信息系统(IS)战略与企业经营战略。 | BA32: 根据组织的目标和优先顺序，综合考虑战略、预算和风险。 | BB32: 谁来做信息系统相关的决策，谁来承担责任？ | BC32: 综合考虑项目的战略适用性和实际可行性。 | BD32: 将组织的部分IT功能委托给外部专业公司执行。 | BE32: 安全威胁完全消除，信息安全得到加强。 | BF32: O | BG32: O | BH32: X | BI32: =10*SUMPRODUCT(--(AY32:BH32<>""),--(((AY32:BH32=정답표!$C$10:$L$10)+(AY32:BH32=정답표!$C$11:$L$11))>0)) -> 100 | BJ32: =SUM(Q32,AB32,AM32,AX32,BI32) -> 450 | BK32: =COUNT(Q32,AB32,AM32,AX32,BI32) -> 5 | BL32: =IF(QuizMatchTable[[#This Row],[분반]]=1, QuizMatchTable[[#This Row],[퀴즈합계]]/4 *0.3, QuizMatchTable[[#This Row],[퀴즈합계]]/5*0.3) -> 27 | BM32: 28 | BN32: 10 | BP32: =SUM(QuizMatchTable[[#This Row],[퀴즈점수(30)]],BM32,BN32,BO32) -> 65 | BQ32: =IF(OR(BP32="",BP32=0,BT32="결석초과"),"",COUNTIFS($B$2:$B$109,B32,$BP$2:$BP$109,">"&BP32)+1) -> 30 | BR32: F | BS32: 3
A33: 경영학과 | B33: 2 | C33: 20220139 | D33: 류개예 | E33: 010-9861-6925 | F33: 3251925645@qq.com | G33: B. 피드백 및 반복 (反馈和迭代) | H33: D. 최소한의 비용과 시간 소모 (最低限度的成本和时间消耗) | I33: C. 운영적 의사결정 (运营性决策) | J33: C. 마케팅 전략 (营销策略) | K33: C. 문제해결 (问题解决) | L33: C. 착수 → 계획 → 실행 → 마무리 (启动 → 计划 → 执行 → 结束) | M33: A. 프로젝트 콘텐츠 (项目内容/产出物), B. 프로젝트 메타데이터 (项目元数据) | N33: C. 구조적 소통 (Structured Communication / 结构化沟通) | O33: X (거짓/错) | P33: O (참/对) | Q33: =10*SUMPRODUCT(--(G33:P33<>""),--(((G33:P33=정답표!$C$2:$L$2)+(G33:P33=정답표!$C$3:$L$3))>0)) -> 90 | R33: BPR | S33: 遵循日常运营的正式化和标准化程序。 | T33: 企业间流程 | U33: 相同数据在多个部门重复存储，导致不一致。 | V33: 引入企业信息系统（EIS） | W33: 减少不必要的审批环节，从而最大限度地减少时间和资源。 | X33: 整合管理与客户的所有互动，最大限度地提高客户终身价值。 | Y33: 将业务运营整合到一个单一且一致的计算平台。 | Z33: O | AA33: O | AB33: =10*SUMPRODUCT(--(R33:AA33<>""),--(((R33:AA33=정답표!$C$4:$L$4)+(R33:AA33=정답표!$C$5:$L$5))>0)) -> 100 | AC33: 硬件、软件、数据、流程、人员 | AD33: 组织战略决定价值链，价值链决定业务流程，业务流程决定 SMIS 需求。 | AE33: 增加物质资本 | AF33: 直接销售用户数据：通过直接销售用户个人数据获取主要收入。 | AG33: 常识 (Common Sense) | AH33: 指通过电子邮件、消息应用等难以追踪的渠道进行的社交分享区域，企业应在此处关注建立信任。 | AI33: 基于兴趣形成，一个用户可以同时属于多个社区。 | AJ33: 财务与会计 | AK33: O | AL33: O | AM33: =10*SUMPRODUCT(--(AC33:AL33<>""),--(((AC33:AL33=정답표!$C$6:$L$6)+(AC33:AL33=정답표!$C$7:$L$7))>0)) -> 90 | AN33: 在风险、成本和便利性之间找到适当的平衡。 | AO33: 因为将所有安全风险降至零在现实中是不可能且低效的。 | AP33: 未应用安全补丁的旧软件 | AQ33: 威胁能够访问系统或数据并造成损害的弱点。 | AR33: 将数据转换为未经授权的人无法理解的形式以进行保护的技术。 | AS33: 根据预设规则允许或阻止网络流量。 | AT33: 主要是技术部门制定和执行的技术问题。 | AU33: 定期测试备份数据是否能实际恢复非常重要。 | AV33: O | AW33: O | AX33: =10*SUMPRODUCT(--(AN33:AW33<>""),--(((AN33:AW33=정답표!$C$8:$L$8)+(AN33:AW33=정답표!$C$9:$L$9))>0)) -> 100 | AY33: 支持IT技术以实现组织目标，并将其与经营目标相结合。 | AZ33: 有效连接信息系统(IS)战略与企业经营战略。 | BA33: 根据组织的目标和优先顺序，综合考虑战略、预算和风险。 | BB33: 谁来做信息系统相关的决策，谁来承担责任？ | BC33: 综合考虑项目的战略适用性和实际可行性。 | BD33: 将组织的部分IT功能委托给外部专业公司执行。 | BE33: 安全威胁完全消除，信息安全得到加强。 | BF33: O | BG33: O | BH33: X | BI33: =10*SUMPRODUCT(--(AY33:BH33<>""),--(((AY33:BH33=정답표!$C$10:$L$10)+(AY33:BH33=정답표!$C$11:$L$11))>0)) -> 100 | BJ33: =SUM(Q33,AB33,AM33,AX33,BI33) -> 480 | BK33: =COUNT(Q33,AB33,AM33,AX33,BI33) -> 5 | BL33: =IF(QuizMatchTable[[#This Row],[분반]]=1, QuizMatchTable[[#This Row],[퀴즈합계]]/4 *0.3, QuizMatchTable[[#This Row],[퀴즈합계]]/5*0.3) -> 28.8 | BM33: 30 | BN33: 18.39 | BP33: =SUM(QuizMatchTable[[#This Row],[퀴즈점수(30)]],BM33,BN33,BO33) -> 77.19 | BQ33: =IF(OR(BP33="",BP33=0,BT33="결석초과"),"",COUNTIFS($B$2:$B$109,B33,$BP$2:$BP$109,">"&BP33)+1) -> 12 | BR33: B+ | BS33: 0
A34: 경영학과 | B34: 2 | C34: 20220140 | D34: 류로요 | E34: 010-8379-9571 | F34: luyaoliu02@gmail.com | R34: BPR | S34: 遵循日常运营的正式化和标准化程序。 | T34: 企业间流程 | U34: 相同数据在多个部门重复存储，导致不一致。 | V34: 引入企业信息系统（EIS） | W34: 减少不必要的审批环节，从而最大限度地减少时间和资源。 | X34: 整合管理与客户的所有互动，最大限度地提高客户终身价值。 | Y34: 将业务运营整合到一个单一且一致的计算平台。 | Z34: O | AA34: O | AB34: =10*SUMPRODUCT(--(R34:AA34<>""),--(((R34:AA34=정답표!$C$4:$L$4)+(R34:AA34=정답표!$C$5:$L$5))>0)) -> 100 | AC34: 硬件、软件、数据、流程、人员 | AD34: 组织战略决定价值链，价值链决定业务流程，业务流程决定 SMIS 需求。 | AE34: 增加物质资本 | AF34: 直接销售用户数据：通过直接销售用户个人数据获取主要收入。 | AG34: 创新 (Innovation) | AH34: 指通过电子邮件、消息应用等难以追踪的渠道进行的社交分享区域，企业应在此处关注建立信任。 | AI34: 基于兴趣形成，一个用户可以同时属于多个社区。 | AJ34: 财务与会计 | AK34: O | AL34: O | AM34: =10*SUMPRODUCT(--(AC34:AL34<>""),--(((AC34:AL34=정답표!$C$6:$L$6)+(AC34:AL34=정답표!$C$7:$L$7))>0)) -> 100 | AN34: 在风险、成本和便利性之间找到适当的平衡。 | AO34: 因为将所有安全风险降至零在现实中是不可能且低效的。 | AP34: 未应用安全补丁的旧软件 | AQ34: 威胁能够访问系统或数据并造成损害的弱点。 | AR34: 将数据转换为未经授权的人无法理解的形式以进行保护的技术。 | AS34: 根据预设规则允许或阻止网络流量。 | AT34: 主要是技术部门制定和执行的技术问题。 | AU34: 定期测试备份数据是否能实际恢复非常重要。 | AV34: O | AW34: O | AX34: =10*SUMPRODUCT(--(AN34:AW34<>""),--(((AN34:AW34=정답표!$C$8:$L$8)+(AN34:AW34=정답표!$C$9:$L$9))>0)) -> 100 | AY34: 支持IT技术以实现组织目标，并将其与经营目标相结合。 | AZ34: 有效连接信息系统(IS)战略与企业经营战略。 | BA34: 根据组织的目标和优先顺序，综合考虑战略、预算和风险。 | BB34: 谁来做信息系统相关的决策，谁来承担责任？ | BC34: 综合考虑项目的战略适用性和实际可行性。 | BD34: 将组织的部分IT功能委托给外部专业公司执行。 | BE34: 安全威胁完全消除，信息安全得到加强。 | BF34: O | BG34: O | BH34: X | BI34: =10*SUMPRODUCT(--(AY34:BH34<>""),--(((AY34:BH34=정답표!$C$10:$L$10)+(AY34:BH34=정답표!$C$11:$L$11))>0)) -> 100 | BJ34: =SUM(Q34,AB34,AM34,AX34,BI34) -> 400 | BK34: =COUNT(Q34,AB34,AM34,AX34,BI34) -> 4 | BL34: =IF(QuizMatchTable[[#This Row],[분반]]=1, QuizMatchTable[[#This Row],[퀴즈합계]]/4 *0.3, QuizMatchTable[[#This Row],[퀴즈합계]]/5*0.3) -> 24 | BM34: 28 | BN34: 18.39 | BP34: =SUM(QuizMatchTable[[#This Row],[퀴즈점수(30)]],BM34,BN34,BO34) -> 70.39 | BQ34: =IF(OR(BP34="",BP34=0,BT34="결석초과"),"",COUNTIFS($B$2:$B$109,B34,$BP$2:$BP$109,">"&BP34)+1) -> 22 | BR34: F | BS34: 3
A35: 경영학과 | B35: 2 | C35: 20220141 | D35: 류명혜 | E35: 010-3952-2165 | F35: 1469098339@qq.com | G35: B. 피드백 및 반복 (反馈和迭代) | H35: D. 최소한의 비용과 시간 소모 (最低限度的成本和时间消耗) | I35: C. 운영적 의사결정 (运营性决策) | J35: C. 마케팅 전략 (营销策略) | K35: C. 문제해결 (问题解决) | L35: C. 착수 → 계획 → 실행 → 마무리 (启动 → 计划 → 执行 → 结束) | M35: A. 프로젝트 콘텐츠 (项目内容/产出物) | N35: B. 비동기적 소통 (Asynchronous Communication / 异步沟通) | O35: X (거짓/错) | P35: O (참/对) | Q35: =10*SUMPRODUCT(--(G35:P35<>""),--(((G35:P35=정답표!$C$2:$L$2)+(G35:P35=정답표!$C$3:$L$3))>0)) -> 90 | R35: BPR | S35: 遵循日常运营的正式化和标准化程序。 | T35: 企业间流程 | U35: 相同数据在多个部门重复存储，导致不一致。 | V35: 引入企业信息系统（EIS） | W35: 减少不必要的审批环节，从而最大限度地减少时间和资源。 | X35: 整合管理与客户的所有互动，最大限度地提高客户终身价值。 | Y35: 将业务运营整合到一个单一且一致的计算平台。 | Z35: O | AA35: O | AB35: =10*SUMPRODUCT(--(R35:AA35<>""),--(((R35:AA35=정답표!$C$4:$L$4)+(R35:AA35=정답표!$C$5:$L$5))>0)) -> 100 | AC35: 硬件、软件、数据、流程、人员 | AD35: 组织战略决定价值链，价值链决定业务流程，业务流程决定 SMIS 需求。 | AE35: 增加物质资本 | AF35: 直接销售用户数据：通过直接销售用户个人数据获取主要收入。 | AG35: 创新 (Innovation) | AH35: 指通过电子邮件、消息应用等难以追踪的渠道进行的社交分享区域，企业应在此处关注建立信任。 | AI35: 基于兴趣形成，一个用户可以同时属于多个社区。 | AJ35: 财务与会计 | AK35: O | AL35: O | AM35: =10*SUMPRODUCT(--(AC35:AL35<>""),--(((AC35:AL35=정답표!$C$6:$L$6)+(AC35:AL35=정답표!$C$7:$L$7))>0)) -> 100 | AN35: 在风险、成本和便利性之间找到适当的平衡。 | AO35: 因为将所有安全风险降至零在现实中是不可能且低效的。 | AP35: 未应用安全补丁的旧软件 | AQ35: 威胁能够访问系统或数据并造成损害的弱点。 | AR35: 将数据转换为未经授权的人无法理解的形式以进行保护的技术。 | AS35: 根据预设规则允许或阻止网络流量。 | AT35: 主要是技术部门制定和执行的技术问题。 | AU35: 定期测试备份数据是否能实际恢复非常重要。 | AV35: O | AW35: O | AX35: =10*SUMPRODUCT(--(AN35:AW35<>""),--(((AN35:AW35=정답표!$C$8:$L$8)+(AN35:AW35=정답표!$C$9:$L$9))>0)) -> 100 | AY35: 支持IT技术以实现组织目标，并将其与经营目标相结合。 | AZ35: 有效连接信息系统(IS)战略与企业经营战略。 | BA35: 根据组织的目标和优先顺序，综合考虑战略、预算和风险。 | BB35: 谁来做信息系统相关的决策，谁来承担责任？ | BC35: 综合考虑项目的战略适用性和实际可行性。 | BD35: 将组织的部分IT功能委托给外部专业公司执行。 | BE35: 安全威胁完全消除，信息安全得到加强。 | BF35: O | BG35: O | BH35: X | BI35: =10*SUMPRODUCT(--(AY35:BH35<>""),--(((AY35:BH35=정답표!$C$10:$L$10)+(AY35:BH35=정답표!$C$11:$L$11))>0)) -> 100 | BJ35: =SUM(Q35,AB35,AM35,AX35,BI35) -> 490 | BK35: =COUNT(Q35,AB35,AM35,AX35,BI35) -> 5 | BL35: =IF(QuizMatchTable[[#This Row],[분반]]=1, QuizMatchTable[[#This Row],[퀴즈합계]]/4 *0.3, QuizMatchTable[[#This Row],[퀴즈합계]]/5*0.3) -> 29.4 | BM35: 28 | BN35: 18.8 | BP35: =SUM(QuizMatchTable[[#This Row],[퀴즈점수(30)]],BM35,BN35,BO35) -> 76.2 | BQ35: =IF(OR(BP35="",BP35=0,BT35="결석초과"),"",COUNTIFS($B$2:$B$109,B35,$BP$2:$BP$109,">"&BP35)+1) -> 14 | BR35: B+ | BS35: 3
A36: 경영학과 | B36: 2 | C36: 20220142 | D36: 류사기 | E36: 010-8275-6734 | F36: 1554009081@qq.com | G36: B. 피드백 및 반복 (反馈和迭代) | H36: D. 최소한의 비용과 시간 소모 (最低限度的成本和时间消耗) | I36: C. 운영적 의사결정 (运营性决策) | J36: C. 마케팅 전략 (营销策略) | K36: C. 문제해결 (问题解决) | L36: C. 착수 → 계획 → 실행 → 마무리 (启动 → 计划 → 执行 → 结束) | M36: A. 프로젝트 콘텐츠 (项目内容/产出物) | N36: B. 비동기적 소통 (Asynchronous Communication / 异步沟通) | O36: X (거짓/错) | P36: O (참/对) | Q36: =10*SUMPRODUCT(--(G36:P36<>""),--(((G36:P36=정답표!$C$2:$L$2)+(G36:P36=정답표!$C$3:$L$3))>0)) -> 90 | R36: BPR | S36: 遵循日常运营的正式化和标准化程序。 | T36: 企业间流程 | U36: 相同数据在多个部门重复存储，导致不一致。 | V36: 引入企业信息系统（EIS） | W36: 减少不必要的审批环节，从而最大限度地减少时间和资源。 | X36: 整合管理与客户的所有互动，最大限度地提高客户终身价值。 | Y36: 将业务运营整合到一个单一且一致的计算平台。 | Z36: X | AA36: X | AB36: =10*SUMPRODUCT(--(R36:AA36<>""),--(((R36:AA36=정답표!$C$4:$L$4)+(R36:AA36=정답표!$C$5:$L$5))>0)) -> 80 | AC36: 硬件、软件、数据、流程、人员 | AD36: 组织战略决定价值链，价值链决定业务流程，业务流程决定 SMIS 需求。 | AE36: 增加物质资本 | AF36: 直接销售用户数据：通过直接销售用户个人数据获取主要收入。 | AG36: 创新 (Innovation) | AH36: 指通过电子邮件、消息应用等难以追踪的渠道进行的社交分享区域，企业应在此处关注建立信任。 | AI36: 基于兴趣形成，一个用户可以同时属于多个社区。 | AJ36: 财务与会计 | AK36: O | AL36: O | AM36: =10*SUMPRODUCT(--(AC36:AL36<>""),--(((AC36:AL36=정답표!$C$6:$L$6)+(AC36:AL36=정답표!$C$7:$L$7))>0)) -> 100 | AN36: 在风险、成本和便利性之间找到适当的平衡。 | AO36: 因为将所有安全风险降至零在现实中是不可能且低效的。 | AP36: 未应用安全补丁的旧软件 | AQ36: 威胁能够访问系统或数据并造成损害的弱点。 | AR36: 将数据转换为未经授权的人无法理解的形式以进行保护的技术。 | AS36: 根据预设规则允许或阻止网络流量。 | AT36: 主要是技术部门制定和执行的技术问题。 | AU36: 定期测试备份数据是否能实际恢复非常重要。 | AV36: O | AW36: O | AX36: =10*SUMPRODUCT(--(AN36:AW36<>""),--(((AN36:AW36=정답표!$C$8:$L$8)+(AN36:AW36=정답표!$C$9:$L$9))>0)) -> 100 | AY36: 支持IT技术以实现组织目标，并将其与经营目标相结合。 | AZ36: 有效连接信息系统(IS)战略与企业经营战略。 | BA36: 根据组织的目标和优先顺序，综合考虑战略、预算和风险。 | BB36: 谁来做信息系统相关的决策，谁来承担责任？ | BC36: 综合考虑项目的战略适用性和实际可行性。 | BD36: 将组织的部分IT功能委托给外部专业公司执行。 | BE36: 安全威胁完全消除，信息安全得到加强。 | BF36: O | BG36: O | BH36: X | BI36: =10*SUMPRODUCT(--(AY36:BH36<>""),--(((AY36:BH36=정답표!$C$10:$L$10)+(AY36:BH36=정답표!$C$11:$L$11))>0)) -> 100 | BJ36: =SUM(Q36,AB36,AM36,AX36,BI36) -> 470 | BK36: =COUNT(Q36,AB36,AM36,AX36,BI36) -> 5 | BL36: =IF(QuizMatchTable[[#This Row],[분반]]=1, QuizMatchTable[[#This Row],[퀴즈합계]]/4 *0.3, QuizMatchTable[[#This Row],[퀴즈합계]]/5*0.3) -> 28.2 | BM36: 30 | BN36: 20 | BP36: =SUM(QuizMatchTable[[#This Row],[퀴즈점수(30)]],BM36,BN36,BO36) -> 78.2 | BQ36: =IF(OR(BP36="",BP36=0,BT36="결석초과"),"",COUNTIFS($B$2:$B$109,B36,$BP$2:$BP$109,">"&BP36)+1) -> 6 | BR36: A0 | BS36: 0
A37: 경영학과 | B37: 2 | C37: 20220143 | D37: 류양 | E37: 010-8190-9167 | F37: a17638169998@163.com | G37: B. 피드백 및 반복 (反馈和迭代) | H37: D. 최소한의 비용과 시간 소모 (最低限度的成本和时间消耗) | I37: C. 운영적 의사결정 (运营性决策) | J37: C. 마케팅 전략 (营销策略) | K37: C. 문제해결 (问题解决) | L37: C. 착수 → 계획 → 실행 → 마무리 (启动 → 计划 → 执行 → 结束) | M37: A. 프로젝트 콘텐츠 (项目内容/产出物), B. 프로젝트 메타데이터 (项目元数据) | N37: B. 비동기적 소통 (Asynchronous Communication / 异步沟通) | O37: X (거짓/错) | P37: O (참/对) | Q37: =10*SUMPRODUCT(--(G37:P37<>""),--(((G37:P37=정답표!$C$2:$L$2)+(G37:P37=정답표!$C$3:$L$3))>0)) -> 100 | R37: BPR | S37: 遵循日常运营的正式化和标准化程序。 | T37: 企业间流程 | U37: 相同数据在多个部门重复存储，导致不一致。 | V37: 引入企业信息系统（EIS） | W37: 减少不必要的审批环节，从而最大限度地减少时间和资源。 | X37: 整合管理与客户的所有互动，最大限度地提高客户终身价值。 | Y37: 将业务运营整合到一个单一且一致的计算平台。 | Z37: O | AA37: O | AB37: =10*SUMPRODUCT(--(R37:AA37<>""),--(((R37:AA37=정답표!$C$4:$L$4)+(R37:AA37=정답표!$C$5:$L$5))>0)) -> 100 | AC37: 硬件、软件、数据、流程、人员 | AD37: 组织战略决定价值链，价值链决定业务流程，业务流程决定 SMIS 需求。 | AE37: 增加物质资本 | AF37: 直接销售用户数据：通过直接销售用户个人数据获取主要收入。 | AG37: 创新 (Innovation) | AH37: 指通过电子邮件、消息应用等难以追踪的渠道进行的社交分享区域，企业应在此处关注建立信任。 | AI37: 基于兴趣形成，一个用户可以同时属于多个社区。 | AJ37: 财务与会计 | AK37: O | AL37: O | AM37: =10*SUMPRODUCT(--(AC37:AL37<>""),--(((AC37:AL37=정답표!$C$6:$L$6)+(AC37:AL37=정답표!$C$7:$L$7))>0)) -> 100 | AN37: 在风险、成本和便利性之间找到适当的平衡。 | AO37: 因为将所有安全风险降至零在现实中是不可能且低效的。 | AP37: 未应用安全补丁的旧软件 | AQ37: 威胁能够访问系统或数据并造成损害的弱点。 | AR37: 将数据转换为未经授权的人无法理解的形式以进行保护的技术。 | AS37: 根据预设规则允许或阻止网络流量。 | AT37: 主要是技术部门制定和执行的技术问题。 | AU37: 定期测试备份数据是否能实际恢复非常重要。 | AV37: O | AW37: O | AX37: =10*SUMPRODUCT(--(AN37:AW37<>""),--(((AN37:AW37=정답표!$C$8:$L$8)+(AN37:AW37=정답표!$C$9:$L$9))>0)) -> 100 | AY37: 支持IT技术以实现组织目标，并将其与经营目标相结合。 | AZ37: 有效连接信息系统(IS)战略与企业经营战略。 | BA37: 根据组织的目标和优先顺序，综合考虑战略、预算和风险。 | BB37: 谁来做信息系统相关的决策，谁来承担责任？ | BC37: 综合考虑项目的战略适用性和实际可行性。 | BD37: 将组织的部分IT功能委托给外部专业公司执行。 | BE37: 安全威胁完全消除，信息安全得到加强。 | BF37: O | BG37: O | BH37: X | BI37: =10*SUMPRODUCT(--(AY37:BH37<>""),--(((AY37:BH37=정답표!$C$10:$L$10)+(AY37:BH37=정답표!$C$11:$L$11))>0)) -> 100 | BJ37: =SUM(Q37,AB37,AM37,AX37,BI37) -> 500 | BK37: =COUNT(Q37,AB37,AM37,AX37,BI37) -> 5 | BL37: =IF(QuizMatchTable[[#This Row],[분반]]=1, QuizMatchTable[[#This Row],[퀴즈합계]]/4 *0.3, QuizMatchTable[[#This Row],[퀴즈합계]]/5*0.3) -> 30 | BM37: 30 | BN37: 18.39 | BP37: =SUM(QuizMatchTable[[#This Row],[퀴즈점수(30)]],BM37,BN37,BO37) -> 78.39 | BQ37: =IF(OR(BP37="",BP37=0,BT37="결석초과"),"",COUNTIFS($B$2:$B$109,B37,$BP$2:$BP$109,">"&BP37)+1) -> 5 | BR37: A+ | BS37: 0
A38: 경영학과 | B38: 2 | C38: 20220144 | D38: 류자명 | E38: 010-5608-2165 | F38: 1293930470@qq.com | G38: B. 피드백 및 반복 (反馈和迭代) | H38: D. 최소한의 비용과 시간 소모 (最低限度的成本和时间消耗) | I38: C. 운영적 의사결정 (运营性决策) | J38: C. 마케팅 전략 (营销策略) | K38: C. 문제해결 (问题解决) | L38: C. 착수 → 계획 → 실행 → 마무리 (启动 → 计划 → 执行 → 结束) | M38: A. 프로젝트 콘텐츠 (项目内容/产出物), B. 프로젝트 메타데이터 (项目元数据) | N38: B. 비동기적 소통 (Asynchronous Communication / 异步沟通) | O38: X (거짓/错) | P38: O (참/对) | Q38: =10*SUMPRODUCT(--(G38:P38<>""),--(((G38:P38=정답표!$C$2:$L$2)+(G38:P38=정답표!$C$3:$L$3))>0)) -> 100 | R38: BPR | S38: 遵循日常运营的正式化和标准化程序。 | T38: 企业间流程 | U38: 相同数据在多个部门重复存储，导致不一致。 | V38: 引入企业信息系统（EIS） | W38: 提高决策的准确性，为实现战略目标做出贡献。 | X38: 加强与供应链合作伙伴的协作，提高物流效率。 | Y38: 实现现有分离系统之间的数据共享和通信。 | Z38: O | AA38: O | AB38: =10*SUMPRODUCT(--(R38:AA38<>""),--(((R38:AA38=정답표!$C$4:$L$4)+(R38:AA38=정답표!$C$5:$L$5))>0)) -> 70 | AC38: 硬件、软件、数据、流程、人员 | AD38: 组织战略决定价值链，价值链决定业务流程，业务流程决定 SMIS 需求。 | AE38: 增加物质资本 | AF38: 免费增值 (Freemium)：提供免费基础服务，对高级功能或去除广告收费。 | AG38: 常识 (Common Sense) | AH38: 指通过电子邮件、消息应用等难以追踪的渠道进行的社交分享区域，企业应在此处关注建立信任。 | AI38: 基于兴趣形成，一个用户可以同时属于多个社区。 | AJ38: 财务与会计 | AK38: O | AL38: O | AM38: =10*SUMPRODUCT(--(AC38:AL38<>""),--(((AC38:AL38=정답표!$C$6:$L$6)+(AC38:AL38=정답표!$C$7:$L$7))>0)) -> 80 | AN38: 在风险、成本和便利性之间找到适当的平衡。 | AO38: 因为将所有安全风险降至零在现实中是不可能且低效的。 | AP38: 未应用安全补丁的旧软件 | AQ38: 威胁能够访问系统或数据并造成损害的弱点。 | AR38: 将数据转换为未经授权的人无法理解的形式以进行保护的技术。 | AS38: 根据预设规则允许或阻止网络流量。 | AT38: 包括数据存储、处理、共享等整个组织的行为标准。 | AU38: 只需执行一次备份就足够了，之后不需要额外的管理。 | AV38: O | AW38: O | AX38: =10*SUMPRODUCT(--(AN38:AW38<>""),--(((AN38:AW38=정답표!$C$8:$L$8)+(AN38:AW38=정답표!$C$9:$L$9))>0)) -> 80 | AY38: 支持IT技术以实现组织目标，并将其与经营目标相结合。 | AZ38: 有效连接信息系统(IS)战略与企业经营战略。 | BA38: 根据组织的目标和优先顺序，综合考虑战略、预算和风险。 | BB38: 谁来做信息系统相关的决策，谁来承担责任？ | BC38: 综合考虑项目的战略适用性和实际可行性。 | BD38: 将组织的部分IT功能委托给外部专业公司执行。 | BE38: 组织对供应商的依赖度可能增加。 | BF38: O | BG38: O | BH38: X | BI38: =10*SUMPRODUCT(--(AY38:BH38<>""),--(((AY38:BH38=정답표!$C$10:$L$10)+(AY38:BH38=정답표!$C$11:$L$11))>0)) -> 90 | BJ38: =SUM(Q38,AB38,AM38,AX38,BI38) -> 420 | BK38: =COUNT(Q38,AB38,AM38,AX38,BI38) -> 5 | BL38: =IF(QuizMatchTable[[#This Row],[분반]]=1, QuizMatchTable[[#This Row],[퀴즈합계]]/4 *0.3, QuizMatchTable[[#This Row],[퀴즈합계]]/5*0.3) -> 25.2 | BM38: 30 | BN38: 18.8 | BP38: =SUM(QuizMatchTable[[#This Row],[퀴즈점수(30)]],BM38,BN38,BO38) -> 74 | BQ38: =IF(OR(BP38="",BP38=0,BT38="결석초과"),"",COUNTIFS($B$2:$B$109,B38,$BP$2:$BP$109,">"&BP38)+1) -> 17 | BR38: B0 | BS38: 0
A39: 경영학과 | B39: 2 | C39: 20220145 | D39: 류종준 | E39: 010-3917-9682 | F39: 2877642230@qq.com | G39: C. 분업 및 전문화 (分工和专业化) | H39: D. 최소한의 비용과 시간 소모 (最低限度的成本和时间消耗) | I39: C. 운영적 의사결정 (运营性决策) | J39: C. 마케팅 전략 (营销策略) | K39: C. 문제해결 (问题解决) | L39: C. 착수 → 계획 → 실행 → 마무리 (启动 → 计划 → 执行 → 结束) | M39: A. 프로젝트 콘텐츠 (项目内容/产出物), B. 프로젝트 메타데이터 (项目元数据) | N39: B. 비동기적 소통 (Asynchronous Communication / 异步沟通) | O39: X (거짓/错) | P39: O (참/对) | Q39: =10*SUMPRODUCT(--(G39:P39<>""),--(((G39:P39=정답표!$C$2:$L$2)+(G39:P39=정답표!$C$3:$L$3))>0)) -> 90 | R39: BPR | S39: 遵循日常运营的正式化和标准化程序。 | T39: 企业间流程 | U39: 相同数据在多个部门重复存储，导致不一致。 | V39: 引入企业信息系统（EIS） | W39: 减少不必要的审批环节，从而最大限度地减少时间和资源。 | X39: 整合管理与客户的所有互动，最大限度地提高客户终身价值。 | Y39: 将业务运营整合到一个单一且一致的计算平台。 | Z39: O | AA39: O | AB39: =10*SUMPRODUCT(--(R39:AA39<>""),--(((R39:AA39=정답표!$C$4:$L$4)+(R39:AA39=정답표!$C$5:$L$5))>0)) -> 100 | AC39: 硬件、软件、社区、流程、人员 | AD39: 组织战略决定价值链，价值链决定业务流程，业务流程决定 SMIS 需求。 | AE39: 增加物质资本 | AF39: 直接销售用户数据：通过直接销售用户个人数据获取主要收入。 | AG39: 创新 (Innovation) | AH39: 指通过电子邮件、消息应用等难以追踪的渠道进行的社交分享区域，企业应在此处关注建立信任。 | AI39: 基于兴趣形成，一个用户可以同时属于多个社区。 | AJ39: 财务与会计 | AK39: O | AL39: O | AM39: =10*SUMPRODUCT(--(AC39:AL39<>""),--(((AC39:AL39=정답표!$C$6:$L$6)+(AC39:AL39=정답표!$C$7:$L$7))>0)) -> 90 | AN39: 在风险、成本和便利性之间找到适当的平衡。 | AO39: 因为将所有安全风险降至零在现实中是不可能且低效的。 | AP39: 未应用安全补丁的旧软件 | AQ39: 威胁能够访问系统或数据并造成损害的弱点。 | AR39: 将数据转换为未经授权的人无法理解的形式以进行保护的技术。 | AS39: 根据预设规则允许或阻止网络流量。 | AT39: 主要是技术部门制定和执行的技术问题。 | AU39: 定期测试备份数据是否能实际恢复非常重要。 | AV39: O | AW39: O | AX39: =10*SUMPRODUCT(--(AN39:AW39<>""),--(((AN39:AW39=정답표!$C$8:$L$8)+(AN39:AW39=정답표!$C$9:$L$9))>0)) -> 100 | AY39: 支持IT技术以实现组织目标，并将其与经营目标相结合。 | AZ39: 有效连接信息系统(IS)战略与企业经营战略。 | BA39: 根据组织的目标和优先顺序，综合考虑战略、预算和风险。 | BB39: 谁来做信息系统相关的决策，谁来承担责任？ | BC39: 综合考虑项目的战略适用性和实际可行性。 | BD39: 将组织的部分IT功能委托给外部专业公司执行。 | BE39: 安全威胁完全消除，信息安全得到加强。 | BF39: O | BG39: O | BH39: X | BI39: =10*SUMPRODUCT(--(AY39:BH39<>""),--(((AY39:BH39=정답표!$C$10:$L$10)+(AY39:BH39=정답표!$C$11:$L$11))>0)) -> 100 | BJ39: =SUM(Q39,AB39,AM39,AX39,BI39) -> 480 | BK39: =COUNT(Q39,AB39,AM39,AX39,BI39) -> 5 | BL39: =IF(QuizMatchTable[[#This Row],[분반]]=1, QuizMatchTable[[#This Row],[퀴즈합계]]/4 *0.3, QuizMatchTable[[#This Row],[퀴즈합계]]/5*0.3) -> 28.8 | BM39: 30 | BN39: 18.8 | BP39: =SUM(QuizMatchTable[[#This Row],[퀴즈점수(30)]],BM39,BN39,BO39) -> 77.6 | BQ39: =IF(OR(BP39="",BP39=0,BT39="결석초과"),"",COUNTIFS($B$2:$B$109,B39,$BP$2:$BP$109,">"&BP39)+1) -> 9 | BR39: B+ | BS39: 0
A40: 경영학과 | B40: 2 | C40: 20220146 | D40: 류흔 | E40: 010-8259-5961 | F40: 893178606@qq.com | G40: A. 계획 수립 및 예산 책정 (制定计划和预算) | H40: D. 최소한의 비용과 시간 소모 (最低限度的成本和时间消耗) | I40: D. 비구조적 의사결정 (非结构性决策) | J40: C. 마케팅 전략 (营销策略) | K40: C. 문제해결 (问题解决) | L40: C. 착수 → 계획 → 실행 → 마무리 (启动 → 计划 → 执行 → 结束) | M40: A. 프로젝트 콘텐츠 (项目内容/产出物), C. 경영진 보고서 (管理层报告) | N40: C. 구조적 소통 (Structured Communication / 结构化沟通) | O40: O (참/对) | P40: O (참/对) | Q40: =10*SUMPRODUCT(--(G40:P40<>""),--(((G40:P40=정답표!$C$2:$L$2)+(G40:P40=정답표!$C$3:$L$3))>0)) -> 50 | R40: BPR | S40: 遵循日常运营的正式化和标准化程序。 | T40: 结构化流程 | U40: 相同数据在多个部门重复存储，导致不一致。 | V40: 扩大手动数据输入和管理流程 | W40: 减少不必要的审批环节，从而最大限度地减少时间和资源。 | X40: 整合管理与客户的所有互动，最大限度地提高客户终身价值。 | Y40: 将业务运营整合到一个单一且一致的计算平台。 | Z40: O | AA40: O | AB40: =10*SUMPRODUCT(--(R40:AA40<>""),--(((R40:AA40=정답표!$C$4:$L$4)+(R40:AA40=정답표!$C$5:$L$5))>0)) -> 80 | AC40: 硬件、软件、数据、流程、人员 | AD40: 组织战略决定价值链，价值链决定业务流程，业务流程决定 SMIS 需求。 | AE40: 增加物质资本 | AF40: 直接销售用户数据：通过直接销售用户个人数据获取主要收入。 | AG40: 创新 (Innovation) | AH40: 指通过电子邮件、消息应用等难以追踪的渠道进行的社交分享区域，企业应在此处关注建立信任。 | AI40: 基于兴趣形成，一个用户可以同时属于多个社区。 | AJ40: 财务与会计 | AK40: O | AL40: O | AM40: =10*SUMPRODUCT(--(AC40:AL40<>""),--(((AC40:AL40=정답표!$C$6:$L$6)+(AC40:AL40=정답표!$C$7:$L$7))>0)) -> 100 | AN40: 在风险、成本和便利性之间找到适当的平衡。 | AO40: 因为将所有安全风险降至零在现实中是不可能且低效的。 | AP40: 将备份数据分离存储在外部存储器中的措施 | AQ40: 指需要保护的有价值的信息或资产本身。 | AR40: 将数据转换为未经授权的人无法理解的形式以进行保护的技术。 | AS40: 检测并自动清除渗透到系统中的恶意代码。 | AT40: 应涵盖事故响应和安全教育等全面内容。 | AU40: 定期测试备份数据是否能实际恢复非常重要。 | AV40: O | AW40: O | AX40: =10*SUMPRODUCT(--(AN40:AW40<>""),--(((AN40:AW40=정답표!$C$8:$L$8)+(AN40:AW40=정답표!$C$9:$L$9))>0)) -> 60 | AY40: 支持IT技术以实现组织目标，并将其与经营目标相结合。 | AZ40: 有效连接信息系统(IS)战略与企业经营战略。 | BA40: 根据组织的目标和优先顺序，综合考虑战略、预算和风险。 | BB40: 谁来做信息系统相关的决策，谁来承担责任？ | BC40: 将项目名称的知名度或对外宣传效果作为重要判断依据。 | BD40: 消除组织内部对该业务的所有责任和义务的方法。 | BE40: 从长期来看，可能会产生比预期更高的成本。 | BF40: O | BG40: O | BH40: X | BI40: =10*SUMPRODUCT(--(AY40:BH40<>""),--(((AY40:BH40=정답표!$C$10:$L$10)+(AY40:BH40=정답표!$C$11:$L$11))>0)) -> 70 | BJ40: =SUM(Q40,AB40,AM40,AX40,BI40) -> 360 | BK40: =COUNT(Q40,AB40,AM40,AX40,BI40) -> 5 | BL40: =IF(QuizMatchTable[[#This Row],[분반]]=1, QuizMatchTable[[#This Row],[퀴즈합계]]/4 *0.3, QuizMatchTable[[#This Row],[퀴즈합계]]/5*0.3) -> 21.6 | BM40: 30 | BN40: 18.8 | BP40: =SUM(QuizMatchTable[[#This Row],[퀴즈점수(30)]],BM40,BN40,BO40) -> 70.4 | BQ40: =IF(OR(BP40="",BP40=0,BT40="결석초과"),"",COUNTIFS($B$2:$B$109,B40,$BP$2:$BP$109,">"&BP40)+1) -> 21 | BR40: F | BS40: 0
A41: 경영학과 | B41: 2 | C41: 20220147 | D41: 맹수 | E41: 010-7327-1581 | F41: goddes778877@gmail.com | G41: D. 자원 할당 및 통제 (资源分配和控制) | H41: D. 최소한의 비용과 시간 소모 (最低限度的成本和时间消耗) | I41: D. 비구조적 의사결정 (非结构性决策) | J41: C. 마케팅 전략 (营销策略) | K41: C. 문제해결 (问题解决) | L41: C. 착수 → 계획 → 실행 → 마무리 (启动 → 计划 → 执行 → 结束) | M41: A. 프로젝트 콘텐츠 (项目内容/产出物), B. 프로젝트 메타데이터 (项目元数据) | N41: B. 비동기적 소통 (Asynchronous Communication / 异步沟通) | O41: X (거짓/错) | P41: O (참/对) | Q41: =10*SUMPRODUCT(--(G41:P41<>""),--(((G41:P41=정답표!$C$2:$L$2)+(G41:P41=정답표!$C$3:$L$3))>0)) -> 80 | R41: BPR | S41: 遵循日常运营的正式化和标准化程序。 | T41: 企业间流程 | U41: 相同数据在多个部门重复存储，导致不一致。 | V41: 引入企业信息系统（EIS） | W41: 减少不必要的审批环节，从而最大限度地减少时间和资源。 | X41: 整合管理与客户的所有互动，最大限度地提高客户终身价值。 | Y41: 将业务运营整合到一个单一且一致的计算平台。 | Z41: O | AA41: O | AB41: =10*SUMPRODUCT(--(R41:AA41<>""),--(((R41:AA41=정답표!$C$4:$L$4)+(R41:AA41=정답표!$C$5:$L$5))>0)) -> 100 | AC41: 硬件、软件、数据、流程、人员 | AD41: 组织战略决定价值链，价值链决定业务流程，业务流程决定 SMIS 需求。 | AE41: 增加物质资本 | AF41: 直接销售用户数据：通过直接销售用户个人数据获取主要收入。 | AG41: 创新 (Innovation) | AH41: 指通过电子邮件、消息应用等难以追踪的渠道进行的社交分享区域，企业应在此处关注建立信任。 | AI41: 基于兴趣形成，一个用户可以同时属于多个社区。 | AJ41: 财务与会计 | AK41: O | AL41: O | AM41: =10*SUMPRODUCT(--(AC41:AL41<>""),--(((AC41:AL41=정답표!$C$6:$L$6)+(AC41:AL41=정답표!$C$7:$L$7))>0)) -> 100 | AN41: 在风险、成本和便利性之间找到适当的平衡。 | AO41: 因为将所有安全风险降至零在现实中是不可能且低效的。 | AP41: 未应用安全补丁的旧软件 | AQ41: 威胁能够访问系统或数据并造成损害的弱点。 | AR41: 将数据转换为未经授权的人无法理解的形式以进行保护的技术。 | AS41: 根据预设规则允许或阻止网络流量。 | AT41: 主要是技术部门制定和执行的技术问题。 | AU41: 定期测试备份数据是否能实际恢复非常重要。 | AV41: O | AW41: O | AX41: =10*SUMPRODUCT(--(AN41:AW41<>""),--(((AN41:AW41=정답표!$C$8:$L$8)+(AN41:AW41=정답표!$C$9:$L$9))>0)) -> 100 | AY41: 支持IT技术以实现组织目标，并将其与经营目标相结合。 | AZ41: 有效连接信息系统(IS)战略与企业经营战略。 | BA41: 根据组织的目标和优先顺序，综合考虑战略、预算和风险。 | BB41: 谁来做信息系统相关的决策，谁来承担责任？ | BC41: 综合考虑项目的战略适用性和实际可行性。 | BD41: 将组织的部分IT功能委托给外部专业公司执行。 | BE41: 安全威胁完全消除，信息安全得到加强。 | BF41: O | BG41: O | BH41: X | BI41: =10*SUMPRODUCT(--(AY41:BH41<>""),--(((AY41:BH41=정답표!$C$10:$L$10)+(AY41:BH41=정답표!$C$11:$L$11))>0)) -> 100 | BJ41: =SUM(Q41,AB41,AM41,AX41,BI41) -> 480 | BK41: =COUNT(Q41,AB41,AM41,AX41,BI41) -> 5 | BL41: =IF(QuizMatchTable[[#This Row],[분반]]=1, QuizMatchTable[[#This Row],[퀴즈합계]]/4 *0.3, QuizMatchTable[[#This Row],[퀴즈합계]]/5*0.3) -> 28.8 | BM41: 30 | BN41: 19.6 | BP41: =SUM(QuizMatchTable[[#This Row],[퀴즈점수(30)]],BM41,BN41,BO41) -> 78.4 | BQ41: =IF(OR(BP41="",BP41=0,BT41="결석초과"),"",COUNTIFS($B$2:$B$109,B41,$BP$2:$BP$109,">"&BP41)+1) -> 4 | BR41: A+ | BS41: 0
A42: 경영학과 | B42: 2 | C42: 20220149 | D42: 반림 | E42: 010-7515-5123 | F42: 1350572443@qq.com | G42: C. 분업 및 전문화 (分工和专业化) | H42: D. 최소한의 비용과 시간 소모 (最低限度的成本和时间消耗) | I42: C. 운영적 의사결정 (运营性决策) | J42: C. 마케팅 전략 (营销策略) | K42: C. 문제해결 (问题解决) | L42: C. 착수 → 계획 → 실행 → 마무리 (启动 → 计划 → 执行 → 结束) | M42: B. 프로젝트 메타데이터 (项目元数据) | N42: B. 비동기적 소통 (Asynchronous Communication / 异步沟通) | O42: X (거짓/错) | P42: O (참/对) | Q42: =10*SUMPRODUCT(--(G42:P42<>""),--(((G42:P42=정답표!$C$2:$L$2)+(G42:P42=정답표!$C$3:$L$3))>0)) -> 80 | R42: BPR | S42: 遵循日常运营的正式化和标准化程序。 | T42: 企业级流程 | U42: 相同数据在多个部门重复存储，导致不一致。 | V42: 引入企业信息系统（EIS） | W42: 减少不必要的审批环节，从而最大限度地减少时间和资源。 | X42: 整合管理与客户的所有互动，最大限度地提高客户终身价值。 | Y42: 将业务运营整合到一个单一且一致的计算平台。 | Z42: O | AA42: O | AB42: =10*SUMPRODUCT(--(R42:AA42<>""),--(((R42:AA42=정답표!$C$4:$L$4)+(R42:AA42=정답표!$C$5:$L$5))>0)) -> 90 | AC42: 硬件、软件、数据、流程、人员 | AD42: 组织战略决定价值链，价值链决定业务流程，业务流程决定 SMIS 需求。 | AE42: 增加物质资本 | AF42: 直接销售用户数据：通过直接销售用户个人数据获取主要收入。 | AG42: 创新 (Innovation) | AH42: 指通过电子邮件、消息应用等难以追踪的渠道进行的社交分享区域，企业应在此处关注建立信任。 | AI42: 基于兴趣形成，一个用户可以同时属于多个社区。 | AJ42: 制造与运营 | AK42: O | AL42: O | AM42: =10*SUMPRODUCT(--(AC42:AL42<>""),--(((AC42:AL42=정답표!$C$6:$L$6)+(AC42:AL42=정답표!$C$7:$L$7))>0)) -> 90 | AN42: 在风险、成本和便利性之间找到适当的平衡。 | AO42: 因为将所有安全风险降至零在现实中是不可能且低效的。 | AP42: 未应用安全补丁的旧软件 | AQ42: 威胁能够访问系统或数据并造成损害的弱点。 | AR42: 将数据转换为未经授权的人无法理解的形式以进行保护的技术。 | AS42: 根据预设规则允许或阻止网络流量。 | AT42: 主要是技术部门制定和执行的技术问题。 | AU42: 定期测试备份数据是否能实际恢复非常重要。 | AV42: O | AW42: O | AX42: =10*SUMPRODUCT(--(AN42:AW42<>""),--(((AN42:AW42=정답표!$C$8:$L$8)+(AN42:AW42=정답표!$C$9:$L$9))>0)) -> 100 | AY42: 支持IT技术以实现组织目标，并将其与经营目标相结合。 | AZ42: 有效连接信息系统(IS)战略与企业经营战略。 | BA42: 根据组织的目标和优先顺序，综合考虑战略、预算和风险。 | BB42: 谁来做信息系统相关的决策，谁来承担责任？ | BC42: 综合考虑项目的战略适用性和实际可行性。 | BD42: 将组织的部分IT功能委托给外部专业公司执行。 | BE42: 安全威胁完全消除，信息安全得到加强。 | BF42: O | BG42: O | BH42: X | BI42: =10*SUMPRODUCT(--(AY42:BH42<>""),--(((AY42:BH42=정답표!$C$10:$L$10)+(AY42:BH42=정답표!$C$11:$L$11))>0)) -> 100 | BJ42: =SUM(Q42,AB42,AM42,AX42,BI42) -> 460 | BK42: =COUNT(Q42,AB42,AM42,AX42,BI42) -> 5 | BL42: =IF(QuizMatchTable[[#This Row],[분반]]=1, QuizMatchTable[[#This Row],[퀴즈합계]]/4 *0.3, QuizMatchTable[[#This Row],[퀴즈합계]]/5*0.3) -> 27.6 | BM42: 26 | BN42: 12.8 | BP42: =SUM(QuizMatchTable[[#This Row],[퀴즈점수(30)]],BM42,BN42,BO42) -> 66.4 | BQ42: =IF(OR(BP42="",BP42=0,BT42="결석초과"),"",COUNTIFS($B$2:$B$109,B42,$BP$2:$BP$109,">"&BP42)+1) -> 28 | BR42: F | BS42: 6
A43: 경영학과 | B43: 2 | C43: 20220151 | D43: 성개 | E43: 010-5804-6056 | F43: 3026851997@qq.com | G43: B. 피드백 및 반복 (反馈和迭代) | H43: D. 최소한의 비용과 시간 소모 (最低限度的成本和时间消耗) | I43: C. 운영적 의사결정 (运营性决策) | J43: C. 마케팅 전략 (营销策略) | K43: C. 문제해결 (问题解决) | L43: C. 착수 → 계획 → 실행 → 마무리 (启动 → 计划 → 执行 → 结束) | M43: A. 프로젝트 콘텐츠 (项目内容/产出物), B. 프로젝트 메타데이터 (项目元数据) | N43: B. 비동기적 소통 (Asynchronous Communication / 异步沟通) | O43: X (거짓/错) | P43: O (참/对) | Q43: =10*SUMPRODUCT(--(G43:P43<>""),--(((G43:P43=정답표!$C$2:$L$2)+(G43:P43=정답표!$C$3:$L$3))>0)) -> 100 | R43: BPR | S43: 遵循日常运营的正式化和标准化程序。 | T43: 企业间流程 | U43: 相同数据在多个部门重复存储，导致不一致。 | V43: 引入企业信息系统（EIS） | W43: 减少不必要的审批环节，从而最大限度地减少时间和资源。 | X43: 整合管理与客户的所有互动，最大限度地提高客户终身价值。 | Y43: 将业务运营整合到一个单一且一致的计算平台。 | Z43: O | AA43: O | AB43: =10*SUMPRODUCT(--(R43:AA43<>""),--(((R43:AA43=정답표!$C$4:$L$4)+(R43:AA43=정답표!$C$5:$L$5))>0)) -> 100 | AC43: 硬件、软件、数据、流程、人员 | AD43: 组织战略决定价值链，价值链决定业务流程，业务流程决定 SMIS 需求。 | AE43: 增加物质资本 | AF43: 直接销售用户数据：通过直接销售用户个人数据获取主要收入。 | AG43: 创新 (Innovation) | AH43: 指通过电子邮件、消息应用等难以追踪的渠道进行的社交分享区域，企业应在此处关注建立信任。 | AI43: 基于兴趣形成，一个用户可以同时属于多个社区。 | AJ43: 财务与会计 | AK43: O | AL43: O | AM43: =10*SUMPRODUCT(--(AC43:AL43<>""),--(((AC43:AL43=정답표!$C$6:$L$6)+(AC43:AL43=정답표!$C$7:$L$7))>0)) -> 100 | AN43: 在风险、成本和便利性之间找到适当的平衡。 | AO43: 因为将所有安全风险降至零在现实中是不可能且低效的。 | AP43: 未应用安全补丁的旧软件 | AQ43: 威胁能够访问系统或数据并造成损害的弱点。 | AR43: 将数据转换为未经授权的人无法理解的形式以进行保护的技术。 | AS43: 根据预设规则允许或阻止网络流量。 | AT43: 主要是技术部门制定和执行的技术问题。 | AU43: 定期测试备份数据是否能实际恢复非常重要。 | AV43: O | AW43: O | AX43: =10*SUMPRODUCT(--(AN43:AW43<>""),--(((AN43:AW43=정답표!$C$8:$L$8)+(AN43:AW43=정답표!$C$9:$L$9))>0)) -> 100 | AY43: 支持IT技术以实现组织目标，并将其与经营目标相结合。 | AZ43: 有效连接信息系统(IS)战略与企业经营战略。 | BA43: 根据组织的目标和优先顺序，综合考虑战略、预算和风险。 | BB43: 谁来做信息系统相关的决策，谁来承担责任？ | BC43: 综合考虑项目的战略适用性和实际可行性。 | BD43: 将组织的部分IT功能委托给外部专业公司执行。 | BE43: 安全威胁完全消除，信息安全得到加强。 | BF43: O | BG43: O | BH43: X | BI43: =10*SUMPRODUCT(--(AY43:BH43<>""),--(((AY43:BH43=정답표!$C$10:$L$10)+(AY43:BH43=정답표!$C$11:$L$11))>0)) -> 100 | BJ43: =SUM(Q43,AB43,AM43,AX43,BI43) -> 500 | BK43: =COUNT(Q43,AB43,AM43,AX43,BI43) -> 5 | BL43: =IF(QuizMatchTable[[#This Row],[분반]]=1, QuizMatchTable[[#This Row],[퀴즈합계]]/4 *0.3, QuizMatchTable[[#This Row],[퀴즈합계]]/5*0.3) -> 30 | BM43: 30 | BN43: 14 | BP43: =SUM(QuizMatchTable[[#This Row],[퀴즈점수(30)]],BM43,BN43,BO43) -> 74 | BQ43: =IF(OR(BP43="",BP43=0,BT43="결석초과"),"",COUNTIFS($B$2:$B$109,B43,$BP$2:$BP$109,">"&BP43)+1) -> 17 | BR43: B0 | BS43: 0
A44: 경영학과 | B44: 2 | C44: 20220152 | D44: 손가의 | E44: 010-5926-0216 | F44: sunjiayi325@gmail.com | G44: B. 피드백 및 반복 (反馈和迭代) | H44: D. 최소한의 비용과 시간 소모 (最低限度的成本和时间消耗) | I44: C. 운영적 의사결정 (运营性决策) | J44: C. 마케팅 전략 (营销策略) | K44: C. 문제해결 (问题解决) | L44: C. 착수 → 계획 → 실행 → 마무리 (启动 → 计划 → 执行 → 结束) | M44: A. 프로젝트 콘텐츠 (项目内容/产出物), B. 프로젝트 메타데이터 (项目元数据) | N44: B. 비동기적 소통 (Asynchronous Communication / 异步沟通) | O44: X (거짓/错) | P44: O (참/对) | Q44: =10*SUMPRODUCT(--(G44:P44<>""),--(((G44:P44=정답표!$C$2:$L$2)+(G44:P44=정답표!$C$3:$L$3))>0)) -> 100 | R44: ERP | S44: 支持战略性和非例行性的经营决策。 | T44: 企业级流程 | U44: 相同数据在多个部门重复存储，导致不一致。 | V44: 引入企业信息系统（EIS） | W44: 提高决策的准确性，为实现战略目标做出贡献。 | X44: 整合管理与客户的所有互动，最大限度地提高客户终身价值。 | Y44: 实现现有分离系统之间的数据共享和通信。 | Z44: O | AA44: O | AB44: =10*SUMPRODUCT(--(R44:AA44<>""),--(((R44:AA44=정답표!$C$4:$L$4)+(R44:AA44=정답표!$C$5:$L$5))>0)) -> 50 | AC44: 硬件、软件、数据、流程、人员 | AD44: SMIS 需求首先被确定，然后影响价值链和组织战略。 | AE44: 个人赋能 | AF44: 直接销售用户数据：通过直接销售用户个人数据获取主要收入。 | AG44: 常识 (Common Sense) | AH44: 指人工智能 (AI) 生成的假新闻或深度伪造内容在社交媒体上传播的阴暗面。 | AI44: 基于兴趣形成，一个用户可以同时属于多个社区。 | AJ44: 财务与会计 | AK44: O | AL44: O | AM44: =10*SUMPRODUCT(--(AC44:AL44<>""),--(((AC44:AL44=정답표!$C$6:$L$6)+(AC44:AL44=정답표!$C$7:$L$7))>0)) -> 60 | AN44: 在风险、成本和便利性之间找到适当的平衡。 | AO44: 因为将所有安全风险降至零在现实中是不可能且低效的。 | AP44: 未应用安全补丁的旧软件 | AQ44: 威胁能够访问系统或数据并造成损害的弱点。 | AR44: 将数据转换为未经授权的人无法理解的形式以进行保护的技术。 | AS44: 检测并自动清除渗透到系统中的恶意代码。 | AT44: 主要是技术部门制定和执行的技术问题。 | AU44: 定期测试备份数据是否能实际恢复非常重要。 | AV44: O | AW44: O | AX44: =10*SUMPRODUCT(--(AN44:AW44<>""),--(((AN44:AW44=정답표!$C$8:$L$8)+(AN44:AW44=정답표!$C$9:$L$9))>0)) -> 90 | AY44: 支持IT技术以实现组织目标，并将其与经营目标相结合。 | AZ44: 有效连接信息系统(IS)战略与企业经营战略。 | BA44: 根据组织的目标和优先顺序，综合考虑战略、预算和风险。 | BB44: 谁来做信息系统相关的决策，谁来承担责任？ | BC44: 综合考虑项目的战略适用性和实际可行性。 | BD44: 将组织的部分IT功能委托给外部专业公司执行。 | BE44: 安全威胁完全消除，信息安全得到加强。 | BF44: O | BG44: O | BH44: X | BI44: =10*SUMPRODUCT(--(AY44:BH44<>""),--(((AY44:BH44=정답표!$C$10:$L$10)+(AY44:BH44=정답표!$C$11:$L$11))>0)) -> 100 | BJ44: =SUM(Q44,AB44,AM44,AX44,BI44) -> 400 | BK44: =COUNT(Q44,AB44,AM44,AX44,BI44) -> 5 | BL44: =IF(QuizMatchTable[[#This Row],[분반]]=1, QuizMatchTable[[#This Row],[퀴즈합계]]/4 *0.3, QuizMatchTable[[#This Row],[퀴즈합계]]/5*0.3) -> 24 | BM44: 30 | BN44: 18.8 | BP44: =SUM(QuizMatchTable[[#This Row],[퀴즈점수(30)]],BM44,BN44,BO44) -> 72.8 | BQ44: =IF(OR(BP44="",BP44=0,BT44="결석초과"),"",COUNTIFS($B$2:$B$109,B44,$BP$2:$BP$109,">"&BP44)+1) -> 20 | BR44: F | BS44: 0
A45: 경영학과 | B45: 2 | C45: 20220153 | D45: 손정의 | E45: 010-5596-8011 | F45: 3446523506@qq.com | G45: C. 분업 및 전문화 (分工和专业化) | H45: D. 최소한의 비용과 시간 소모 (最低限度的成本和时间消耗) | I45: C. 운영적 의사결정 (运营性决策) | J45: C. 마케팅 전략 (营销策略) | K45: C. 문제해결 (问题解决) | L45: C. 착수 → 계획 → 실행 → 마무리 (启动 → 计划 → 执行 → 结束) | M45: A. 프로젝트 콘텐츠 (项目内容/产出物), B. 프로젝트 메타데이터 (项目元数据) | N45: B. 비동기적 소통 (Asynchronous Communication / 异步沟通) | O45: X (거짓/错) | P45: O (참/对) | Q45: =10*SUMPRODUCT(--(G45:P45<>""),--(((G45:P45=정답표!$C$2:$L$2)+(G45:P45=정답표!$C$3:$L$3))>0)) -> 90 | R45: BPR | S45: 遵循日常运营的正式化和标准化程序。 | T45: 企业间流程 | U45: 相同数据在多个部门重复存储，导致不一致。 | V45: 引入企业信息系统（EIS） | W45: 减少不必要的审批环节，从而最大限度地减少时间和资源。 | X45: 整合管理与客户的所有互动，最大限度地提高客户终身价值。 | Y45: 将业务运营整合到一个单一且一致的计算平台。 | Z45: O | AA45: O | AB45: =10*SUMPRODUCT(--(R45:AA45<>""),--(((R45:AA45=정답표!$C$4:$L$4)+(R45:AA45=정답표!$C$5:$L$5))>0)) -> 100 | AC45: 硬件、软件、数据、流程、人员 | AD45: 组织战略决定价值链，价值链决定业务流程，业务流程决定 SMIS 需求。 | AE45: 增加物质资本 | AF45: 直接销售用户数据：通过直接销售用户个人数据获取主要收入。 | AG45: 创新 (Innovation) | AH45: 指通过电子邮件、消息应用等难以追踪的渠道进行的社交分享区域，企业应在此处关注建立信任。 | AI45: 基于兴趣形成，一个用户可以同时属于多个社区。 | AJ45: 财务与会计 | AK45: O | AL45: O | AM45: =10*SUMPRODUCT(--(AC45:AL45<>""),--(((AC45:AL45=정답표!$C$6:$L$6)+(AC45:AL45=정답표!$C$7:$L$7))>0)) -> 100 | AN45: 在风险、成本和便利性之间找到适当的平衡。 | AO45: 因为将所有安全风险降至零在现实中是不可能且低效的。 | AP45: 未应用安全补丁的旧软件 | AQ45: 威胁能够访问系统或数据并造成损害的弱点。 | AR45: 将数据转换为未经授权的人无法理解的形式以进行保护的技术。 | AS45: 根据预设规则允许或阻止网络流量。 | AT45: 主要是技术部门制定和执行的技术问题。 | AU45: 定期测试备份数据是否能实际恢复非常重要。 | AV45: O | AW45: O | AX45: =10*SUMPRODUCT(--(AN45:AW45<>""),--(((AN45:AW45=정답표!$C$8:$L$8)+(AN45:AW45=정답표!$C$9:$L$9))>0)) -> 100 | AY45: 支持IT技术以实现组织目标，并将其与经营目标相结合。 | AZ45: 有效连接信息系统(IS)战略与企业经营战略。 | BA45: 根据组织的目标和优先顺序，综合考虑战略、预算和风险。 | BB45: 谁来做信息系统相关的决策，谁来承担责任？ | BC45: 综合考虑项目的战略适用性和实际可行性。 | BD45: 将组织的所有核心能力完全转移给外部公司。 | BE45: 安全威胁完全消除，信息安全得到加强。 | BF45: O | BG45: O | BH45: X | BI45: =10*SUMPRODUCT(--(AY45:BH45<>""),--(((AY45:BH45=정답표!$C$10:$L$10)+(AY45:BH45=정답표!$C$11:$L$11))>0)) -> 90 | BJ45: =SUM(Q45,AB45,AM45,AX45,BI45) -> 480 | BK45: =COUNT(Q45,AB45,AM45,AX45,BI45) -> 5 | BL45: =IF(QuizMatchTable[[#This Row],[분반]]=1, QuizMatchTable[[#This Row],[퀴즈합계]]/4 *0.3, QuizMatchTable[[#This Row],[퀴즈합계]]/5*0.3) -> 28.8 | BM45: 30 | BN45: 18.8 | BP45: =SUM(QuizMatchTable[[#This Row],[퀴즈점수(30)]],BM45,BN45,BO45) -> 77.6 | BQ45: =IF(OR(BP45="",BP45=0,BT45="결석초과"),"",COUNTIFS($B$2:$B$109,B45,$BP$2:$BP$109,">"&BP45)+1) -> 9 | BR45: B+ | BS45: 0
A46: 경영학과 | B46: 2 | C46: 20220154 | D46: 시지열 | E46: 010-6729-0752 | F46: 2733987239@qq.com | G46: C. 분업 및 전문화 (分工和专业化) | H46: D. 최소한의 비용과 시간 소모 (最低限度的成本和时间消耗) | I46: C. 운영적 의사결정 (运营性决策) | J46: C. 마케팅 전략 (营销策略) | K46: C. 문제해결 (问题解决) | L46: C. 착수 → 계획 → 실행 → 마무리 (启动 → 计划 → 执行 → 结束) | M46: A. 프로젝트 콘텐츠 (项目内容/产出物), B. 프로젝트 메타데이터 (项目元数据) | N46: B. 비동기적 소통 (Asynchronous Communication / 异步沟通) | O46: X (거짓/错) | Q46: =10*SUMPRODUCT(--(G46:P46<>""),--(((G46:P46=정답표!$C$2:$L$2)+(G46:P46=정답표!$C$3:$L$3))>0)) -> 80 | R46: BPR | S46: 遵循日常运营的正式化和标准化程序。 | T46: 企业间流程 | U46: 相同数据在多个部门重复存储，导致不一致。 | V46: 引入企业信息系统（EIS） | W46: 减少不必要的审批环节，从而最大限度地减少时间和资源。 | X46: 整合管理与客户的所有互动，最大限度地提高客户终身价值。 | Y46: 将业务运营整合到一个单一且一致的计算平台。 | Z46: O | AA46: O | AB46: =10*SUMPRODUCT(--(R46:AA46<>""),--(((R46:AA46=정답표!$C$4:$L$4)+(R46:AA46=정답표!$C$5:$L$5))>0)) -> 100 | AC46: 硬件、软件、社区、流程、人员 | AD46: 组织战略决定价值链，价值链决定业务流程，业务流程决定 SMIS 需求。 | AE46: 增加物质资本 | AF46: 直接销售用户数据：通过直接销售用户个人数据获取主要收入。 | AG46: 创新 (Innovation) | AH46: 指通过电子邮件、消息应用等难以追踪的渠道进行的社交分享区域，企业应在此处关注建立信任。 | AI46: 基于兴趣形成，一个用户可以同时属于多个社区。 | AJ46: 财务与会计 | AK46: O | AL46: O | AM46: =10*SUMPRODUCT(--(AC46:AL46<>""),--(((AC46:AL46=정답표!$C$6:$L$6)+(AC46:AL46=정답표!$C$7:$L$7))>0)) -> 90 | AN46: 在风险、成本和便利性之间找到适当的平衡。 | AO46: 因为将所有安全风险降至零在现实中是不可能且低效的。 | AP46: 未应用安全补丁的旧软件 | AQ46: 威胁能够访问系统或数据并造成损害的弱点。 | AR46: 将数据转换为未经授权的人无法理解的形式以进行保护的技术。 | AS46: 根据预设规则允许或阻止网络流量。 | AT46: 主要是技术部门制定和执行的技术问题。 | AU46: 定期测试备份数据是否能实际恢复非常重要。 | AV46: O | AW46: O | AX46: =10*SUMPRODUCT(--(AN46:AW46<>""),--(((AN46:AW46=정답표!$C$8:$L$8)+(AN46:AW46=정답표!$C$9:$L$9))>0)) -> 100 | AY46: 支持IT技术以实现组织目标，并将其与经营目标相结合。 | AZ46: 有效连接信息系统(IS)战略与企业经营战略。 | BA46: 根据组织的目标和优先顺序，综合考虑战略、预算和风险。 | BB46: 谁来做信息系统相关的决策，谁来承担责任？ | BC46: 综合考虑项目的战略适用性和实际可行性。 | BD46: 将组织的部分IT功能委托给外部专业公司执行。 | BE46: 安全威胁完全消除，信息安全得到加强。 | BF46: O | BG46: O | BH46: X | BI46: =10*SUMPRODUCT(--(AY46:BH46<>""),--(((AY46:BH46=정답표!$C$10:$L$10)+(AY46:BH46=정답표!$C$11:$L$11))>0)) -> 100 | BJ46: =SUM(Q46,AB46,AM46,AX46,BI46) -> 470 | BK46: =COUNT(Q46,AB46,AM46,AX46,BI46) -> 5 | BL46: =IF(QuizMatchTable[[#This Row],[분반]]=1, QuizMatchTable[[#This Row],[퀴즈합계]]/4 *0.3, QuizMatchTable[[#This Row],[퀴즈합계]]/5*0.3) -> 28.2 | BM46: 30 | BN46: 20 | BP46: =SUM(QuizMatchTable[[#This Row],[퀴즈점수(30)]],BM46,BN46,BO46) -> 78.2 | BQ46: =IF(OR(BP46="",BP46=0,BT46="결석초과"),"",COUNTIFS($B$2:$B$109,B46,$BP$2:$BP$109,">"&BP46)+1) -> 6 | BR46: A0 | BS46: 0
A47: 경영학과 | B47: 2 | C47: 20220159 | D47: 완정 | E47: 010-5749-8946 | F47: 2874356979@qq.com | G47: B. 피드백 및 반복 (反馈和迭代) | H47: D. 최소한의 비용과 시간 소모 (最低限度的成本和时间消耗) | I47: C. 운영적 의사결정 (运营性决策) | J47: C. 마케팅 전략 (营销策略) | K47: C. 문제해결 (问题解决) | L47: C. 착수 → 계획 → 실행 → 마무리 (启动 → 计划 → 执行 → 结束) | M47: A. 프로젝트 콘텐츠 (项目内容/产出物), B. 프로젝트 메타데이터 (项目元数据) | N47: B. 비동기적 소통 (Asynchronous Communication / 异步沟通) | O47: X (거짓/错) | P47: O (참/对) | Q47: =10*SUMPRODUCT(--(G47:P47<>""),--(((G47:P47=정답표!$C$2:$L$2)+(G47:P47=정답표!$C$3:$L$3))>0)) -> 100 | R47: BPR | S47: 遵循日常运营的正式化和标准化程序。 | T47: 企业间流程 | U47: 相同数据在多个部门重复存储，导致不一致。 | V47: 引入企业信息系统（EIS） | W47: 减少不必要的审批环节，从而最大限度地减少时间和资源。 | X47: 整合管理与客户的所有互动，最大限度地提高客户终身价值。 | Y47: 将业务运营整合到一个单一且一致的计算平台。 | Z47: O | AA47: O | AB47: =10*SUMPRODUCT(--(R47:AA47<>""),--(((R47:AA47=정답표!$C$4:$L$4)+(R47:AA47=정답표!$C$5:$L$5))>0)) -> 100 | AC47: 硬件、软件、数据、流程、人员 | AD47: 组织战略决定价值链，价值链决定业务流程，业务流程决定 SMIS 需求。 | AE47: 增加物质资本 | AF47: 直接销售用户数据：通过直接销售用户个人数据获取主要收入。 | AG47: 创新 (Innovation) | AH47: 指通过电子邮件、消息应用等难以追踪的渠道进行的社交分享区域，企业应在此处关注建立信任。 | AI47: 基于兴趣形成，一个用户可以同时属于多个社区。 | AJ47: 财务与会计 | AK47: O | AL47: O | AM47: =10*SUMPRODUCT(--(AC47:AL47<>""),--(((AC47:AL47=정답표!$C$6:$L$6)+(AC47:AL47=정답표!$C$7:$L$7))>0)) -> 100 | AN47: 在风险、成本和便利性之间找到适当的平衡。 | AO47: 因为将所有安全风险降至零在现实中是不可能且低效的。 | AP47: 未应用安全补丁的旧软件 | AQ47: 威胁能够访问系统或数据并造成损害的弱点。 | AR47: 将数据转换为未经授权的人无法理解的形式以进行保护的技术。 | AS47: 根据预设规则允许或阻止网络流量。 | AT47: 主要是技术部门制定和执行的技术问题。 | AU47: 定期测试备份数据是否能实际恢复非常重要。 | AV47: O | AW47: O | AX47: =10*SUMPRODUCT(--(AN47:AW47<>""),--(((AN47:AW47=정답표!$C$8:$L$8)+(AN47:AW47=정답표!$C$9:$L$9))>0)) -> 100 | AY47: 支持IT技术以实现组织目标，并将其与经营目标相结合。 | AZ47: 有效连接信息系统(IS)战略与企业经营战略。 | BA47: 根据组织的目标和优先顺序，综合考虑战略、预算和风险。 | BB47: 谁来做信息系统相关的决策，谁来承担责任？ | BC47: 综合考虑项目的战略适用性和实际可行性。 | BD47: 将组织的部分IT功能委托给外部专业公司执行。 | BE47: 从长期来看，可能会产生比预期更高的成本。 | BF47: O | BG47: O | BH47: X | BI47: =10*SUMPRODUCT(--(AY47:BH47<>""),--(((AY47:BH47=정답표!$C$10:$L$10)+(AY47:BH47=정답표!$C$11:$L$11))>0)) -> 90 | BJ47: =SUM(Q47,AB47,AM47,AX47,BI47) -> 490 | BK47: =COUNT(Q47,AB47,AM47,AX47,BI47) -> 5 | BL47: =IF(QuizMatchTable[[#This Row],[분반]]=1, QuizMatchTable[[#This Row],[퀴즈합계]]/4 *0.3, QuizMatchTable[[#This Row],[퀴즈합계]]/5*0.3) -> 29.4 | BM47: 28 | BN47: 18.8 | BP47: =SUM(QuizMatchTable[[#This Row],[퀴즈점수(30)]],BM47,BN47,BO47) -> 76.2 | BQ47: =IF(OR(BP47="",BP47=0,BT47="결석초과"),"",COUNTIFS($B$2:$B$109,B47,$BP$2:$BP$109,">"&BP47)+1) -> 14 | BR47: B+ | BS47: 3
A48: 경영학과 | B48: 2 | C48: 20220169 | D48: 이소 | E48: 010-8116-5763 | F48: 2529534160@qq.com | G48: C. 분업 및 전문화 (分工和专业化) | H48: D. 최소한의 비용과 시간 소모 (最低限度的成本和时间消耗) | I48: C. 운영적 의사결정 (运营性决策) | J48: C. 마케팅 전략 (营销策略) | K48: C. 문제해결 (问题解决) | L48: C. 착수 → 계획 → 실행 → 마무리 (启动 → 计划 → 执行 → 结束) | M48: A. 프로젝트 콘텐츠 (项目内容/产出物), B. 프로젝트 메타데이터 (项目元数据) | N48: B. 비동기적 소통 (Asynchronous Communication / 异步沟通) | O48: X (거짓/错) | P48: O (참/对) | Q48: =10*SUMPRODUCT(--(G48:P48<>""),--(((G48:P48=정답표!$C$2:$L$2)+(G48:P48=정답표!$C$3:$L$3))>0)) -> 90 | R48: BPR | S48: 遵循日常运营的正式化和标准化程序。 | T48: 企业间流程 | U48: 相同数据在多个部门重复存储，导致不一致。 | V48: 引入企业信息系统（EIS） | W48: 减少不必要的审批环节，从而最大限度地减少时间和资源。 | X48: 整合管理与客户的所有互动，最大限度地提高客户终身价值。 | Y48: 将业务运营整合到一个单一且一致的计算平台。 | Z48: O | AA48: O | AB48: =10*SUMPRODUCT(--(R48:AA48<>""),--(((R48:AA48=정답표!$C$4:$L$4)+(R48:AA48=정답표!$C$5:$L$5))>0)) -> 100 | AC48: 硬件、软件、社区、流程、人员 | AD48: 组织战略决定价值链，价值链决定业务流程，业务流程决定 SMIS 需求。 | AE48: 增加物质资本 | AF48: 直接销售用户数据：通过直接销售用户个人数据获取主要收入。 | AG48: 创新 (Innovation) | AH48: 指通过电子邮件、消息应用等难以追踪的渠道进行的社交分享区域，企业应在此处关注建立信任。 | AI48: 基于兴趣形成，一个用户可以同时属于多个社区。 | AJ48: 财务与会计 | AK48: O | AL48: O | AM48: =10*SUMPRODUCT(--(AC48:AL48<>""),--(((AC48:AL48=정답표!$C$6:$L$6)+(AC48:AL48=정답표!$C$7:$L$7))>0)) -> 90 | AN48: 在风险、成本和便利性之间找到适当的平衡。 | AO48: 因为将所有安全风险降至零在现实中是不可能且低效的。 | AP48: 未应用安全补丁的旧软件 | AQ48: 威胁能够访问系统或数据并造成损害的弱点。 | AR48: 将数据转换为未经授权的人无法理解的形式以进行保护的技术。 | AS48: 根据预设规则允许或阻止网络流量。 | AT48: 主要是技术部门制定和执行的技术问题。 | AU48: 定期测试备份数据是否能实际恢复非常重要。 | AV48: O | AW48: O | AX48: =10*SUMPRODUCT(--(AN48:AW48<>""),--(((AN48:AW48=정답표!$C$8:$L$8)+(AN48:AW48=정답표!$C$9:$L$9))>0)) -> 100 | AY48: 支持IT技术以实现组织目标，并将其与经营目标相结合。 | AZ48: 有效连接信息系统(IS)战略与企业经营战略。 | BA48: 根据组织的目标和优先顺序，综合考虑战略、预算和风险。 | BB48: 谁来做信息系统相关的决策，谁来承担责任？ | BC48: 综合考虑项目的战略适用性和实际可行性。 | BD48: 将组织的部分IT功能委托给外部专业公司执行。 | BE48: 安全威胁完全消除，信息安全得到加强。 | BF48: O | BG48: O | BH48: X | BI48: =10*SUMPRODUCT(--(AY48:BH48<>""),--(((AY48:BH48=정답표!$C$10:$L$10)+(AY48:BH48=정답표!$C$11:$L$11))>0)) -> 100 | BJ48: =SUM(Q48,AB48,AM48,AX48,BI48) -> 480 | BK48: =COUNT(Q48,AB48,AM48,AX48,BI48) -> 5 | BL48: =IF(QuizMatchTable[[#This Row],[분반]]=1, QuizMatchTable[[#This Row],[퀴즈합계]]/4 *0.3, QuizMatchTable[[#This Row],[퀴즈합계]]/5*0.3) -> 28.8 | BM48: 30 | BN48: 18.39 | BP48: =SUM(QuizMatchTable[[#This Row],[퀴즈점수(30)]],BM48,BN48,BO48) -> 77.19 | BQ48: =IF(OR(BP48="",BP48=0,BT48="결석초과"),"",COUNTIFS($B$2:$B$109,B48,$BP$2:$BP$109,">"&BP48)+1) -> 12 | BR48: B+ | BS48: 0
A49: 경영학과 | B49: 2 | C49: 20220170 | D49: 이원 | E49: 010-9893-9650 | F49: 13583179312@163.com | AC49: 硬件、软件、社区、流程、人员 | AD49: 组织战略决定价值链，价值链决定业务流程，业务流程决定 SMIS 需求。 | AE49: 增加物质资本 | AF49: 直接销售用户数据：通过直接销售用户个人数据获取主要收入。 | AG49: 创新 (Innovation) | AH49: 指通过电子邮件、消息应用等难以追踪的渠道进行的社交分享区域，企业应在此处关注建立信任。 | AI49: 基于兴趣形成，一个用户可以同时属于多个社区。 | AJ49: 财务与会计 | AK49: O | AL49: O | AM49: =10*SUMPRODUCT(--(AC49:AL49<>""),--(((AC49:AL49=정답표!$C$6:$L$6)+(AC49:AL49=정답표!$C$7:$L$7))>0)) -> 90 | AN49: 在风险、成本和便利性之间找到适当的平衡。 | AO49: 因为将所有安全风险降至零在现实中是不可能且低效的。 | AP49: 将备份数据分离存储在外部存储器中的措施 | AQ49: 威胁能够访问系统或数据并造成损害的弱点。 | AR49: 将数据转换为未经授权的人无法理解的形式以进行保护的技术。 | AS49: 检测并自动清除渗透到系统中的恶意代码。 | AT49: 与管理层、管理者、员工等所有组织成员的责任相关。 | AU49: 定期测试备份数据是否能实际恢复非常重要。 | AV49: O | AW49: O | AX49: =10*SUMPRODUCT(--(AN49:AW49<>""),--(((AN49:AW49=정답표!$C$8:$L$8)+(AN49:AW49=정답표!$C$9:$L$9))>0)) -> 70 | AY49: 支持IT技术以实现组织目标，并将其与经营目标相结合。 | AZ49: 有效连接信息系统(IS)战略与企业经营战略。 | BA49: 根据组织的目标和优先顺序，综合考虑战略、预算和风险。 | BB49: 谁来做信息系统相关的决策，谁来承担责任？ | BC49: 综合考虑项目的战略适用性和实际可行性。 | BD49: 将组织的所有核心能力完全转移给外部公司。 | BE49: 安全威胁完全消除，信息安全得到加强。 | BF49: O | BG49: O | BH49: X | BI49: =10*SUMPRODUCT(--(AY49:BH49<>""),--(((AY49:BH49=정답표!$C$10:$L$10)+(AY49:BH49=정답표!$C$11:$L$11))>0)) -> 90 | BJ49: =SUM(Q49,AB49,AM49,AX49,BI49) -> 250 | BK49: =COUNT(Q49,AB49,AM49,AX49,BI49) -> 3 | BL49: =IF(QuizMatchTable[[#This Row],[분반]]=1, QuizMatchTable[[#This Row],[퀴즈합계]]/4 *0.3, QuizMatchTable[[#This Row],[퀴즈합계]]/5*0.3) -> 15 | BM49: 22.67 | BN49: 19.6 | BP49: =SUM(QuizMatchTable[[#This Row],[퀴즈점수(30)]],BM49,BN49,BO49) -> 57.27 | BQ49: =IF(OR(BP49="",BP49=0,BT49="결석초과"),"",COUNTIFS($B$2:$B$109,B49,$BP$2:$BP$109,">"&BP49)+1) -> 31 | BR49: F | BS49: 11
A50: 경영학과 | B50: 2 | C50: 20220178 | D50: 전일남 | E50: 010-5750-9200 | F50: 3170946358@qq.com | G50: B. 피드백 및 반복 (反馈和迭代) | H50: D. 최소한의 비용과 시간 소모 (最低限度的成本和时间消耗) | I50: C. 운영적 의사결정 (运营性决策) | J50: C. 마케팅 전략 (营销策略) | K50: C. 문제해결 (问题解决) | L50: C. 착수 → 계획 → 실행 → 마무리 (启动 → 计划 → 执行 → 结束) | M50: A. 프로젝트 콘텐츠 (项目内容/产出物), B. 프로젝트 메타데이터 (项目元数据) | N50: B. 비동기적 소통 (Asynchronous Communication / 异步沟通) | O50: X (거짓/错) | P50: O (참/对) | Q50: =10*SUMPRODUCT(--(G50:P50<>""),--(((G50:P50=정답표!$C$2:$L$2)+(G50:P50=정답표!$C$3:$L$3))>0)) -> 100 | R50: BPR | S50: 遵循日常运营的正式化和标准化程序。 | T50: 企业间流程 | U50: 相同数据在多个部门重复存储，导致不一致。 | V50: 引入企业信息系统（EIS） | W50: 减少不必要的审批环节，从而最大限度地减少时间和资源。 | X50: 整合管理与客户的所有互动，最大限度地提高客户终身价值。 | Y50: 将业务运营整合到一个单一且一致的计算平台。 | Z50: O | AA50: O | AB50: =10*SUMPRODUCT(--(R50:AA50<>""),--(((R50:AA50=정답표!$C$4:$L$4)+(R50:AA50=정답표!$C$5:$L$5))>0)) -> 100 | AC50: 硬件、软件、社区、流程、人员 | AD50: 组织战略决定价值链，价值链决定业务流程，业务流程决定 SMIS 需求。 | AE50: 施加影响力 | AF50: 直接销售用户数据：通过直接销售用户个人数据获取主要收入。 | AG50: 创新 (Innovation) | AH50: 指通过电子邮件、消息应用等难以追踪的渠道进行的社交分享区域，企业应在此处关注建立信任。 | AI50: 基于兴趣形成，一个用户可以同时属于多个社区。 | AJ50: 财务与会计 | AK50: O | AL50: O | AM50: =10*SUMPRODUCT(--(AC50:AL50<>""),--(((AC50:AL50=정답표!$C$6:$L$6)+(AC50:AL50=정답표!$C$7:$L$7))>0)) -> 80 | AN50: 在风险、成本和便利性之间找到适当的平衡。 | AO50: 因为将所有安全风险降至零在现实中是不可能且低效的。 | AP50: 未应用安全补丁的旧软件 | AQ50: 威胁能够访问系统或数据并造成损害的弱点。 | AR50: 将数据转换为未经授权的人无法理解的形式以进行保护的技术。 | AS50: 根据预设规则允许或阻止网络流量。 | AT50: 主要是技术部门制定和执行的技术问题。 | AU50: 定期测试备份数据是否能实际恢复非常重要。 | AV50: O | AW50: O | AX50: =10*SUMPRODUCT(--(AN50:AW50<>""),--(((AN50:AW50=정답표!$C$8:$L$8)+(AN50:AW50=정답표!$C$9:$L$9))>0)) -> 100 | AY50: 支持IT技术以实现组织目标，并将其与经营目标相结合。 | AZ50: 有效连接信息系统(IS)战略与企业经营战略。 | BA50: 根据组织的目标和优先顺序，综合考虑战略、预算和风险。 | BB50: 谁来做信息系统相关的决策，谁来承担责任？ | BC50: 综合考虑项目的战略适用性和实际可行性。 | BD50: 将组织的部分IT功能委托给外部专业公司执行。 | BE50: 安全威胁完全消除，信息安全得到加强。 | BF50: O | BG50: O | BH50: X | BI50: =10*SUMPRODUCT(--(AY50:BH50<>""),--(((AY50:BH50=정답표!$C$10:$L$10)+(AY50:BH50=정답표!$C$11:$L$11))>0)) -> 100 | BJ50: =SUM(Q50,AB50,AM50,AX50,BI50) -> 480 | BK50: =COUNT(Q50,AB50,AM50,AX50,BI50) -> 5 | BL50: =IF(QuizMatchTable[[#This Row],[분반]]=1, QuizMatchTable[[#This Row],[퀴즈합계]]/4 *0.3, QuizMatchTable[[#This Row],[퀴즈합계]]/5*0.3) -> 28.8 | BM50: 26 | BN50: 18.8 | BP50: =SUM(QuizMatchTable[[#This Row],[퀴즈점수(30)]],BM50,BN50,BO50) -> 73.6 | BQ50: =IF(OR(BP50="",BP50=0,BT50="결석초과"),"",COUNTIFS($B$2:$B$109,B50,$BP$2:$BP$109,">"&BP50)+1) -> 19 | BR50: B0 | BS50: 6
A51: 경영학과 | B51: 2 | C51: 20220180 | D51: 제효휘 | E51: 010-6852-1803 | F51: qixi5303@gmail.com | G51: C. 분업 및 전문화 (分工和专业化) | H51: D. 최소한의 비용과 시간 소모 (最低限度的成本和时间消耗) | I51: C. 운영적 의사결정 (运营性决策) | J51: C. 마케팅 전략 (营销策略) | K51: C. 문제해결 (问题解决) | L51: C. 착수 → 계획 → 실행 → 마무리 (启动 → 计划 → 执行 → 结束) | M51: A. 프로젝트 콘텐츠 (项目内容/产出物), B. 프로젝트 메타데이터 (项目元数据) | N51: B. 비동기적 소통 (Asynchronous Communication / 异步沟通) | O51: O (참/对) | P51: X (거짓/错) | Q51: =10*SUMPRODUCT(--(G51:P51<>""),--(((G51:P51=정답표!$C$2:$L$2)+(G51:P51=정답표!$C$3:$L$3))>0)) -> 70 | R51: ERP | S51: 遵循日常运营的正式化和标准化程序。 | T51: 企业间流程 | U51: 相同数据在多个部门重复存储，导致不一致。 | V51: 引入企业信息系统（EIS） | W51: 减少不必要的审批环节，从而最大限度地减少时间和资源。 | X51: 整合管理与客户的所有互动，最大限度地提高客户终身价值。 | Y51: 将业务运营整合到一个单一且一致的计算平台。 | Z51: O | AA51: O | AB51: =10*SUMPRODUCT(--(R51:AA51<>""),--(((R51:AA51=정답표!$C$4:$L$4)+(R51:AA51=정답표!$C$5:$L$5))>0)) -> 90 | AC51: 硬件、软件、数据、流程、人员 | AD51: 组织战略决定价值链，价值链决定业务流程，业务流程决定 SMIS 需求。 | AE51: 增加物质资本 | AF51: 直接销售用户数据：通过直接销售用户个人数据获取主要收入。 | AG51: 创新 (Innovation) | AH51: 指通过电子邮件、消息应用等难以追踪的渠道进行的社交分享区域，企业应在此处关注建立信任。 | AI51: 基于兴趣形成，一个用户可以同时属于多个社区。 | AJ51: 财务与会计 | AK51: O | AL51: O | AM51: =10*SUMPRODUCT(--(AC51:AL51<>""),--(((AC51:AL51=정답표!$C$6:$L$6)+(AC51:AL51=정답표!$C$7:$L$7))>0)) -> 100 | AN51: 在风险、成本和便利性之间找到适当的平衡。 | AO51: 因为将所有安全风险降至零在现实中是不可能且低效的。 | AP51: 未应用安全补丁的旧软件 | AQ51: 威胁能够访问系统或数据并造成损害的弱点。 | AR51: 将数据转换为未经授权的人无法理解的形式以进行保护的技术。 | AS51: 根据预设规则允许或阻止网络流量。 | AT51: 主要是技术部门制定和执行的技术问题。 | AU51: 定期测试备份数据是否能实际恢复非常重要。 | AV51: O | AW51: O | AX51: =10*SUMPRODUCT(--(AN51:AW51<>""),--(((AN51:AW51=정답표!$C$8:$L$8)+(AN51:AW51=정답표!$C$9:$L$9))>0)) -> 100 | BJ51: =SUM(Q51,AB51,AM51,AX51,BI51) -> 360 | BK51: =COUNT(Q51,AB51,AM51,AX51,BI51) -> 4 | BL51: =IF(QuizMatchTable[[#This Row],[분반]]=1, QuizMatchTable[[#This Row],[퀴즈합계]]/4 *0.3, QuizMatchTable[[#This Row],[퀴즈합계]]/5*0.3) -> 21.6 | BM51: 28 | BN51: 17.6 | BP51: =SUM(QuizMatchTable[[#This Row],[퀴즈점수(30)]],BM51,BN51,BO51) -> 67.2 | BQ51: =IF(OR(BP51="",BP51=0,BT51="결석초과"),"",COUNTIFS($B$2:$B$109,B51,$BP$2:$BP$109,">"&BP51)+1) -> 27 | BR51: F | BS51: 3
A52: 경영학과 | B52: 2 | C52: 20220181 | D52: 조맹우 | E52: 010-5842-6574 | F52: 1071414539@qq.com | R52: BPR | S52: 遵循日常运营的正式化和标准化程序。 | T52: 企业级流程 | U52: 相同数据在多个部门重复存储，导致不一致。 | V52: 引入企业信息系统（EIS） | W52: 减少不必要的审批环节，从而最大限度地减少时间和资源。 | X52: 整合管理与客户的所有互动，最大限度地提高客户终身价值。 | Y52: 将业务运营整合到一个单一且一致的计算平台。 | Z52: O | AA52: O | AB52: =10*SUMPRODUCT(--(R52:AA52<>""),--(((R52:AA52=정답표!$C$4:$L$4)+(R52:AA52=정답표!$C$5:$L$5))>0)) -> 90 | AC52: 硬件、软件、数据、流程、人员 | AD52: 组织战略决定价值链，价值链决定业务流程，业务流程决定 SMIS 需求。 | AE52: 增加物质资本 | AF52: 直接销售用户数据：通过直接销售用户个人数据获取主要收入。 | AG52: 创新 (Innovation) | AH52: 指通过电子邮件、消息应用等难以追踪的渠道进行的社交分享区域，企业应在此处关注建立信任。 | AI52: 基于兴趣形成，一个用户可以同时属于多个社区。 | AJ52: 财务与会计 | AK52: O | AL52: O | AM52: =10*SUMPRODUCT(--(AC52:AL52<>""),--(((AC52:AL52=정답표!$C$6:$L$6)+(AC52:AL52=정답표!$C$7:$L$7))>0)) -> 100 | AN52: 在风险、成本和便利性之间找到适当的平衡。 | AO52: 因为将所有安全风险降至零在现实中是不可能且低效的。 | AP52: 未应用安全补丁的旧软件 | AQ52: 威胁能够访问系统或数据并造成损害的弱点。 | AR52: 将数据转换为未经授权的人无法理解的形式以进行保护的技术。 | AS52: 根据预设规则允许或阻止网络流量。 | AT52: 主要是技术部门制定和执行的技术问题。 | AU52: 定期测试备份数据是否能实际恢复非常重要。 | AV52: O | AW52: O | AX52: =10*SUMPRODUCT(--(AN52:AW52<>""),--(((AN52:AW52=정답표!$C$8:$L$8)+(AN52:AW52=정답표!$C$9:$L$9))>0)) -> 100 | AY52: 支持IT技术以实现组织目标，并将其与经营目标相结合。 | AZ52: 有效连接信息系统(IS)战略与企业经营战略。 | BA52: 根据组织的目标和优先顺序，综合考虑战略、预算和风险。 | BB52: 谁来做信息系统相关的决策，谁来承担责任？ | BC52: 综合考虑项目的战略适用性和实际可行性。 | BD52: 将组织的部分IT功能委托给外部专业公司执行。 | BE52: 安全威胁完全消除，信息安全得到加强。 | BF52: O | BG52: O | BH52: X | BI52: =10*SUMPRODUCT(--(AY52:BH52<>""),--(((AY52:BH52=정답표!$C$10:$L$10)+(AY52:BH52=정답표!$C$11:$L$11))>0)) -> 100 | BJ52: =SUM(Q52,AB52,AM52,AX52,BI52) -> 390 | BK52: =COUNT(Q52,AB52,AM52,AX52,BI52) -> 4 | BL52: =IF(QuizMatchTable[[#This Row],[분반]]=1, QuizMatchTable[[#This Row],[퀴즈합계]]/4 *0.3, QuizMatchTable[[#This Row],[퀴즈합계]]/5*0.3) -> 23.4 | BM52: 26 | BN52: 19.6 | BP52: =SUM(QuizMatchTable[[#This Row],[퀴즈점수(30)]],BM52,BN52,BO52) -> 69 | BQ52: =IF(OR(BP52="",BP52=0,BT52="결석초과"),"",COUNTIFS($B$2:$B$109,B52,$BP$2:$BP$109,">"&BP52)+1) -> 24 | BR52: F | BS52: 6
A53: 경영학과 | B53: 2 | C53: 20220182 | D53: 조염흔 | E53: 010-7755-6927 | F53: xxin0213@163.com | G53: C. 분업 및 전문화 (分工和专业化) | H53: D. 최소한의 비용과 시간 소모 (最低限度的成本和时间消耗) | I53: C. 운영적 의사결정 (运营性决策) | J53: C. 마케팅 전략 (营销策略) | K53: C. 문제해결 (问题解决) | L53: C. 착수 → 계획 → 실행 → 마무리 (启动 → 计划 → 执行 → 结束) | M53: A. 프로젝트 콘텐츠 (项目内容/产出物), B. 프로젝트 메타데이터 (项目元数据) | N53: B. 비동기적 소통 (Asynchronous Communication / 异步沟通) | O53: X (거짓/错) | P53: O (참/对) | Q53: =10*SUMPRODUCT(--(G53:P53<>""),--(((G53:P53=정답표!$C$2:$L$2)+(G53:P53=정답표!$C$3:$L$3))>0)) -> 90 | R53: BPR | S53: 遵循日常运营的正式化和标准化程序。 | T53: 企业间流程 | U53: 相同数据在多个部门重复存储，导致不一致。 | V53: 引入企业信息系统（EIS） | W53: 减少不必要的审批环节，从而最大限度地减少时间和资源。 | X53: 整合管理与客户的所有互动，最大限度地提高客户终身价值。 | Y53: 将业务运营整合到一个单一且一致的计算平台。 | Z53: O | AA53: O | AB53: =10*SUMPRODUCT(--(R53:AA53<>""),--(((R53:AA53=정답표!$C$4:$L$4)+(R53:AA53=정답표!$C$5:$L$5))>0)) -> 100 | AC53: 硬件、软件、数据、流程、人员 | AD53: 组织战略决定价值链，价值链决定业务流程，业务流程决定 SMIS 需求。 | AE53: 增加物质资本 | AF53: 直接销售用户数据：通过直接销售用户个人数据获取主要收入。 | AG53: 创新 (Innovation) | AH53: 指通过电子邮件、消息应用等难以追踪的渠道进行的社交分享区域，企业应在此处关注建立信任。 | AI53: 基于兴趣形成，一个用户可以同时属于多个社区。 | AJ53: 财务与会计 | AK53: O | AL53: O | AM53: =10*SUMPRODUCT(--(AC53:AL53<>""),--(((AC53:AL53=정답표!$C$6:$L$6)+(AC53:AL53=정답표!$C$7:$L$7))>0)) -> 100 | AN53: 在风险、成本和便利性之间找到适当的平衡。 | AO53: 因为将所有安全风险降至零在现实中是不可能且低效的。 | AP53: 未应用安全补丁的旧软件 | AQ53: 威胁能够访问系统或数据并造成损害的弱点。 | AR53: 将数据转换为未经授权的人无法理解的形式以进行保护的技术。 | AS53: 根据预设规则允许或阻止网络流量。 | AT53: 主要是技术部门制定和执行的技术问题。 | AU53: 定期测试备份数据是否能实际恢复非常重要。 | AV53: O | AW53: O | AX53: =10*SUMPRODUCT(--(AN53:AW53<>""),--(((AN53:AW53=정답표!$C$8:$L$8)+(AN53:AW53=정답표!$C$9:$L$9))>0)) -> 100 | AY53: 支持IT技术以实现组织目标，并将其与经营目标相结合。 | AZ53: 有效连接信息系统(IS)战略与企业经营战略。 | BA53: 根据组织的目标和优先顺序，综合考虑战略、预算和风险。 | BB53: 谁来做信息系统相关的决策，谁来承担责任？ | BC53: 综合考虑项目的战略适用性和实际可行性。 | BD53: 将组织的部分IT功能委托给外部专业公司执行。 | BE53: 安全威胁完全消除，信息安全得到加强。 | BF53: O | BG53: O | BH53: X | BI53: =10*SUMPRODUCT(--(AY53:BH53<>""),--(((AY53:BH53=정답표!$C$10:$L$10)+(AY53:BH53=정답표!$C$11:$L$11))>0)) -> 100 | BJ53: =SUM(Q53,AB53,AM53,AX53,BI53) -> 490 | BK53: =COUNT(Q53,AB53,AM53,AX53,BI53) -> 5 | BL53: =IF(QuizMatchTable[[#This Row],[분반]]=1, QuizMatchTable[[#This Row],[퀴즈합계]]/4 *0.3, QuizMatchTable[[#This Row],[퀴즈합계]]/5*0.3) -> 29.4 | BM53: 30 | BN53: 19.6 | BP53: =SUM(QuizMatchTable[[#This Row],[퀴즈점수(30)]],BM53,BN53,BO53) -> 79 | BQ53: =IF(OR(BP53="",BP53=0,BT53="결석초과"),"",COUNTIFS($B$2:$B$109,B53,$BP$2:$BP$109,">"&BP53)+1) -> 2 | BR53: A+ | BS53: 0
A54: 경영학과 | B54: 2 | C54: 20220184 | D54: 진발강 | E54: 010-8165-6195 | F54: 1219127626@qq.com | G54: C. 분업 및 전문화 (分工和专业化) | H54: D. 최소한의 비용과 시간 소모 (最低限度的成本和时间消耗) | I54: C. 운영적 의사결정 (运营性决策) | J54: C. 마케팅 전략 (营销策略) | K54: C. 문제해결 (问题解决) | L54: C. 착수 → 계획 → 실행 → 마무리 (启动 → 计划 → 执行 → 结束) | M54: A. 프로젝트 콘텐츠 (项目内容/产出物), B. 프로젝트 메타데이터 (项目元数据) | N54: B. 비동기적 소통 (Asynchronous Communication / 异步沟通) | O54: X (거짓/错) | P54: O (참/对) | Q54: =10*SUMPRODUCT(--(G54:P54<>""),--(((G54:P54=정답표!$C$2:$L$2)+(G54:P54=정답표!$C$3:$L$3))>0)) -> 90 | R54: BPR | S54: 遵循日常运营的正式化和标准化程序。 | T54: 企业间流程 | U54: 相同数据在多个部门重复存储，导致不一致。 | V54: 引入企业信息系统（EIS） | W54: 减少不必要的审批环节，从而最大限度地减少时间和资源。 | X54: 整合管理与客户的所有互动，最大限度地提高客户终身价值。 | Y54: 将业务运营整合到一个单一且一致的计算平台。 | Z54: O | AA54: O | AB54: =10*SUMPRODUCT(--(R54:AA54<>""),--(((R54:AA54=정답표!$C$4:$L$4)+(R54:AA54=정답표!$C$5:$L$5))>0)) -> 100 | AC54: 硬件、软件、数据、流程、人员 | AD54: 组织战略决定价值链，价值链决定业务流程，业务流程决定 SMIS 需求。 | AE54: 增加物质资本 | AF54: 直接销售用户数据：通过直接销售用户个人数据获取主要收入。 | AG54: 创新 (Innovation) | AH54: 指通过电子邮件、消息应用等难以追踪的渠道进行的社交分享区域，企业应在此处关注建立信任。 | AI54: 基于兴趣形成，一个用户可以同时属于多个社区。 | AJ54: 财务与会计 | AK54: O | AL54: O | AM54: =10*SUMPRODUCT(--(AC54:AL54<>""),--(((AC54:AL54=정답표!$C$6:$L$6)+(AC54:AL54=정답표!$C$7:$L$7))>0)) -> 100 | AN54: 在风险、成本和便利性之间找到适当的平衡。 | AO54: 因为将所有安全风险降至零在现实中是不可能且低效的。 | AP54: 未应用安全补丁的旧软件 | AQ54: 威胁能够访问系统或数据并造成损害的弱点。 | AR54: 将数据转换为未经授权的人无法理解的形式以进行保护的技术。 | AS54: 根据预设规则允许或阻止网络流量。 | AT54: 主要是技术部门制定和执行的技术问题。 | AU54: 定期测试备份数据是否能实际恢复非常重要。 | AV54: O | AW54: O | AX54: =10*SUMPRODUCT(--(AN54:AW54<>""),--(((AN54:AW54=정답표!$C$8:$L$8)+(AN54:AW54=정답표!$C$9:$L$9))>0)) -> 100 | AY54: 支持IT技术以实现组织目标，并将其与经营目标相结合。 | AZ54: 有效连接信息系统(IS)战略与企业经营战略。 | BA54: 根据组织的目标和优先顺序，综合考虑战略、预算和风险。 | BB54: 谁来做信息系统相关的决策，谁来承担责任？ | BC54: 综合考虑项目的战略适用性和实际可行性。 | BD54: 将组织的部分IT功能委托给外部专业公司执行。 | BE54: 安全威胁完全消除，信息安全得到加强。 | BF54: O | BG54: O | BH54: X | BI54: =10*SUMPRODUCT(--(AY54:BH54<>""),--(((AY54:BH54=정답표!$C$10:$L$10)+(AY54:BH54=정답표!$C$11:$L$11))>0)) -> 100 | BJ54: =SUM(Q54,AB54,AM54,AX54,BI54) -> 490 | BK54: =COUNT(Q54,AB54,AM54,AX54,BI54) -> 5 | BL54: =IF(QuizMatchTable[[#This Row],[분반]]=1, QuizMatchTable[[#This Row],[퀴즈합계]]/4 *0.3, QuizMatchTable[[#This Row],[퀴즈합계]]/5*0.3) -> 29.4 | BM54: 30 | BN54: 16 | BP54: =SUM(QuizMatchTable[[#This Row],[퀴즈점수(30)]],BM54,BN54,BO54) -> 75.4 | BQ54: =IF(OR(BP54="",BP54=0,BT54="결석초과"),"",COUNTIFS($B$2:$B$109,B54,$BP$2:$BP$109,">"&BP54)+1) -> 16 | BR54: B+ | BS54: 0
A55: 경영학과 | B55: 2 | C55: 20220185 | D55: 진사연 | E55: 010-7696-8651 | F55: siranchen85@gamil.com | G55: B. 피드백 및 반복 (反馈和迭代) | H55: D. 최소한의 비용과 시간 소모 (最低限度的成本和时间消耗) | I55: C. 운영적 의사결정 (运营性决策) | J55: C. 마케팅 전략 (营销策略) | K55: C. 문제해결 (问题解决) | L55: C. 착수 → 계획 → 실행 → 마무리 (启动 → 计划 → 执行 → 结束) | M55: A. 프로젝트 콘텐츠 (项目内容/产出物), B. 프로젝트 메타데이터 (项目元数据) | N55: B. 비동기적 소통 (Asynchronous Communication / 异步沟通) | O55: X (거짓/错) | P55: O (참/对) | Q55: =10*SUMPRODUCT(--(G55:P55<>""),--(((G55:P55=정답표!$C$2:$L$2)+(G55:P55=정답표!$C$3:$L$3))>0)) -> 100 | R55: BPR | S55: 遵循日常运营的正式化和标准化程序。 | T55: 企业间流程 | U55: 相同数据在多个部门重复存储，导致不一致。 | V55: 引入企业信息系统（EIS） | W55: 减少不必要的审批环节，从而最大限度地减少时间和资源。 | X55: 整合管理与客户的所有互动，最大限度地提高客户终身价值。 | Y55: 将业务运营整合到一个单一且一致的计算平台。 | Z55: O | AA55: O | AB55: =10*SUMPRODUCT(--(R55:AA55<>""),--(((R55:AA55=정답표!$C$4:$L$4)+(R55:AA55=정답표!$C$5:$L$5))>0)) -> 100 | AC55: 硬件、软件、数据、流程、人员 | AD55: 组织战略决定价值链，价值链决定业务流程，业务流程决定 SMIS 需求。 | AE55: 增加物质资本 | AF55: 直接销售用户数据：通过直接销售用户个人数据获取主要收入。 | AG55: 创新 (Innovation) | AH55: 指通过电子邮件、消息应用等难以追踪的渠道进行的社交分享区域，企业应在此处关注建立信任。 | AI55: 基于兴趣形成，一个用户可以同时属于多个社区。 | AJ55: 财务与会计 | AK55: O | AL55: O | AM55: =10*SUMPRODUCT(--(AC55:AL55<>""),--(((AC55:AL55=정답표!$C$6:$L$6)+(AC55:AL55=정답표!$C$7:$L$7))>0)) -> 100 | AN55: 在风险、成本和便利性之间找到适当的平衡。 | AO55: 因为将所有安全风险降至零在现实中是不可能且低效的。 | AP55: 未应用安全补丁的旧软件 | AQ55: 威胁能够访问系统或数据并造成损害的弱点。 | AR55: 将数据转换为未经授权的人无法理解的形式以进行保护的技术。 | AS55: 根据预设规则允许或阻止网络流量。 | AT55: 主要是技术部门制定和执行的技术问题。 | AU55: 定期测试备份数据是否能实际恢复非常重要。 | AV55: O | AW55: O | AX55: =10*SUMPRODUCT(--(AN55:AW55<>""),--(((AN55:AW55=정답표!$C$8:$L$8)+(AN55:AW55=정답표!$C$9:$L$9))>0)) -> 100 | AY55: 支持IT技术以实现组织目标，并将其与经营目标相结合。 | AZ55: 有效连接信息系统(IS)战略与企业经营战略。 | BA55: 根据组织的目标和优先顺序，综合考虑战略、预算和风险。 | BB55: 谁来做信息系统相关的决策，谁来承担责任？ | BC55: 综合考虑项目的战略适用性和实际可行性。 | BD55: 将组织的部分IT功能委托给外部专业公司执行。 | BE55: 安全威胁完全消除，信息安全得到加强。 | BF55: O | BG55: O | BH55: X | BI55: =10*SUMPRODUCT(--(AY55:BH55<>""),--(((AY55:BH55=정답표!$C$10:$L$10)+(AY55:BH55=정답표!$C$11:$L$11))>0)) -> 100 | BJ55: =SUM(Q55,AB55,AM55,AX55,BI55) -> 500 | BK55: =COUNT(Q55,AB55,AM55,AX55,BI55) -> 5 | BL55: =IF(QuizMatchTable[[#This Row],[분반]]=1, QuizMatchTable[[#This Row],[퀴즈합계]]/4 *0.3, QuizMatchTable[[#This Row],[퀴즈합계]]/5*0.3) -> 30 | BM55: 30 | BN55: 19.6 | BP55: =SUM(QuizMatchTable[[#This Row],[퀴즈점수(30)]],BM55,BN55,BO55) -> 79.6 | BQ55: =IF(OR(BP55="",BP55=0,BT55="결석초과"),"",COUNTIFS($B$2:$B$109,B55,$BP$2:$BP$109,">"&BP55)+1) -> 1 | BR55: A+ | BS55: 0
A56: 경영학과 | B56: 2 | C56: 20220188 | D56: 하호인 | E56: 010-2487-5675 | F56: h318191908@icloud.com | G56: B. 피드백 및 반복 (反馈和迭代) | H56: D. 최소한의 비용과 시간 소모 (最低限度的成本和时间消耗) | I56: C. 운영적 의사결정 (运营性决策) | J56: C. 마케팅 전략 (营销策略) | K56: C. 문제해결 (问题解决) | L56: C. 착수 → 계획 → 실행 → 마무리 (启动 → 计划 → 执行 → 结束) | M56: A. 프로젝트 콘텐츠 (项目内容/产出物), B. 프로젝트 메타데이터 (项目元数据) | N56: B. 비동기적 소통 (Asynchronous Communication / 异步沟通) | O56: X (거짓/错) | P56: O (참/对) | Q56: =10*SUMPRODUCT(--(G56:P56<>""),--(((G56:P56=정답표!$C$2:$L$2)+(G56:P56=정답표!$C$3:$L$3))>0)) -> 100 | R56: BPR | S56: 遵循日常运营的正式化和标准化程序。 | T56: 企业间流程 | U56: 相同数据在多个部门重复存储，导致不一致。 | V56: 引入企业信息系统（EIS） | W56: 减少不必要的审批环节，从而最大限度地减少时间和资源。 | X56: 整合管理与客户的所有互动，最大限度地提高客户终身价值。 | Y56: 将业务运营整合到一个单一且一致的计算平台。 | Z56: O | AA56: O | AB56: =10*SUMPRODUCT(--(R56:AA56<>""),--(((R56:AA56=정답표!$C$4:$L$4)+(R56:AA56=정답표!$C$5:$L$5))>0)) -> 100 | AC56: 硬件、软件、数据、流程、人员 | AD56: 组织战略决定价值链，价值链决定业务流程，业务流程决定 SMIS 需求。 | AE56: 增加物质资本 | AF56: 直接销售用户数据：通过直接销售用户个人数据获取主要收入。 | AG56: 创新 (Innovation) | AH56: 指通过电子邮件、消息应用等难以追踪的渠道进行的社交分享区域，企业应在此处关注建立信任。 | AI56: 基于兴趣形成，一个用户可以同时属于多个社区。 | AJ56: 财务与会计 | AK56: O | AL56: O | AM56: =10*SUMPRODUCT(--(AC56:AL56<>""),--(((AC56:AL56=정답표!$C$6:$L$6)+(AC56:AL56=정답표!$C$7:$L$7))>0)) -> 100 | AN56: 在风险、成本和便利性之间找到适当的平衡。 | AO56: 因为将所有安全风险降至零在现实中是不可能且低效的。 | AP56: 未应用安全补丁的旧软件 | AQ56: 威胁能够访问系统或数据并造成损害的弱点。 | AR56: 将数据转换为未经授权的人无法理解的形式以进行保护的技术。 | AS56: 根据预设规则允许或阻止网络流量。 | AT56: 主要是技术部门制定和执行的技术问题。 | AU56: 定期测试备份数据是否能实际恢复非常重要。 | AV56: O | AW56: O | AX56: =10*SUMPRODUCT(--(AN56:AW56<>""),--(((AN56:AW56=정답표!$C$8:$L$8)+(AN56:AW56=정답표!$C$9:$L$9))>0)) -> 100 | AY56: 支持IT技术以实现组织目标，并将其与经营目标相结合。 | AZ56: 有效连接信息系统(IS)战略与企业经营战略。 | BA56: 根据组织的目标和优先顺序，综合考虑战略、预算和风险。 | BB56: 谁来做信息系统相关的决策，谁来承担责任？ | BC56: 综合考虑项目的战略适用性和实际可行性。 | BD56: 将组织的部分IT功能委托给外部专业公司执行。 | BE56: 安全威胁完全消除，信息安全得到加强。 | BF56: O | BG56: O | BH56: X | BI56: =10*SUMPRODUCT(--(AY56:BH56<>""),--(((AY56:BH56=정답표!$C$10:$L$10)+(AY56:BH56=정답표!$C$11:$L$11))>0)) -> 100 | BJ56: =SUM(Q56,AB56,AM56,AX56,BI56) -> 500 | BK56: =COUNT(Q56,AB56,AM56,AX56,BI56) -> 5 | BL56: =IF(QuizMatchTable[[#This Row],[분반]]=1, QuizMatchTable[[#This Row],[퀴즈합계]]/4 *0.3, QuizMatchTable[[#This Row],[퀴즈합계]]/5*0.3) -> 30 | BM56: 30 | BN56: 18 | BP56: =SUM(QuizMatchTable[[#This Row],[퀴즈점수(30)]],BM56,BN56,BO56) -> 78 | BQ56: =IF(OR(BP56="",BP56=0,BT56="결석초과"),"",COUNTIFS($B$2:$B$109,B56,$BP$2:$BP$109,">"&BP56)+1) -> 8 | BR56: A0 | BS56: 0
A57: 경영학과 | B57: 2 | C57: 20220190 | D57: 호산 | E57: 010-8370-3716 | F57: 3319925196@qq.com | G57: B. 피드백 및 반복 (反馈和迭代) | H57: D. 최소한의 비용과 시간 소모 (最低限度的成本和时间消耗) | I57: C. 운영적 의사결정 (运营性决策) | K57: C. 문제해결 (问题解决) | L57: A. 계획 → 착수 → 실행 → 마무리 (计划 → 启动 → 执行 → 结束) | M57: A. 프로젝트 콘텐츠 (项目内容/产出物), B. 프로젝트 메타데이터 (项目元数据), C. 경영진 보고서 (管理层报告) | N57: B. 비동기적 소통 (Asynchronous Communication / 异步沟通) | O57: O (참/对) | P57: O (참/对) | Q57: =10*SUMPRODUCT(--(G57:P57<>""),--(((G57:P57=정답표!$C$2:$L$2)+(G57:P57=정답표!$C$3:$L$3))>0)) -> 60 | R57: BPR | S57: 遵循日常运营的正式化和标准化程序。 | T57: 企业级流程 | U57: 相同数据在多个部门重复存储，导致不一致。 | V57: 引入企业信息系统（EIS） | W57: 减少不必要的审批环节，从而最大限度地减少时间和资源。 | X57: 整合管理与客户的所有互动，最大限度地提高客户终身价值。 | Y57: 将业务运营整合到一个单一且一致的计算平台。 | Z57: O | AA57: O | AB57: =10*SUMPRODUCT(--(R57:AA57<>""),--(((R57:AA57=정답표!$C$4:$L$4)+(R57:AA57=정답표!$C$5:$L$5))>0)) -> 90 | AC57: 硬件、软件、数据、流程、人员 | AD57: 组织战略决定价值链，价值链决定业务流程，业务流程决定 SMIS 需求。 | AE57: 个人赋能 | AF57: 直接销售用户数据：通过直接销售用户个人数据获取主要收入。 | AG57: 创新 (Innovation) | AH57: 指通过电子邮件、消息应用等难以追踪的渠道进行的社交分享区域，企业应在此处关注建立信任。 | AI57: 基于兴趣形成，一个用户可以同时属于多个社区。 | AJ57: 财务与会计 | AK57: O | AL57: O | AM57: =10*SUMPRODUCT(--(AC57:AL57<>""),--(((AC57:AL57=정답표!$C$6:$L$6)+(AC57:AL57=정답표!$C$7:$L$7))>0)) -> 90 | AN57: 在风险、成本和便利性之间找到适当的平衡。 | AO57: 因为信息系统的复杂性增加，导致安全管理的难度提高。 | AP57: 未应用安全补丁的旧软件 | AQ57: 威胁能够访问系统或数据并造成损害的弱点。 | AR57: 将数据转换为未经授权的人无法理解的形式以进行保护的技术。 | AS57: 根据预设规则允许或阻止网络流量。 | AT57: 主要是技术部门制定和执行的技术问题。 | AU57: 定期测试备份数据是否能实际恢复非常重要。 | AV57: O | AW57: O | AX57: =10*SUMPRODUCT(--(AN57:AW57<>""),--(((AN57:AW57=정답표!$C$8:$L$8)+(AN57:AW57=정답표!$C$9:$L$9))>0)) -> 90 | AY57: 支持IT技术以实现组织目标，并将其与经营目标相结合。 | AZ57: 有效连接信息系统(IS)战略与企业经营战略。 | BA57: 根据组织的目标和优先顺序，综合考虑战略、预算和风险。 | BB57: 谁最擅长操作电脑并拥有技术专业知识？ | BC57: 综合考虑项目的战略适用性和实际可行性。 | BD57: 将组织的部分IT功能委托给外部专业公司执行。 | BE57: 安全威胁完全消除，信息安全得到加强。 | BF57: O | BG57: O | BH57: X | BI57: =10*SUMPRODUCT(--(AY57:BH57<>""),--(((AY57:BH57=정답표!$C$10:$L$10)+(AY57:BH57=정답표!$C$11:$L$11))>0)) -> 90 | BJ57: =SUM(Q57,AB57,AM57,AX57,BI57) -> 420 | BK57: =COUNT(Q57,AB57,AM57,AX57,BI57) -> 5 | BL57: =IF(QuizMatchTable[[#This Row],[분반]]=1, QuizMatchTable[[#This Row],[퀴즈합계]]/4 *0.3, QuizMatchTable[[#This Row],[퀴즈합계]]/5*0.3) -> 25.2 | BM57: 26 | BN57: 16.8 | BP57: =SUM(QuizMatchTable[[#This Row],[퀴즈점수(30)]],BM57,BN57,BO57) -> 68 | BQ57: =IF(OR(BP57="",BP57=0,BT57="결석초과"),"",COUNTIFS($B$2:$B$109,B57,$BP$2:$BP$109,">"&BP57)+1) -> 26 | BR57: F | BS57: 6
A58: 경영학과 | B58: 2 | C58: 20220191 | D58: 황개희 | E58: 010-8096-0826 | F58: 17726496914@163.com | H58: D. 최소한의 비용과 시간 소모 (最低限度的成本和时间消耗) | I58: C. 운영적 의사결정 (运营性决策) | J58: C. 마케팅 전략 (营销策略) | K58: C. 문제해결 (问题解决) | L58: C. 착수 → 계획 → 실행 → 마무리 (启动 → 计划 → 执行 → 结束) | M58: A. 프로젝트 콘텐츠 (项目内容/产出物), B. 프로젝트 메타데이터 (项目元数据) | N58: B. 비동기적 소통 (Asynchronous Communication / 异步沟通) | O58: X (거짓/错) | P58: O (참/对) | Q58: =10*SUMPRODUCT(--(G58:P58<>""),--(((G58:P58=정답표!$C$2:$L$2)+(G58:P58=정답표!$C$3:$L$3))>0)) -> 90 | R58: BPR | S58: 遵循日常运营的正式化和标准化程序。 | T58: 企业间流程 | U58: 相同数据在多个部门重复存储，导致不一致。 | V58: 引入企业信息系统（EIS） | W58: 减少不必要的审批环节，从而最大限度地减少时间和资源。 | X58: 整合管理与客户的所有互动，最大限度地提高客户终身价值。 | Y58: 将业务运营整合到一个单一且一致的计算平台。 | Z58: O | AA58: O | AB58: =10*SUMPRODUCT(--(R58:AA58<>""),--(((R58:AA58=정답표!$C$4:$L$4)+(R58:AA58=정답표!$C$5:$L$5))>0)) -> 100 | AC58: 硬件、软件、数据、流程、人员 | AD58: 组织战略决定价值链，价值链决定业务流程，业务流程决定 SMIS 需求。 | AE58: 增加物质资本 | AF58: 直接销售用户数据：通过直接销售用户个人数据获取主要收入。 | AG58: 创新 (Innovation) | AH58: 指通过电子邮件、消息应用等难以追踪的渠道进行的社交分享区域，企业应在此处关注建立信任。 | AI58: 基于兴趣形成，一个用户可以同时属于多个社区。 | AJ58: 财务与会计 | AK58: O | AL58: O | AM58: =10*SUMPRODUCT(--(AC58:AL58<>""),--(((AC58:AL58=정답표!$C$6:$L$6)+(AC58:AL58=정답표!$C$7:$L$7))>0)) -> 100 | AY58: 支持IT技术以实现组织目标，并将其与经营目标相结合。 | AZ58: 有效连接信息系统(IS)战略与企业经营战略。 | BA58: 根据组织的目标和优先顺序，综合考虑战略、预算和风险。 | BB58: 谁来做信息系统相关的决策，谁来承担责任？ | BC58: 综合考虑项目的战略适用性和实际可行性。 | BD58: 将组织的部分IT功能委托给外部专业公司执行。 | BE58: 安全威胁完全消除，信息安全得到加强。 | BF58: O | BG58: O | BH58: X | BI58: =10*SUMPRODUCT(--(AY58:BH58<>""),--(((AY58:BH58=정답표!$C$10:$L$10)+(AY58:BH58=정답표!$C$11:$L$11))>0)) -> 100 | BJ58: =SUM(Q58,AB58,AM58,AX58,BI58) -> 390 | BK58: =COUNT(Q58,AB58,AM58,AX58,BI58) -> 4 | BL58: =IF(QuizMatchTable[[#This Row],[분반]]=1, QuizMatchTable[[#This Row],[퀴즈합계]]/4 *0.3, QuizMatchTable[[#This Row],[퀴즈합계]]/5*0.3) -> 23.4 | BM58: 28.67 | BN58: 17.6 | BP58: =SUM(QuizMatchTable[[#This Row],[퀴즈점수(30)]],BM58,BN58,BO58) -> 69.67 | BQ58: =IF(OR(BP58="",BP58=0,BT58="결석초과"),"",COUNTIFS($B$2:$B$109,B58,$BP$2:$BP$109,">"&BP58)+1) -> 23 | BR58: F | BS58: 2
A59: 경영학과 | B59: 2 | C59: 20220192 | D59: 후택예 | E59: 010-2816-7721 | F59: 2714108460@qq.com | G59: B. 피드백 및 반복 (反馈和迭代) | H59: D. 최소한의 비용과 시간 소모 (最低限度的成本和时间消耗) | I59: C. 운영적 의사결정 (运营性决策) | J59: C. 마케팅 전략 (营销策略) | K59: C. 문제해결 (问题解决) | L59: C. 착수 → 계획 → 실행 → 마무리 (启动 → 计划 → 执行 → 结束) | M59: A. 프로젝트 콘텐츠 (项目内容/产出物), B. 프로젝트 메타데이터 (项目元数据) | N59: B. 비동기적 소통 (Asynchronous Communication / 异步沟通) | O59: X (거짓/错) | P59: O (참/对) | Q59: =10*SUMPRODUCT(--(G59:P59<>""),--(((G59:P59=정답표!$C$2:$L$2)+(G59:P59=정답표!$C$3:$L$3))>0)) -> 100 | R59: BPR | S59: 遵循日常运营的正式化和标准化程序。 | T59: 企业间流程 | U59: 相同数据在多个部门重复存储，导致不一致。 | V59: 引入企业信息系统（EIS） | W59: 减少不必要的审批环节，从而最大限度地减少时间和资源。 | X59: 整合管理与客户的所有互动，最大限度地提高客户终身价值。 | Y59: 将业务运营整合到一个单一且一致的计算平台。 | Z59: O | AA59: O | AB59: =10*SUMPRODUCT(--(R59:AA59<>""),--(((R59:AA59=정답표!$C$4:$L$4)+(R59:AA59=정답표!$C$5:$L$5))>0)) -> 100 | AN59: 在风险、成本和便利性之间找到适当的平衡。 | AO59: 因为将所有安全风险降至零在现实中是不可能且低效的。 | AP59: 未应用安全补丁的旧软件 | AQ59: 威胁能够访问系统或数据并造成损害的弱点。 | AR59: 将数据转换为未经授权的人无法理解的形式以进行保护的技术。 | AS59: 根据预设规则允许或阻止网络流量。 | AT59: 主要是技术部门制定和执行的技术问题。 | AU59: 定期测试备份数据是否能实际恢复非常重要。 | AV59: O | AW59: O | AX59: =10*SUMPRODUCT(--(AN59:AW59<>""),--(((AN59:AW59=정답표!$C$8:$L$8)+(AN59:AW59=정답표!$C$9:$L$9))>0)) -> 100 | AY59: 支持IT技术以实现组织目标，并将其与经营目标相结合。 | AZ59: 有效连接信息系统(IS)战略与企业经营战略。 | BA59: 根据组织的目标和优先顺序，综合考虑战略、预算和风险。 | BB59: 谁最擅长操作电脑并拥有技术专业知识？ | BC59: 综合考虑项目的战略适用性和实际可行性。 | BD59: 将组织的部分IT功能委托给外部专业公司执行。 | BE59: 安全威胁完全消除，信息安全得到加强。 | BF59: O | BG59: O | BH59: X | BI59: =10*SUMPRODUCT(--(AY59:BH59<>""),--(((AY59:BH59=정답표!$C$10:$L$10)+(AY59:BH59=정답표!$C$11:$L$11))>0)) -> 90 | BJ59: =SUM(Q59,AB59,AM59,AX59,BI59) -> 390 | BK59: =COUNT(Q59,AB59,AM59,AX59,BI59) -> 4 | BL59: =IF(QuizMatchTable[[#This Row],[분반]]=1, QuizMatchTable[[#This Row],[퀴즈합계]]/4 *0.3, QuizMatchTable[[#This Row],[퀴즈합계]]/5*0.3) -> 23.4 | BM59: 26 | BN59: 19.6 | BP59: =SUM(QuizMatchTable[[#This Row],[퀴즈점수(30)]],BM59,BN59,BO59) -> 69 | BQ59: =IF(OR(BP59="",BP59=0,BT59="결석초과"),"",COUNTIFS($B$2:$B$109,B59,$BP$2:$BP$109,">"&BP59)+1) -> 24 | BR59: F | BS59: 6
A60: 경영학과 | B60: 3 | C60: 20220135 | D60: 담신학 | E60: 010-8190-7671 | F60: 1809602781@qq.com | G60: A. 계획 수립 및 예산 책정 (制定计划和预算) | H60: C. 의미 있고 만족스러운 경험 (有意义且令人满意的经验) | I60: D. 비구조적 의사결정 (非结构性决策) | J60: C. 마케팅 전략 (营销策略) | K60: D. 프로젝트 관리 (项目管理) | L60: C. 착수 → 계획 → 실행 → 마무리 (启动 → 计划 → 执行 → 结束) | M60: D. 팀원들의 개인정보 (团队成员的个人信息) | N60: B. 비동기적 소통 (Asynchronous Communication / 异步沟通) | O60: O (참/对) | P60: O (참/对) | Q60: =10*SUMPRODUCT(--(G60:P60<>""),--(((G60:P60=정답표!$C$2:$L$2)+(G60:P60=정답표!$C$3:$L$3))>0)) -> 40 | R60: BPR | S60: 遵循日常运营的正式化和标准化程序。 | T60: 结构化流程 | U60: 数据泄露的担忧减少，安全控制变得容易。 | V60: 扩大手动数据输入和管理流程 | W60: 减少不必要的审批环节，从而最大限度地减少时间和资源。 | X60: 整合管理与客户的所有互动，最大限度地提高客户终身价值。 | Y60: 将业务运营整合到一个单一且一致的计算平台。 | Z60: O | AA60: O | AB60: =10*SUMPRODUCT(--(R60:AA60<>""),--(((R60:AA60=정답표!$C$4:$L$4)+(R60:AA60=정답표!$C$5:$L$5))>0)) -> 70 | AC60: 战略、价值链、产业结构、流程、安全 | AD60: 组织战略决定价值链，价值链决定业务流程，业务流程决定 SMIS 需求。 | AE60: 增加物质资本 | AF60: 免费增值 (Freemium)：提供免费基础服务，对高级功能或去除广告收费。 | AG60: 创新 (Innovation) | AH60: 指通过电子邮件、消息应用等难以追踪的渠道进行的社交分享区域，企业应在此处关注建立信任。 | AI60: 基于兴趣形成，一个用户可以同时属于多个社区。 | AJ60: 财务与会计 | AK60: O | AL60: O | AM60: =10*SUMPRODUCT(--(AC60:AL60<>""),--(((AC60:AL60=정답표!$C$6:$L$6)+(AC60:AL60=정답표!$C$7:$L$7))>0)) -> 80 | AN60: 在风险、成本和便利性之间找到适当的平衡。 | AO60: 因为将所有安全风险降至零在现实中是不可能且低效的。 | AP60: 黑客试图渗透系统的行为 | AQ60: 可能对系统或数据造成损害的潜在风险因素。 | AR60: 将数据转换为未经授权的人无法理解的形式以进行保护的技术。 | AS60: 检测并自动清除渗透到系统中的恶意代码。 | AT60: 包括数据存储、处理、共享等整个组织的行为标准。 | AU60: 验证备份数据可恢复性的测试是浪费时间，可以省略。 | AV60: O | AW60: O | AX60: =10*SUMPRODUCT(--(AN60:AW60<>""),--(((AN60:AW60=정답표!$C$8:$L$8)+(AN60:AW60=정답표!$C$9:$L$9))>0)) -> 50 | AY60: 支持IT技术以实现组织目标，并将其与经营目标相结合。 | AZ60: 有效连接信息系统(IS)战略与企业经营战略。 | BA60: 根据组织的目标和优先顺序，综合考虑战略、预算和风险。 | BB60: 谁来做信息系统相关的决策，谁来承担责任？ | BC60: 综合考虑项目的战略适用性和实际可行性。 | BD60: 将组织的部分IT功能委托给外部专业公司执行。 | BE60: 安全威胁完全消除，信息安全得到加强。 | BF60: O | BG60: O | BH60: X | BI60: =10*SUMPRODUCT(--(AY60:BH60<>""),--(((AY60:BH60=정답표!$C$10:$L$10)+(AY60:BH60=정답표!$C$11:$L$11))>0)) -> 100 | BJ60: =SUM(Q60,AB60,AM60,AX60,BI60) -> 340 | BK60: =COUNT(Q60,AB60,AM60,AX60,BI60) -> 5 | BL60: =IF(QuizMatchTable[[#This Row],[분반]]=1, QuizMatchTable[[#This Row],[퀴즈합계]]/4 *0.3, QuizMatchTable[[#This Row],[퀴즈합계]]/5*0.3) -> 20.4 | BM60: 30 | BN60: 18.39 | BP60: =SUM(QuizMatchTable[[#This Row],[퀴즈점수(30)]],BM60,BN60,BO60) -> 68.79 | BQ60: =IF(OR(BP60="",BP60=0,BT60="결석초과"),"",COUNTIFS($B$2:$B$109,B60,$BP$2:$BP$109,">"&BP60)+1) -> 18 | BR60: B0 | BS60: 0
A61: 경영학과 | B61: 3 | C61: 20220136 | D61: 도기서 | E61: 010-3973-5932 | F61: 978283560@qq.com | G61: B. 피드백 및 반복 (反馈和迭代) | H61: D. 최소한의 비용과 시간 소모 (最低限度的成本和时间消耗) | I61: C. 운영적 의사결정 (运营性决策) | J61: C. 마케팅 전략 (营销策略) | K61: C. 문제해결 (问题解决) | L61: C. 착수 → 계획 → 실행 → 마무리 (启动 → 计划 → 执行 → 结束) | M61: A. 프로젝트 콘텐츠 (项目内容/产出物), B. 프로젝트 메타데이터 (项目元数据) | N61: B. 비동기적 소통 (Asynchronous Communication / 异步沟通) | O61: X (거짓/错) | P61: O (참/对) | Q61: =10*SUMPRODUCT(--(G61:P61<>""),--(((G61:P61=정답표!$C$2:$L$2)+(G61:P61=정답표!$C$3:$L$3))>0)) -> 100 | R61: BPR | S61: 遵循日常运营的正式化和标准化程序。 | T61: 企业间流程 | U61: 相同数据在多个部门重复存储，导致不一致。 | V61: 引入企业信息系统（EIS） | W61: 减少不必要的审批环节，从而最大限度地减少时间和资源。 | X61: 整合管理与客户的所有互动，最大限度地提高客户终身价值。 | Y61: 将业务运营整合到一个单一且一致的计算平台。 | Z61: O | AA61: O | AB61: =10*SUMPRODUCT(--(R61:AA61<>""),--(((R61:AA61=정답표!$C$4:$L$4)+(R61:AA61=정답표!$C$5:$L$5))>0)) -> 100 | AC61: 硬件、软件、社区、流程、人员 | AD61: 组织战略决定价值链，价值链决定业务流程，业务流程决定 SMIS 需求。 | AE61: 增加物质资本 | AF61: 直接销售用户数据：通过直接销售用户个人数据获取主要收入。 | AG61: 创新 (Innovation) | AH61: 指通过电子邮件、消息应用等难以追踪的渠道进行的社交分享区域，企业应在此处关注建立信任。 | AI61: 基于兴趣形成，一个用户可以同时属于多个社区。 | AJ61: 财务与会计 | AK61: O | AL61: O | AM61: =10*SUMPRODUCT(--(AC61:AL61<>""),--(((AC61:AL61=정답표!$C$6:$L$6)+(AC61:AL61=정답표!$C$7:$L$7))>0)) -> 90 | AN61: 在风险、成本和便利性之间找到适当的平衡。 | AO61: 因为将所有安全风险降至零在现实中是不可能且低效的。 | AP61: 未应用安全补丁的旧软件 | AQ61: 威胁能够访问系统或数据并造成损害的弱点。 | AR61: 将数据转换为未经授权的人无法理解的形式以进行保护的技术。 | AS61: 根据预设规则允许或阻止网络流量。 | AT61: 主要是技术部门制定和执行的技术问题。 | AU61: 定期测试备份数据是否能实际恢复非常重要。 | AV61: O | AW61: O | AX61: =10*SUMPRODUCT(--(AN61:AW61<>""),--(((AN61:AW61=정답표!$C$8:$L$8)+(AN61:AW61=정답표!$C$9:$L$9))>0)) -> 100 | AY61: 支持IT技术以实现组织目标，并将其与经营目标相结合。 | AZ61: 有效连接信息系统(IS)战略与企业经营战略。 | BA61: 根据组织的目标和优先顺序，综合考虑战略、预算和风险。 | BB61: 谁来做信息系统相关的决策，谁来承担责任？ | BC61: 综合考虑项目的战略适用性和实际可行性。 | BD61: 将组织的部分IT功能委托给外部专业公司执行。 | BE61: 安全威胁完全消除，信息安全得到加强。 | BF61: O | BG61: O | BH61: X | BI61: =10*SUMPRODUCT(--(AY61:BH61<>""),--(((AY61:BH61=정답표!$C$10:$L$10)+(AY61:BH61=정답표!$C$11:$L$11))>0)) -> 100 | BJ61: =SUM(Q61,AB61,AM61,AX61,BI61) -> 490 | BK61: =COUNT(Q61,AB61,AM61,AX61,BI61) -> 5 | BL61: =IF(QuizMatchTable[[#This Row],[분반]]=1, QuizMatchTable[[#This Row],[퀴즈합계]]/4 *0.3, QuizMatchTable[[#This Row],[퀴즈합계]]/5*0.3) -> 29.4 | BM61: 28.67 | BN61: 20 | BP61: =SUM(QuizMatchTable[[#This Row],[퀴즈점수(30)]],BM61,BN61,BO61) -> 78.07 | BQ61: =IF(OR(BP61="",BP61=0,BT61="결석초과"),"",COUNTIFS($B$2:$B$109,B61,$BP$2:$BP$109,">"&BP61)+1) -> 2 | BR61: A+ | BS61: 2
A62: 경영학과 | B62: 3 | C62: 20220137 | D62: 도말남 | E62: 010-2239-5296 | F62: 19953163390@163.com | G62: B. 피드백 및 반복 (反馈和迭代) | H62: D. 최소한의 비용과 시간 소모 (最低限度的成本和时间消耗) | I62: C. 운영적 의사결정 (运营性决策) | J62: C. 마케팅 전략 (营销策略) | K62: C. 문제해결 (问题解决) | L62: C. 착수 → 계획 → 실행 → 마무리 (启动 → 计划 → 执行 → 结束) | M62: A. 프로젝트 콘텐츠 (项目内容/产出物) | N62: B. 비동기적 소통 (Asynchronous Communication / 异步沟通) | O62: X (거짓/错) | P62: O (참/对) | Q62: =10*SUMPRODUCT(--(G62:P62<>""),--(((G62:P62=정답표!$C$2:$L$2)+(G62:P62=정답표!$C$3:$L$3))>0)) -> 90 | AC62: 硬件、软件、数据、流程、人员 | AD62: 组织战略决定价值链，价值链决定业务流程，业务流程决定 SMIS 需求。 | AE62: 增加物质资本 | AF62: 直接销售用户数据：通过直接销售用户个人数据获取主要收入。 | AG62: 创新 (Innovation) | AH62: 指通过电子邮件、消息应用等难以追踪的渠道进行的社交分享区域，企业应在此处关注建立信任。 | AI62: 基于兴趣形成，一个用户可以同时属于多个社区。 | AJ62: 财务与会计 | AK62: O | AL62: O | AM62: =10*SUMPRODUCT(--(AC62:AL62<>""),--(((AC62:AL62=정답표!$C$6:$L$6)+(AC62:AL62=정답표!$C$7:$L$7))>0)) -> 100 | AN62: 在风险、成本和便利性之间找到适当的平衡。 | AO62: 因为将所有安全风险降至零在现实中是不可能且低效的。 | AP62: 未应用安全补丁的旧软件 | AQ62: 威胁能够访问系统或数据并造成损害的弱点。 | AR62: 将数据转换为未经授权的人无法理解的形式以进行保护的技术。 | AS62: 根据预设规则允许或阻止网络流量。 | AT62: 主要是技术部门制定和执行的技术问题。 | AU62: 定期测试备份数据是否能实际恢复非常重要。 | AV62: O | AW62: O | AX62: =10*SUMPRODUCT(--(AN62:AW62<>""),--(((AN62:AW62=정답표!$C$8:$L$8)+(AN62:AW62=정답표!$C$9:$L$9))>0)) -> 100 | AY62: 支持IT技术以实现组织目标，并将其与经营目标相结合。 | AZ62: 有效连接信息系统(IS)战略与企业经营战略。 | BA62: 根据组织的目标和优先顺序，综合考虑战略、预算和风险。 | BB62: 谁来做信息系统相关的决策，谁来承担责任？ | BC62: 综合考虑项目的战略适用性和实际可行性。 | BD62: 将组织的部分IT功能委托给外部专业公司执行。 | BE62: 安全威胁完全消除，信息安全得到加强。 | BF62: O | BG62: O | BH62: X | BI62: =10*SUMPRODUCT(--(AY62:BH62<>""),--(((AY62:BH62=정답표!$C$10:$L$10)+(AY62:BH62=정답표!$C$11:$L$11))>0)) -> 100 | BJ62: =SUM(Q62,AB62,AM62,AX62,BI62) -> 390 | BK62: =COUNT(Q62,AB62,AM62,AX62,BI62) -> 4 | BL62: =IF(QuizMatchTable[[#This Row],[분반]]=1, QuizMatchTable[[#This Row],[퀴즈합계]]/4 *0.3, QuizMatchTable[[#This Row],[퀴즈합계]]/5*0.3) -> 23.4 | BM62: 27.33 | BN62: 16 | BP62: =SUM(QuizMatchTable[[#This Row],[퀴즈점수(30)]],BM62,BN62,BO62) -> 66.73 | BQ62: =IF(OR(BP62="",BP62=0,BT62="결석초과"),"",COUNTIFS($B$2:$B$109,B62,$BP$2:$BP$109,">"&BP62)+1) -> 22 | BR62: F | BS62: 4
A63: 경영학과 | B63: 3 | C63: 20220138 | D63: 동욱성 | E63: 010-8250-9362 | F63: 2315570141@qq.com | G63: B. 피드백 및 반복 (反馈和迭代) | H63: D. 최소한의 비용과 시간 소모 (最低限度的成本和时间消耗) | I63: C. 운영적 의사결정 (运营性决策) | J63: C. 마케팅 전략 (营销策略) | K63: C. 문제해결 (问题解决) | L63: C. 착수 → 계획 → 실행 → 마무리 (启动 → 计划 → 执行 → 结束) | M63: A. 프로젝트 콘텐츠 (项目内容/产出物), B. 프로젝트 메타데이터 (项目元数据) | N63: B. 비동기적 소통 (Asynchronous Communication / 异步沟通) | O63: X (거짓/错) | P63: O (참/对) | Q63: =10*SUMPRODUCT(--(G63:P63<>""),--(((G63:P63=정답표!$C$2:$L$2)+(G63:P63=정답표!$C$3:$L$3))>0)) -> 100 | R63: BPR | S63: 遵循日常运营的正式化和标准化程序。 | T63: 企业间流程 | U63: 相同数据在多个部门重复存储，导致不一致。 | V63: 引入企业信息系统（EIS） | W63: 减少不必要的审批环节，从而最大限度地减少时间和资源。 | X63: 整合管理与客户的所有互动，最大限度地提高客户终身价值。 | Y63: 实现现有分离系统之间的数据共享和通信。 | Z63: O | AA63: O | AB63: =10*SUMPRODUCT(--(R63:AA63<>""),--(((R63:AA63=정답표!$C$4:$L$4)+(R63:AA63=정답표!$C$5:$L$5))>0)) -> 90 | AN63: 在风险、成本和便利性之间找到适当的平衡。 | AO63: 因为将所有安全风险降至零在现实中是不可能且低效的。 | AP63: 未应用安全补丁的旧软件 | AQ63: 威胁能够访问系统或数据并造成损害的弱点。 | AR63: 将数据转换为未经授权的人无法理解的形式以进行保护的技术。 | AS63: 根据预设规则允许或阻止网络流量。 | AT63: 主要是技术部门制定和执行的技术问题。 | AU63: 定期测试备份数据是否能实际恢复非常重要。 | AV63: O | AW63: O | AX63: =10*SUMPRODUCT(--(AN63:AW63<>""),--(((AN63:AW63=정답표!$C$8:$L$8)+(AN63:AW63=정답표!$C$9:$L$9))>0)) -> 100 | AY63: 支持IT技术以实现组织目标，并将其与经营目标相结合。 | AZ63: 有效连接信息系统(IS)战略与企业经营战略。 | BA63: 根据组织的目标和优先顺序，综合考虑战略、预算和风险。 | BB63: 谁来做信息系统相关的决策，谁来承担责任？ | BC63: 综合考虑项目的战略适用性和实际可行性。 | BD63: 将组织的部分IT功能委托给外部专业公司执行。 | BE63: 安全威胁完全消除，信息安全得到加强。 | BF63: O | BG63: O | BH63: X | BI63: =10*SUMPRODUCT(--(AY63:BH63<>""),--(((AY63:BH63=정답표!$C$10:$L$10)+(AY63:BH63=정답표!$C$11:$L$11))>0)) -> 100 | BJ63: =SUM(Q63,AB63,AM63,AX63,BI63) -> 390 | BK63: =COUNT(Q63,AB63,AM63,AX63,BI63) -> 4 | BL63: =IF(QuizMatchTable[[#This Row],[분반]]=1, QuizMatchTable[[#This Row],[퀴즈합계]]/4 *0.3, QuizMatchTable[[#This Row],[퀴즈합계]]/5*0.3) -> 23.4 | BM63: 28 | BN63: 19.6 | BP63: =SUM(QuizMatchTable[[#This Row],[퀴즈점수(30)]],BM63,BN63,BO63) -> 71 | BQ63: =IF(OR(BP63="",BP63=0,BT63="결석초과"),"",COUNTIFS($B$2:$B$109,B63,$BP$2:$BP$109,">"&BP63)+1) -> 13 | BR63: B+ | BS63: 3
A64: 경영학과 | B64: 3 | C64: 20220148 | D64: 문미기 | E64: 010-2187-7281 | F64: 1590240163@qq.com | G64: D. 자원 할당 및 통제 (资源分配和控制) | H64: B. 팀 역량의 성장 (团队能力/素质的成长) | I64: A. 전략적 의사결정 (战略性决策) | J64: A. 하드웨어 (硬件) | K64: B. 의사결정 (决策制定) | L64: A. 계획 → 착수 → 실행 → 마무리 (计划 → 启动 → 执行 → 结束) | M64: A. 프로젝트 콘텐츠 (项目内容/产出物) | N64: B. 비동기적 소통 (Asynchronous Communication / 异步沟通) | O64: O (참/对) | P64: O (참/对) | Q64: =10*SUMPRODUCT(--(G64:P64<>""),--(((G64:P64=정답표!$C$2:$L$2)+(G64:P64=정답표!$C$3:$L$3))>0)) -> 20 | R64: BPR | S64: 遵循日常运营的正式化和标准化程序。 | T64: 工作组流程 | U64: 通过部门专业化系统，专业性得到加强。 | V64: 引入企业信息系统（EIS） | W64: 提高客户满意度以实现组织的战略目标。 | X64: 加强与供应链合作伙伴的协作，提高物流效率。 | Y64: 实现现有分离系统之间的数据共享和通信。 | Z64: O | AA64: O | AB64: =10*SUMPRODUCT(--(R64:AA64<>""),--(((R64:AA64=정답표!$C$4:$L$4)+(R64:AA64=정답표!$C$5:$L$5))>0)) -> 50 | AY64: 直接执行和管理组织内的所有业务流程。 | AZ64: 有效连接信息系统(IS)战略与企业经营战略。 | BA64: 考虑将所有业务功能委托给外部专业公司。 | BB64: 哪个部门使用的信息系统相关预算最多？ | BC64: 综合考虑项目的战略适用性和实际可行性。 | BD64: 将组织的部分IT功能委托给外部专业公司执行。 | BE64: 组织对供应商的依赖度可能增加。 | BF64: O | BG64: O | BH64: X | BI64: =10*SUMPRODUCT(--(AY64:BH64<>""),--(((AY64:BH64=정답표!$C$10:$L$10)+(AY64:BH64=정답표!$C$11:$L$11))>0)) -> 60 | BJ64: =SUM(Q64,AB64,AM64,AX64,BI64) -> 130 | BK64: =COUNT(Q64,AB64,AM64,AX64,BI64) -> 3 | BL64: =IF(QuizMatchTable[[#This Row],[분반]]=1, QuizMatchTable[[#This Row],[퀴즈합계]]/4 *0.3, QuizMatchTable[[#This Row],[퀴즈합계]]/5*0.3) -> 7.8 | BM64: 22.67 | BN64: 16.39 | BP64: =SUM(QuizMatchTable[[#This Row],[퀴즈점수(30)]],BM64,BN64,BO64) -> 46.86 | BQ64: =IF(OR(BP64="",BP64=0,BT64="결석초과"),"",COUNTIFS($B$2:$B$109,B64,$BP$2:$BP$109,">"&BP64)+1) -> 30 | BR64: F | BS64: 11
A65: 경영학과 | B65: 3 | C65: 20220150 | D65: 서문 | E65: 010-5587-0567 | F65: 2481937848@qq.com | G65: B. 피드백 및 반복 (反馈和迭代) | H65: D. 최소한의 비용과 시간 소모 (最低限度的成本和时间消耗) | I65: C. 운영적 의사결정 (运营性决策) | J65: C. 마케팅 전략 (营销策略) | K65: C. 문제해결 (问题解决) | L65: C. 착수 → 계획 → 실행 → 마무리 (启动 → 计划 → 执行 → 结束) | M65: A. 프로젝트 콘텐츠 (项目内容/产出物), B. 프로젝트 메타데이터 (项目元数据) | N65: B. 비동기적 소통 (Asynchronous Communication / 异步沟通) | O65: X (거짓/错) | P65: O (참/对) | Q65: =10*SUMPRODUCT(--(G65:P65<>""),--(((G65:P65=정답표!$C$2:$L$2)+(G65:P65=정답표!$C$3:$L$3))>0)) -> 100 | R65: BPR | S65: 遵循日常运营的正式化和标准化程序。 | T65: 企业间流程 | U65: 相同数据在多个部门重复存储，导致不一致。 | V65: 引入企业信息系统（EIS） | W65: 减少不必要的审批环节，从而最大限度地减少时间和资源。 | X65: 整合管理与客户的所有互动，最大限度地提高客户终身价值。 | Y65: 将业务运营整合到一个单一且一致的计算平台。 | Z65: O | AA65: O | AB65: =10*SUMPRODUCT(--(R65:AA65<>""),--(((R65:AA65=정답표!$C$4:$L$4)+(R65:AA65=정답표!$C$5:$L$5))>0)) -> 100 | AC65: 硬件、软件、数据、流程、人员 | AD65: 组织战略决定价值链，价值链决定业务流程，业务流程决定 SMIS 需求。 | AE65: 增加物质资本 | AF65: 直接销售用户数据：通过直接销售用户个人数据获取主要收入。 | AG65: 创新 (Innovation) | AH65: 指通过电子邮件、消息应用等难以追踪的渠道进行的社交分享区域，企业应在此处关注建立信任。 | AI65: 基于兴趣形成，一个用户可以同时属于多个社区。 | AJ65: 财务与会计 | AK65: O | AL65: O | AM65: =10*SUMPRODUCT(--(AC65:AL65<>""),--(((AC65:AL65=정답표!$C$6:$L$6)+(AC65:AL65=정답표!$C$7:$L$7))>0)) -> 100 | AN65: 在风险、成本和便利性之间找到适当的平衡。 | AO65: 因为将所有安全风险降至零在现实中是不可能且低效的。 | AP65: 未应用安全补丁的旧软件 | AQ65: 威胁能够访问系统或数据并造成损害的弱点。 | AR65: 将数据转换为未经授权的人无法理解的形式以进行保护的技术。 | AS65: 根据预设规则允许或阻止网络流量。 | AT65: 主要是技术部门制定和执行的技术问题。 | AU65: 定期测试备份数据是否能实际恢复非常重要。 | AV65: O | AW65: O | AX65: =10*SUMPRODUCT(--(AN65:AW65<>""),--(((AN65:AW65=정답표!$C$8:$L$8)+(AN65:AW65=정답표!$C$9:$L$9))>0)) -> 100 | AY65: 支持IT技术以实现组织目标，并将其与经营目标相结合。 | AZ65: 有效连接信息系统(IS)战略与企业经营战略。 | BA65: 根据组织的目标和优先顺序，综合考虑战略、预算和风险。 | BB65: 谁来做信息系统相关的决策，谁来承担责任？ | BC65: 综合考虑项目的战略适用性和实际可行性。 | BD65: 将组织的部分IT功能委托给外部专业公司执行。 | BE65: 安全威胁完全消除，信息安全得到加强。 | BF65: O | BG65: O | BH65: X | BI65: =10*SUMPRODUCT(--(AY65:BH65<>""),--(((AY65:BH65=정답표!$C$10:$L$10)+(AY65:BH65=정답표!$C$11:$L$11))>0)) -> 100 | BJ65: =SUM(Q65,AB65,AM65,AX65,BI65) -> 500 | BK65: =COUNT(Q65,AB65,AM65,AX65,BI65) -> 5 | BL65: =IF(QuizMatchTable[[#This Row],[분반]]=1, QuizMatchTable[[#This Row],[퀴즈합계]]/4 *0.3, QuizMatchTable[[#This Row],[퀴즈합계]]/5*0.3) -> 30 | BM65: 28.67 | BN65: 18.39 | BP65: =SUM(QuizMatchTable[[#This Row],[퀴즈점수(30)]],BM65,BN65,BO65) -> 77.06 | BQ65: =IF(OR(BP65="",BP65=0,BT65="결석초과"),"",COUNTIFS($B$2:$B$109,B65,$BP$2:$BP$109,">"&BP65)+1) -> 8 | BR65: A0 | BS65: 2
A66: 경영학과 | B66: 3 | C66: 20220155 | D66: 양원신 | E66: 010-7776-8361 | F66: 2553792661@qq.com | G66: B. 피드백 및 반복 (反馈和迭代) | H66: D. 최소한의 비용과 시간 소모 (最低限度的成本和时间消耗) | I66: C. 운영적 의사결정 (运营性决策) | J66: C. 마케팅 전략 (营销策略) | K66: C. 문제해결 (问题解决) | L66: C. 착수 → 계획 → 실행 → 마무리 (启动 → 计划 → 执行 → 结束) | M66: A. 프로젝트 콘텐츠 (项目内容/产出物), B. 프로젝트 메타데이터 (项目元数据) | N66: B. 비동기적 소통 (Asynchronous Communication / 异步沟通) | O66: X (거짓/错) | P66: O (참/对) | Q66: =10*SUMPRODUCT(--(G66:P66<>""),--(((G66:P66=정답표!$C$2:$L$2)+(G66:P66=정답표!$C$3:$L$3))>0)) -> 100 | R66: BPR | S66: 遵循日常运营的正式化和标准化程序。 | T66: 企业间流程 | U66: 相同数据在多个部门重复存储，导致不一致。 | V66: 引入企业信息系统（EIS） | W66: 减少不必要的审批环节，从而最大限度地减少时间和资源。 | X66: 整合管理与客户的所有互动，最大限度地提高客户终身价值。 | Y66: 将业务运营整合到一个单一且一致的计算平台。 | Z66: O | AA66: O | AB66: =10*SUMPRODUCT(--(R66:AA66<>""),--(((R66:AA66=정답표!$C$4:$L$4)+(R66:AA66=정답표!$C$5:$L$5))>0)) -> 100 | AC66: 硬件、软件、社区、流程、人员 | AD66: 组织战略决定价值链，价值链决定业务流程，业务流程决定 SMIS 需求。 | AE66: 增加物质资本 | AF66: 直接销售用户数据：通过直接销售用户个人数据获取主要收入。 | AG66: 创新 (Innovation) | AH66: 指通过电子邮件、消息应用等难以追踪的渠道进行的社交分享区域，企业应在此处关注建立信任。 | AI66: 基于兴趣形成，一个用户可以同时属于多个社区。 | AJ66: 财务与会计 | AK66: O | AL66: O | AM66: =10*SUMPRODUCT(--(AC66:AL66<>""),--(((AC66:AL66=정답표!$C$6:$L$6)+(AC66:AL66=정답표!$C$7:$L$7))>0)) -> 90 | AN66: 在风险、成本和便利性之间找到适当的平衡。 | AO66: 因为将所有安全风险降至零在现实中是不可能且低效的。 | AP66: 未应用安全补丁的旧软件 | AQ66: 威胁能够访问系统或数据并造成损害的弱点。 | AR66: 将数据转换为未经授权的人无法理解的形式以进行保护的技术。 | AS66: 根据预设规则允许或阻止网络流量。 | AT66: 主要是技术部门制定和执行的技术问题。 | AU66: 定期测试备份数据是否能实际恢复非常重要。 | AV66: O | AW66: O | AX66: =10*SUMPRODUCT(--(AN66:AW66<>""),--(((AN66:AW66=정답표!$C$8:$L$8)+(AN66:AW66=정답표!$C$9:$L$9))>0)) -> 100 | AY66: 支持IT技术以实现组织目标，并将其与经营目标相结合。 | AZ66: 有效连接信息系统(IS)战略与企业经营战略。 | BA66: 根据组织的目标和优先顺序，综合考虑战略、预算和风险。 | BB66: 谁来做信息系统相关的决策，谁来承担责任？ | BC66: 综合考虑项目的战略适用性和实际可行性。 | BD66: 将组织的部分IT功能委托给外部专业公司执行。 | BE66: 安全威胁完全消除，信息安全得到加强。 | BF66: O | BG66: O | BH66: X | BI66: =10*SUMPRODUCT(--(AY66:BH66<>""),--(((AY66:BH66=정답표!$C$10:$L$10)+(AY66:BH66=정답표!$C$11:$L$11))>0)) -> 100 | BJ66: =SUM(Q66,AB66,AM66,AX66,BI66) -> 490 | BK66: =COUNT(Q66,AB66,AM66,AX66,BI66) -> 5 | BL66: =IF(QuizMatchTable[[#This Row],[분반]]=1, QuizMatchTable[[#This Row],[퀴즈합계]]/4 *0.3, QuizMatchTable[[#This Row],[퀴즈합계]]/5*0.3) -> 29.4 | BM66: 30 | BN66: 16.39 | BP66: =SUM(QuizMatchTable[[#This Row],[퀴즈점수(30)]],BM66,BN66,BO66) -> 75.79 | BQ66: =IF(OR(BP66="",BP66=0,BT66="결석초과"),"",COUNTIFS($B$2:$B$109,B66,$BP$2:$BP$109,">"&BP66)+1) -> 9 | BR66: B+ | BS66: 0
A67: 경영학과 | B67: 3 | C67: 20220156 | D67: 양자건 | E67: 010-5793-1865 | F67: 3120046869@qq.com | G67: A. 계획 수립 및 예산 책정 (制定计划和预算) | H67: D. 최소한의 비용과 시간 소모 (最低限度的成本和时间消耗) | I67: D. 비구조적 의사결정 (非结构性决策) | J67: C. 마케팅 전략 (营销策略) | K67: D. 프로젝트 관리 (项目管理) | L67: C. 착수 → 계획 → 실행 → 마무리 (启动 → 计划 → 执行 → 结束) | M67: D. 팀원들의 개인정보 (团队成员的个人信息) | N67: A. 동기적 소통 (Synchronous Communication / 同步沟通) | O67: X (거짓/错) | P67: O (참/对) | Q67: =10*SUMPRODUCT(--(G67:P67<>""),--(((G67:P67=정답표!$C$2:$L$2)+(G67:P67=정답표!$C$3:$L$3))>0)) -> 50 | R67: ERP | S67: 频繁发生例外情况，并被设计为能够适应这些情况。 | T67: 工作组流程 | U67: 相同数据在多个部门重复存储，导致不一致。 | V67: 扩大手动数据输入和管理流程 | W67: 减少不必要的审批环节，从而最大限度地减少时间和资源。 | X67: 整合管理与客户的所有互动，最大限度地提高客户终身价值。 | Y67: 将业务运营整合到一个单一且一致的计算平台。 | Z67: O | AA67: O | AB67: =10*SUMPRODUCT(--(R67:AA67<>""),--(((R67:AA67=정답표!$C$4:$L$4)+(R67:AA67=정답표!$C$5:$L$5))>0)) -> 60 | AY67: 支持IT技术以实现组织目标，并将其与经营目标相结合。 | AZ67: 有效连接信息系统(IS)战略与企业经营战略。 | BA67: 根据组织的目标和优先顺序，综合考虑战略、预算和风险。 | BB67: 谁来做信息系统相关的决策，谁来承担责任？ | BC67: 综合考虑项目的战略适用性和实际可行性。 | BD67: 将组织的部分IT功能委托给外部专业公司执行。 | BE67: 安全威胁完全消除，信息安全得到加强。 | BF67: O | BG67: O | BH67: X | BI67: =10*SUMPRODUCT(--(AY67:BH67<>""),--(((AY67:BH67=정답표!$C$10:$L$10)+(AY67:BH67=정답표!$C$11:$L$11))>0)) -> 100 | BJ67: =SUM(Q67,AB67,AM67,AX67,BI67) -> 210 | BK67: =COUNT(Q67,AB67,AM67,AX67,BI67) -> 3 | BL67: =IF(QuizMatchTable[[#This Row],[분반]]=1, QuizMatchTable[[#This Row],[퀴즈합계]]/4 *0.3, QuizMatchTable[[#This Row],[퀴즈합계]]/5*0.3) -> 12.6 | BM67: 24.67 | BN67: 19.2 | BP67: =SUM(QuizMatchTable[[#This Row],[퀴즈점수(30)]],BM67,BN67,BO67) -> 56.47 | BQ67: =IF(OR(BP67="",BP67=0,BT67="결석초과"),"",COUNTIFS($B$2:$B$109,B67,$BP$2:$BP$109,">"&BP67)+1) -> 26 | BR67: F | BS67: 8
A68: 경영학과 | B68: 3 | C68: 20220157 | D68: 오강 | E68: 010-5862-8327 | F68: 826271866@qq.com | G68: B. 피드백 및 반복 (反馈和迭代) | H68: B. 팀 역량의 성장 (团队能力/素质的成长) | I68: C. 운영적 의사결정 (运营性决策) | J68: C. 마케팅 전략 (营销策略) | K68: C. 문제해결 (问题解决) | L68: C. 착수 → 계획 → 실행 → 마무리 (启动 → 计划 → 执行 → 结束) | M68: A. 프로젝트 콘텐츠 (项目内容/产出物), B. 프로젝트 메타데이터 (项目元数据) | N68: B. 비동기적 소통 (Asynchronous Communication / 异步沟通) | O68: X (거짓/错) | P68: O (참/对) | Q68: =10*SUMPRODUCT(--(G68:P68<>""),--(((G68:P68=정답표!$C$2:$L$2)+(G68:P68=정답표!$C$3:$L$3))>0)) -> 90 | R68: BPR | S68: 遵循日常运营的正式化和标准化程序。 | T68: 企业间流程 | U68: 相同数据在多个部门重复存储，导致不一致。 | V68: 引入企业信息系统（EIS） | W68: 减少不必要的审批环节，从而最大限度地减少时间和资源。 | X68: 整合管理与客户的所有互动，最大限度地提高客户终身价值。 | Y68: 将业务运营整合到一个单一且一致的计算平台。 | Z68: O | AA68: O | AB68: =10*SUMPRODUCT(--(R68:AA68<>""),--(((R68:AA68=정답표!$C$4:$L$4)+(R68:AA68=정답표!$C$5:$L$5))>0)) -> 100 | AC68: 硬件、软件、数据、流程、人员 | AD68: 组织战略决定价值链，价值链决定业务流程，业务流程决定 SMIS 需求。 | AE68: 增加物质资本 | AF68: 直接销售用户数据：通过直接销售用户个人数据获取主要收入。 | AG68: 创新 (Innovation) | AH68: 指通过电子邮件、消息应用等难以追踪的渠道进行的社交分享区域，企业应在此处关注建立信任。 | AI68: 基于兴趣形成，一个用户可以同时属于多个社区。 | AJ68: 财务与会计 | AK68: O | AL68: O | AM68: =10*SUMPRODUCT(--(AC68:AL68<>""),--(((AC68:AL68=정답표!$C$6:$L$6)+(AC68:AL68=정답표!$C$7:$L$7))>0)) -> 100 | AY68: 支持IT技术以实现组织目标，并将其与经营目标相结合。 | AZ68: 有效连接信息系统(IS)战略与企业经营战略。 | BA68: 根据组织的目标和优先顺序，综合考虑战略、预算和风险。 | BB68: 谁来做信息系统相关的决策，谁来承担责任？ | BC68: 综合考虑项目的战略适用性和实际可行性。 | BD68: 将组织的所有核心能力完全转移给外部公司。 | BE68: 安全威胁完全消除，信息安全得到加强。 | BF68: O | BG68: O | BH68: X | BI68: =10*SUMPRODUCT(--(AY68:BH68<>""),--(((AY68:BH68=정답표!$C$10:$L$10)+(AY68:BH68=정답표!$C$11:$L$11))>0)) -> 90 | BJ68: =SUM(Q68,AB68,AM68,AX68,BI68) -> 380 | BK68: =COUNT(Q68,AB68,AM68,AX68,BI68) -> 4 | BL68: =IF(QuizMatchTable[[#This Row],[분반]]=1, QuizMatchTable[[#This Row],[퀴즈합계]]/4 *0.3, QuizMatchTable[[#This Row],[퀴즈합계]]/5*0.3) -> 22.8 | BM68: 28 | BN68: 17.2 | BP68: =SUM(QuizMatchTable[[#This Row],[퀴즈점수(30)]],BM68,BN68,BO68) -> 68 | BQ68: =IF(OR(BP68="",BP68=0,BT68="결석초과"),"",COUNTIFS($B$2:$B$109,B68,$BP$2:$BP$109,">"&BP68)+1) -> 19 | BR68: B0 | BS68: 3
A69: 경영학과 | B69: 3 | C69: 20220158 | D69: 오이가 | E69: 010-8168-2097 | F69: 1417585421@qq.com | G69: B. 피드백 및 반복 (反馈和迭代) | H69: D. 최소한의 비용과 시간 소모 (最低限度的成本和时间消耗) | I69: C. 운영적 의사결정 (运营性决策) | J69: C. 마케팅 전략 (营销策略) | K69: C. 문제해결 (问题解决) | L69: C. 착수 → 계획 → 실행 → 마무리 (启动 → 计划 → 执行 → 结束) | M69: A. 프로젝트 콘텐츠 (项目内容/产出物), B. 프로젝트 메타데이터 (项目元数据) | N69: B. 비동기적 소통 (Asynchronous Communication / 异步沟通) | O69: X (거짓/错) | P69: O (참/对) | Q69: =10*SUMPRODUCT(--(G69:P69<>""),--(((G69:P69=정답표!$C$2:$L$2)+(G69:P69=정답표!$C$3:$L$3))>0)) -> 100 | R69: BPR | S69: 遵循日常运营的正式化和标准化程序。 | T69: 企业间流程 | U69: 相同数据在多个部门重复存储，导致不一致。 | V69: 引入企业信息系统（EIS） | W69: 减少不必要的审批环节，从而最大限度地减少时间和资源。 | X69: 整合管理与客户的所有互动，最大限度地提高客户终身价值。 | Y69: 将业务运营整合到一个单一且一致的计算平台。 | Z69: O | AA69: O | AB69: =10*SUMPRODUCT(--(R69:AA69<>""),--(((R69:AA69=정답표!$C$4:$L$4)+(R69:AA69=정답표!$C$5:$L$5))>0)) -> 100 | AC69: 硬件、软件、数据、流程、人员 | AD69: 业务流程决定 SMIS 需求，然后反过来塑造组织战略和价值链。 | AE69: 增加物质资本 | AF69: 直接销售用户数据：通过直接销售用户个人数据获取主要收入。 | AG69: 常识 (Common Sense) | AH69: 指通过电子邮件、消息应用等难以追踪的渠道进行的社交分享区域，企业应在此处关注建立信任。 | AI69: 基于兴趣形成，一个用户可以同时属于多个社区。 | AJ69: 财务与会计 | AK69: O | AL69: O | AM69: =10*SUMPRODUCT(--(AC69:AL69<>""),--(((AC69:AL69=정답표!$C$6:$L$6)+(AC69:AL69=정답표!$C$7:$L$7))>0)) -> 80 | AN69: 在风险、成本和便利性之间找到适当的平衡。 | AO69: 因为将所有安全风险降至零在现实中是不可能且低效的。 | AP69: 未应用安全补丁的旧软件 | AQ69: 威胁能够访问系统或数据并造成损害的弱点。 | AR69: 将数据转换为未经授权的人无法理解的形式以进行保护的技术。 | AS69: 根据预设规则允许或阻止网络流量。 | AT69: 主要是技术部门制定和执行的技术问题。 | AU69: 定期测试备份数据是否能实际恢复非常重要。 | AV69: O | AW69: O | AX69: =10*SUMPRODUCT(--(AN69:AW69<>""),--(((AN69:AW69=정답표!$C$8:$L$8)+(AN69:AW69=정답표!$C$9:$L$9))>0)) -> 100 | AY69: 支持IT技术以实现组织目标，并将其与经营目标相结合。 | AZ69: 有效连接信息系统(IS)战略与企业经营战略。 | BA69: 根据组织的目标和优先顺序，综合考虑战略、预算和风险。 | BB69: 谁最擅长操作电脑并拥有技术专业知识？ | BC69: 综合考虑项目的战略适用性和实际可行性。 | BD69: 将组织的所有核心能力完全转移给外部公司。 | BE69: 安全威胁完全消除，信息安全得到加强。 | BF69: O | BG69: O | BH69: X | BI69: =10*SUMPRODUCT(--(AY69:BH69<>""),--(((AY69:BH69=정답표!$C$10:$L$10)+(AY69:BH69=정답표!$C$11:$L$11))>0)) -> 80 | BJ69: =SUM(Q69,AB69,AM69,AX69,BI69) -> 460 | BK69: =COUNT(Q69,AB69,AM69,AX69,BI69) -> 5 | BL69: =IF(QuizMatchTable[[#This Row],[분반]]=1, QuizMatchTable[[#This Row],[퀴즈합계]]/4 *0.3, QuizMatchTable[[#This Row],[퀴즈합계]]/5*0.3) -> 27.6 | BM69: 28 | BN69: 19.2 | BP69: =SUM(QuizMatchTable[[#This Row],[퀴즈점수(30)]],BM69,BN69,BO69) -> 74.8 | BQ69: =IF(OR(BP69="",BP69=0,BT69="결석초과"),"",COUNTIFS($B$2:$B$109,B69,$BP$2:$BP$109,">"&BP69)+1) -> 10 | BR69: B+ | BS69: 3
A70: 경영학과 | B70: 3 | C70: 20220160 | D70: 왕욱상 | E70: 010-5658-6392 | F70: 2530511788@qq.com | G70: A. 계획 수립 및 예산 책정 (制定计划和预算) | H70: A. 성공적인 결과물 (目标达成) (成功的产物/成果) | I70: A. 전략적 의사결정 (战略性决策) | J70: C. 마케팅 전략 (营销策略) | K70: A. 정보 공유 (信息共享) | L70: C. 착수 → 계획 → 실행 → 마무리 (启动 → 计划 → 执行 → 结束) | M70: B. 프로젝트 메타데이터 (项目元数据), C. 경영진 보고서 (管理层报告) | N70: A. 동기적 소통 (Synchronous Communication / 同步沟通) | O70: O (참/对) | P70: O (참/对) | Q70: =10*SUMPRODUCT(--(G70:P70<>""),--(((G70:P70=정답표!$C$2:$L$2)+(G70:P70=정답표!$C$3:$L$3))>0)) -> 30 | R70: SCM | S70: 遵循日常运营的正式化和标准化程序。 | T70: 企业级流程 | U70: 相同数据在多个部门重复存储，导致不一致。 | V70: 维持部门独立的系统 | W70: 提高客户满意度以实现组织的战略目标。 | X70: 整合管理与客户的所有互动，最大限度地提高客户终身价值。 | Y70: 实现现有分离系统之间的数据共享和通信。 | Z70: O | AA70: O | AB70: =10*SUMPRODUCT(--(R70:AA70<>""),--(((R70:AA70=정답표!$C$4:$L$4)+(R70:AA70=정답표!$C$5:$L$5))>0)) -> 50 | BJ70: =SUM(Q70,AB70,AM70,AX70,BI70) -> 80 | BK70: =COUNT(Q70,AB70,AM70,AX70,BI70) -> 2 | BL70: =IF(QuizMatchTable[[#This Row],[분반]]=1, QuizMatchTable[[#This Row],[퀴즈합계]]/4 *0.3, QuizMatchTable[[#This Row],[퀴즈합계]]/5*0.3) -> 4.8 | BM70: 24 | BN70: 15.2 | BP70: =SUM(QuizMatchTable[[#This Row],[퀴즈점수(30)]],BM70,BN70,BO70) -> 44 | BQ70: =IF(OR(BP70="",BP70=0,BT70="결석초과"),"",COUNTIFS($B$2:$B$109,B70,$BP$2:$BP$109,">"&BP70)+1) -> 31 | BR70: F | BS70: 9
A71: 경영학과 | B71: 3 | C71: 20220161 | D71: 왕자선 | E71: 010-6615-9562 | F71: 1160383135@qq.com | G71: B. 피드백 및 반복 (反馈和迭代) | H71: D. 최소한의 비용과 시간 소모 (最低限度的成本和时间消耗) | I71: C. 운영적 의사결정 (运营性决策) | J71: C. 마케팅 전략 (营销策略) | K71: C. 문제해결 (问题解决) | L71: C. 착수 → 계획 → 실행 → 마무리 (启动 → 计划 → 执行 → 结束) | M71: A. 프로젝트 콘텐츠 (项目内容/产出物), B. 프로젝트 메타데이터 (项目元数据), C. 경영진 보고서 (管理层报告) | N71: B. 비동기적 소통 (Asynchronous Communication / 异步沟通) | O71: X (거짓/错) | P71: O (참/对) | Q71: =10*SUMPRODUCT(--(G71:P71<>""),--(((G71:P71=정답표!$C$2:$L$2)+(G71:P71=정답표!$C$3:$L$3))>0)) -> 90 | R71: BPR | S71: 遵循日常运营的正式化和标准化程序。 | T71: 企业间流程 | U71: 相同数据在多个部门重复存储，导致不一致。 | V71: 引入企业信息系统（EIS） | W71: 减少不必要的审批环节，从而最大限度地减少时间和资源。 | X71: 整合管理与客户的所有互动，最大限度地提高客户终身价值。 | Y71: 将业务运营整合到一个单一且一致的计算平台。 | Z71: O | AA71: O | AB71: =10*SUMPRODUCT(--(R71:AA71<>""),--(((R71:AA71=정답표!$C$4:$L$4)+(R71:AA71=정답표!$C$5:$L$5))>0)) -> 100 | AC71: 硬件、软件、数据、流程、人员 | AD71: 价值链直接设计动态流程流以推导出 SMIS 需求。 | AE71: 增加物质资本 | AF71: 直接销售用户数据：通过直接销售用户个人数据获取主要收入。 | AG71: 创新 (Innovation) | AH71: 指通过电子邮件、消息应用等难以追踪的渠道进行的社交分享区域，企业应在此处关注建立信任。 | AI71: 基于兴趣形成，一个用户可以同时属于多个社区。 | AJ71: 财务与会计 | AK71: O | AL71: O | AM71: =10*SUMPRODUCT(--(AC71:AL71<>""),--(((AC71:AL71=정답표!$C$6:$L$6)+(AC71:AL71=정답표!$C$7:$L$7))>0)) -> 90 | AN71: 在风险、成本和便利性之间找到适当的平衡。 | AO71: 因为将所有安全风险降至零在现实中是不可能且低效的。 | AP71: 将备份数据分离存储在外部存储器中的措施 | AQ71: 威胁能够访问系统或数据并造成损害的弱点。 | AR71: 将数据转换为未经授权的人无法理解的形式以进行保护的技术。 | AS71: 检测并自动清除渗透到系统中的恶意代码。 | AT71: 主要是技术部门制定和执行的技术问题。 | AU71: 定期测试备份数据是否能实际恢复非常重要。 | AV71: O | AW71: O | AX71: =10*SUMPRODUCT(--(AN71:AW71<>""),--(((AN71:AW71=정답표!$C$8:$L$8)+(AN71:AW71=정답표!$C$9:$L$9))>0)) -> 80 | BJ71: =SUM(Q71,AB71,AM71,AX71,BI71) -> 360 | BK71: =COUNT(Q71,AB71,AM71,AX71,BI71) -> 4 | BL71: =IF(QuizMatchTable[[#This Row],[분반]]=1, QuizMatchTable[[#This Row],[퀴즈합계]]/4 *0.3, QuizMatchTable[[#This Row],[퀴즈합계]]/5*0.3) -> 21.6 | BM71: 24 | BN71: 18.8 | BP71: =SUM(QuizMatchTable[[#This Row],[퀴즈점수(30)]],BM71,BN71,BO71) -> 64.4 | BQ71: =IF(OR(BP71="",BP71=0,BT71="결석초과"),"",COUNTIFS($B$2:$B$109,B71,$BP$2:$BP$109,">"&BP71)+1) -> 23 | BR71: F | BS71: 9
A72: 경영학과 | B72: 3 | C72: 20220162 | D72: 왕자함 | E72: 010-8265-9085 | F72: 3026199392@qq.com | G72: B. 피드백 및 반복 (反馈和迭代) | H72: D. 최소한의 비용과 시간 소모 (最低限度的成本和时间消耗) | I72: C. 운영적 의사결정 (运营性决策) | J72: C. 마케팅 전략 (营销策略) | K72: C. 문제해결 (问题解决) | L72: C. 착수 → 계획 → 실행 → 마무리 (启动 → 计划 → 执行 → 结束) | M72: A. 프로젝트 콘텐츠 (项目内容/产出物), B. 프로젝트 메타데이터 (项目元数据) | N72: B. 비동기적 소통 (Asynchronous Communication / 异步沟通) | O72: X (거짓/错) | P72: O (참/对) | Q72: =10*SUMPRODUCT(--(G72:P72<>""),--(((G72:P72=정답표!$C$2:$L$2)+(G72:P72=정답표!$C$3:$L$3))>0)) -> 100 | AC72: 硬件、软件、数据、流程、人员 | AD72: 组织战略决定价值链，价值链决定业务流程，业务流程决定 SMIS 需求。 | AE72: 增加物质资本 | AF72: 直接销售用户数据：通过直接销售用户个人数据获取主要收入。 | AG72: 创新 (Innovation) | AH72: 指通过电子邮件、消息应用等难以追踪的渠道进行的社交分享区域，企业应在此处关注建立信任。 | AI72: 基于兴趣形成，一个用户可以同时属于多个社区。 | AJ72: 财务与会计 | AK72: O | AL72: O | AM72: =10*SUMPRODUCT(--(AC72:AL72<>""),--(((AC72:AL72=정답표!$C$6:$L$6)+(AC72:AL72=정답표!$C$7:$L$7))>0)) -> 100 | AY72: 支持IT技术以实现组织目标，并将其与经营目标相结合。 | AZ72: 有效连接信息系统(IS)战略与企业经营战略。 | BA72: 根据组织的目标和优先顺序，综合考虑战略、预算和风险。 | BB72: 谁来做信息系统相关的决策，谁来承担责任？ | BC72: 综合考虑项目的战略适用性和实际可行性。 | BD72: 将组织的部分IT功能委托给外部专业公司执行。 | BE72: 安全威胁完全消除，信息安全得到加强。 | BF72: O | BG72: O | BH72: O | BI72: =10*SUMPRODUCT(--(AY72:BH72<>""),--(((AY72:BH72=정답표!$C$10:$L$10)+(AY72:BH72=정답표!$C$11:$L$11))>0)) -> 90 | BJ72: =SUM(Q72,AB72,AM72,AX72,BI72) -> 290 | BK72: =COUNT(Q72,AB72,AM72,AX72,BI72) -> 3 | BL72: =IF(QuizMatchTable[[#This Row],[분반]]=1, QuizMatchTable[[#This Row],[퀴즈합계]]/4 *0.3, QuizMatchTable[[#This Row],[퀴즈합계]]/5*0.3) -> 17.4 | BM72: 26.67 | BN72: 19.6 | BP72: =SUM(QuizMatchTable[[#This Row],[퀴즈점수(30)]],BM72,BN72,BO72) -> 63.67 | BQ72: =IF(OR(BP72="",BP72=0,BT72="결석초과"),"",COUNTIFS($B$2:$B$109,B72,$BP$2:$BP$109,">"&BP72)+1) -> 24 | BR72: F | BS72: 5
A73: 경영학과 | B73: 3 | C73: 20220163 | D73: 왕지정 | E73: 010-7503-5032 | F73: 378368151@qq.com | G73: B. 피드백 및 반복 (反馈和迭代) | H73: D. 최소한의 비용과 시간 소모 (最低限度的成本和时间消耗) | I73: C. 운영적 의사결정 (运营性决策) | J73: C. 마케팅 전략 (营销策略) | K73: C. 문제해결 (问题解决) | L73: C. 착수 → 계획 → 실행 → 마무리 (启动 → 计划 → 执行 → 结束) | M73: A. 프로젝트 콘텐츠 (项目内容/产出物), B. 프로젝트 메타데이터 (项目元数据) | N73: B. 비동기적 소통 (Asynchronous Communication / 异步沟通) | O73: X (거짓/错) | P73: O (참/对) | Q73: =10*SUMPRODUCT(--(G73:P73<>""),--(((G73:P73=정답표!$C$2:$L$2)+(G73:P73=정답표!$C$3:$L$3))>0)) -> 100 | R73: BPR | S73: 遵循日常运营的正式化和标准化程序。 | T73: 企业间流程 | U73: 相同数据在多个部门重复存储，导致不一致。 | V73: 引入企业信息系统（EIS） | W73: 减少不必要的审批环节，从而最大限度地减少时间和资源。 | X73: 整合管理与客户的所有互动，最大限度地提高客户终身价值。 | Y73: 将业务运营整合到一个单一且一致的计算平台。 | Z73: O | AA73: O | AB73: =10*SUMPRODUCT(--(R73:AA73<>""),--(((R73:AA73=정답표!$C$4:$L$4)+(R73:AA73=정답표!$C$5:$L$5))>0)) -> 100 | AC73: 硬件、软件、数据、流程、人员 | AD73: 组织战略决定价值链，价值链决定业务流程，业务流程决定 SMIS 需求。 | AE73: 增加物质资本 | AF73: 直接销售用户数据：通过直接销售用户个人数据获取主要收入。 | AG73: 创新 (Innovation) | AH73: 指通过电子邮件、消息应用等难以追踪的渠道进行的社交分享区域，企业应在此处关注建立信任。 | AI73: 基于兴趣形成，一个用户可以同时属于多个社区。 | AJ73: 财务与会计 | AK73: O | AL73: O | AM73: =10*SUMPRODUCT(--(AC73:AL73<>""),--(((AC73:AL73=정답표!$C$6:$L$6)+(AC73:AL73=정답표!$C$7:$L$7))>0)) -> 100 | AN73: 在风险、成本和便利性之间找到适当的平衡。 | AO73: 因为将所有安全风险降至零在现实中是不可能且低效的。 | AP73: 未应用安全补丁的旧软件 | AQ73: 威胁能够访问系统或数据并造成损害的弱点。 | AR73: 将数据转换为未经授权的人无法理解的形式以进行保护的技术。 | AS73: 根据预设规则允许或阻止网络流量。 | AT73: 主要是技术部门制定和执行的技术问题。 | AU73: 定期测试备份数据是否能实际恢复非常重要。 | AV73: O | AW73: O | AX73: =10*SUMPRODUCT(--(AN73:AW73<>""),--(((AN73:AW73=정답표!$C$8:$L$8)+(AN73:AW73=정답표!$C$9:$L$9))>0)) -> 100 | AY73: 支持IT技术以实现组织目标，并将其与经营目标相结合。 | AZ73: 有效连接信息系统(IS)战略与企业经营战略。 | BA73: 根据组织的目标和优先顺序，综合考虑战略、预算和风险。 | BB73: 谁来做信息系统相关的决策，谁来承担责任？ | BC73: 综合考虑项目的战略适用性和实际可行性。 | BD73: 将组织的部分IT功能委托给外部专业公司执行。 | BE73: 安全威胁完全消除，信息安全得到加强。 | BF73: O | BG73: O | BH73: X | BI73: =10*SUMPRODUCT(--(AY73:BH73<>""),--(((AY73:BH73=정답표!$C$10:$L$10)+(AY73:BH73=정답표!$C$11:$L$11))>0)) -> 100 | BJ73: =SUM(Q73,AB73,AM73,AX73,BI73) -> 500 | BK73: =COUNT(Q73,AB73,AM73,AX73,BI73) -> 5 | BL73: =IF(QuizMatchTable[[#This Row],[분반]]=1, QuizMatchTable[[#This Row],[퀴즈합계]]/4 *0.3, QuizMatchTable[[#This Row],[퀴즈합계]]/5*0.3) -> 30 | BM73: 28.67 | BN73: 19.2 | BP73: =SUM(QuizMatchTable[[#This Row],[퀴즈점수(30)]],BM73,BN73,BO73) -> 77.87 | BQ73: =IF(OR(BP73="",BP73=0,BT73="결석초과"),"",COUNTIFS($B$2:$B$109,B73,$BP$2:$BP$109,">"&BP73)+1) -> 3 | BR73: A+ | BS73: 2
A74: 경영학과 | B74: 3 | C74: 20220164 | D74: 왕효리 | E74: 010-3969-9256 | F74: 1058561233@qq.com | G74: B. 피드백 및 반복 (反馈和迭代) | H74: D. 최소한의 비용과 시간 소모 (最低限度的成本和时间消耗) | I74: C. 운영적 의사결정 (运营性决策) | J74: C. 마케팅 전략 (营销策略) | K74: C. 문제해결 (问题解决) | L74: C. 착수 → 계획 → 실행 → 마무리 (启动 → 计划 → 执行 → 结束) | M74: A. 프로젝트 콘텐츠 (项目内容/产出物), B. 프로젝트 메타데이터 (项目元数据) | N74: B. 비동기적 소통 (Asynchronous Communication / 异步沟通) | O74: X (거짓/错) | P74: O (참/对) | Q74: =10*SUMPRODUCT(--(G74:P74<>""),--(((G74:P74=정답표!$C$2:$L$2)+(G74:P74=정답표!$C$3:$L$3))>0)) -> 100 | R74: BPR | S74: 遵循日常运营的正式化和标准化程序。 | T74: 工作组流程 | U74: 相同数据在多个部门重复存储，导致不一致。 | V74: 引入企业信息系统（EIS） | W74: 减少不必要的审批环节，从而最大限度地减少时间和资源。 | X74: 整合管理与客户的所有互动，最大限度地提高客户终身价值。 | Y74: 将业务运营整合到一个单一且一致的计算平台。 | Z74: O | AA74: O | AB74: =10*SUMPRODUCT(--(R74:AA74<>""),--(((R74:AA74=정답표!$C$4:$L$4)+(R74:AA74=정답표!$C$5:$L$5))>0)) -> 90 | AC74: 内容、平台、网络、价值链、硬件 | AD74: SMIS 需求首先被确定，然后影响价值链和组织战略。 | AE74: 个人赋能 | AF74: 直接销售用户数据：通过直接销售用户个人数据获取主要收入。 | AG74: 保护 (Protection) | AH74: 指通过电子邮件、消息应用等难以追踪的渠道进行的社交分享区域，企业应在此处关注建立信任。 | AI74: 信息传播缓慢，主要倾向于由少数领导者控制。 | AJ74: 客户服务 | AK74: O | AL74: O | AM74: =10*SUMPRODUCT(--(AC74:AL74<>""),--(((AC74:AL74=정답표!$C$6:$L$6)+(AC74:AL74=정답표!$C$7:$L$7))>0)) -> 40 | AN74: 在风险、成本和便利性之间找到适当的平衡。 | AO74: 因为将所有安全风险降至零在现实中是不可能且低效的。 | AP74: 将备份数据分离存储在外部存储器中的措施 | AQ74: 外部试图绕过安全系统进行非法访问的行为。 | AR74: 将数据转换为未经授权的人无法理解的形式以进行保护的技术。 | AS74: 根据预设规则允许或阻止网络流量。 | AT74: 主要是技术部门制定和执行的技术问题。 | AU74: 定期测试备份数据是否能实际恢复非常重要。 | AV74: X | AW74: X | AX74: =10*SUMPRODUCT(--(AN74:AW74<>""),--(((AN74:AW74=정답표!$C$8:$L$8)+(AN74:AW74=정답표!$C$9:$L$9))>0)) -> 60 | AY74: 支持IT技术以实现组织目标，并将其与经营目标相结合。 | AZ74: 有效连接信息系统(IS)战略与企业经营战略。 | BA74: 根据组织的目标和优先顺序，综合考虑战略、预算和风险。 | BB74: 谁来做信息系统相关的决策，谁来承担责任？ | BC74: 综合考虑项目的战略适用性和实际可行性。 | BD74: 将组织的部分IT功能委托给外部专业公司执行。 | BE74: 安全威胁完全消除，信息安全得到加强。 | BF74: O | BG74: O | BH74: X | BI74: =10*SUMPRODUCT(--(AY74:BH74<>""),--(((AY74:BH74=정답표!$C$10:$L$10)+(AY74:BH74=정답표!$C$11:$L$11))>0)) -> 100 | BJ74: =SUM(Q74,AB74,AM74,AX74,BI74) -> 390 | BK74: =COUNT(Q74,AB74,AM74,AX74,BI74) -> 5 | BL74: =IF(QuizMatchTable[[#This Row],[분반]]=1, QuizMatchTable[[#This Row],[퀴즈합계]]/4 *0.3, QuizMatchTable[[#This Row],[퀴즈합계]]/5*0.3) -> 23.4 | BM74: 28 | BN74: 19.2 | BP74: =SUM(QuizMatchTable[[#This Row],[퀴즈점수(30)]],BM74,BN74,BO74) -> 70.6 | BQ74: =IF(OR(BP74="",BP74=0,BT74="결석초과"),"",COUNTIFS($B$2:$B$109,B74,$BP$2:$BP$109,">"&BP74)+1) -> 14 | BR74: B+ | BS74: 3
A75: 경영학과 | B75: 3 | C75: 20220165 | D75: 우도 | E75: 010-5723-7870 | F75: 2836190278@qq.com | G75: B. 피드백 및 반복 (反馈和迭代) | H75: D. 최소한의 비용과 시간 소모 (最低限度的成本和时间消耗) | I75: C. 운영적 의사결정 (运营性决策) | J75: C. 마케팅 전략 (营销策略) | K75: C. 문제해결 (问题解决) | L75: C. 착수 → 계획 → 실행 → 마무리 (启动 → 计划 → 执行 → 结束) | M75: A. 프로젝트 콘텐츠 (项目内容/产出物), D. 팀원들의 개인정보 (团队成员的个人信息) | N75: B. 비동기적 소통 (Asynchronous Communication / 异步沟通) | O75: X (거짓/错) | P75: O (참/对) | Q75: =10*SUMPRODUCT(--(G75:P75<>""),--(((G75:P75=정답표!$C$2:$L$2)+(G75:P75=정답표!$C$3:$L$3))>0)) -> 90 | R75: BPR | S75: 遵循日常运营的正式化和标准化程序。 | T75: 企业间流程 | U75: 相同数据在多个部门重复存储，导致不一致。 | V75: 引入企业信息系统（EIS） | W75: 减少不必要的审批环节，从而最大限度地减少时间和资源。 | X75: 整合管理与客户的所有互动，最大限度地提高客户终身价值。 | Y75: 将业务运营整合到一个单一且一致的计算平台。 | Z75: O | AA75: X | AB75: =10*SUMPRODUCT(--(R75:AA75<>""),--(((R75:AA75=정답표!$C$4:$L$4)+(R75:AA75=정답표!$C$5:$L$5))>0)) -> 90 | AC75: 硬件、软件、数据、流程、人员 | AD75: 组织战略决定价值链，价值链决定业务流程，业务流程决定 SMIS 需求。 | AE75: 增加物质资本 | AF75: 广告 (Advertising)：通过基于用户数据的定制广告获取收入。 | AG75: 常识 (Common Sense) | AH75: 指通过电子邮件、消息应用等难以追踪的渠道进行的社交分享区域，企业应在此处关注建立信任。 | AI75: 通过单向通信传递信息，用户之间的互动有限。 | AJ75: 制造与运营 | AK75: O | AL75: O | AM75: =10*SUMPRODUCT(--(AC75:AL75<>""),--(((AC75:AL75=정답표!$C$6:$L$6)+(AC75:AL75=정답표!$C$7:$L$7))>0)) -> 60 | AN75: 在风险、成本和便利性之间找到适当的平衡。 | AO75: 因为将所有安全风险降至零在现实中是不可能且低效的。 | AP75: 将备份数据分离存储在外部存储器中的措施 | AQ75: 威胁能够访问系统或数据并造成损害的弱点。 | AR75: 将数据转换为未经授权的人无法理解的形式以进行保护的技术。 | AS75: 根据预设规则允许或阻止网络流量。 | AT75: 主要是技术部门制定和执行的技术问题。 | AU75: 定期测试备份数据是否能实际恢复非常重要。 | AV75: O | AW75: O | AX75: =10*SUMPRODUCT(--(AN75:AW75<>""),--(((AN75:AW75=정답표!$C$8:$L$8)+(AN75:AW75=정답표!$C$9:$L$9))>0)) -> 90 | AY75: 支持IT技术以实现组织目标，并将其与经营目标相结合。 | AZ75: 有效连接信息系统(IS)战略与企业经营战略。 | BA75: 根据组织的目标和优先顺序，综合考虑战略、预算和风险。 | BB75: 哪个部门使用的信息系统相关预算最多？ | BC75: 以项目总成本是否最高作为标准。 | BD75: 将组织的部分IT功能委托给外部专业公司执行。 | BE75: 安全威胁完全消除，信息安全得到加强。 | BF75: O | BG75: O | BH75: X | BI75: =10*SUMPRODUCT(--(AY75:BH75<>""),--(((AY75:BH75=정답표!$C$10:$L$10)+(AY75:BH75=정답표!$C$11:$L$11))>0)) -> 80 | BJ75: =SUM(Q75,AB75,AM75,AX75,BI75) -> 410 | BK75: =COUNT(Q75,AB75,AM75,AX75,BI75) -> 5 | BL75: =IF(QuizMatchTable[[#This Row],[분반]]=1, QuizMatchTable[[#This Row],[퀴즈합계]]/4 *0.3, QuizMatchTable[[#This Row],[퀴즈합계]]/5*0.3) -> 24.6 | BM75: 26 | BN75: 3.2 | BP75: =SUM(QuizMatchTable[[#This Row],[퀴즈점수(30)]],BM75,BN75,BO75) -> 53.8 | BQ75: =IF(OR(BP75="",BP75=0,BT75="결석초과"),"",COUNTIFS($B$2:$B$109,B75,$BP$2:$BP$109,">"&BP75)+1) -> 28 | BR75: F | BS75: 6
A76: 경영학과 | B76: 3 | C76: 20220166 | D76: 원맹요 | E76: 010-5173-0752 | F76: 2256771714@qq.com | G76: B. 피드백 및 반복 (反馈和迭代) | H76: D. 최소한의 비용과 시간 소모 (最低限度的成本和时间消耗) | I76: C. 운영적 의사결정 (运营性决策) | J76: C. 마케팅 전략 (营销策略) | K76: C. 문제해결 (问题解决) | L76: C. 착수 → 계획 → 실행 → 마무리 (启动 → 计划 → 执行 → 结束) | M76: C. 경영진 보고서 (管理层报告) | N76: C. 구조적 소통 (Structured Communication / 结构化沟通) | O76: X (거짓/错) | P76: O (참/对) | Q76: =10*SUMPRODUCT(--(G76:P76<>""),--(((G76:P76=정답표!$C$2:$L$2)+(G76:P76=정답표!$C$3:$L$3))>0)) -> 80 | R76: BPR | S76: 遵循日常运营的正式化和标准化程序。 | T76: 企业间流程 | U76: 相同数据在多个部门重复存储，导致不一致。 | V76: 引入企业信息系统（EIS） | W76: 减少不必要的审批环节，从而最大限度地减少时间和资源。 | X76: 整合管理与客户的所有互动，最大限度地提高客户终身价值。 | Y76: 将业务运营整合到一个单一且一致的计算平台。 | Z76: O | AA76: O | AB76: =10*SUMPRODUCT(--(R76:AA76<>""),--(((R76:AA76=정답표!$C$4:$L$4)+(R76:AA76=정답표!$C$5:$L$5))>0)) -> 100 | AC76: 硬件、软件、数据、流程、人员 | AD76: 组织战略决定价值链，价值链决定业务流程，业务流程决定 SMIS 需求。 | AE76: 增加物质资本 | AF76: 直接销售用户数据：通过直接销售用户个人数据获取主要收入。 | AG76: 创新 (Innovation) | AH76: 指通过电子邮件、消息应用等难以追踪的渠道进行的社交分享区域，企业应在此处关注建立信任。 | AI76: 基于兴趣形成，一个用户可以同时属于多个社区。 | AJ76: 财务与会计 | AK76: O | AL76: O | AM76: =10*SUMPRODUCT(--(AC76:AL76<>""),--(((AC76:AL76=정답표!$C$6:$L$6)+(AC76:AL76=정답표!$C$7:$L$7))>0)) -> 100 | AN76: 在风险、成本和便利性之间找到适当的平衡。 | AO76: 因为将所有安全风险降至零在现实中是不可能且低效的。 | AP76: 未应用安全补丁的旧软件 | AQ76: 威胁能够访问系统或数据并造成损害的弱点。 | AS76: 根据预设规则允许或阻止网络流量。 | AT76: 主要是技术部门制定和执行的技术问题。 | AU76: 定期测试备份数据是否能实际恢复非常重要。 | AV76: O | AW76: O | AX76: =10*SUMPRODUCT(--(AN76:AW76<>""),--(((AN76:AW76=정답표!$C$8:$L$8)+(AN76:AW76=정답표!$C$9:$L$9))>0)) -> 90 | AY76: 支持IT技术以实现组织目标，并将其与经营目标相结合。 | AZ76: 有效连接信息系统(IS)战略与企业经营战略。 | BA76: 根据组织的目标和优先顺序，综合考虑战略、预算和风险。 | BB76: 谁来做信息系统相关的决策，谁来承担责任？ | BC76: 综合考虑项目的战略适用性和实际可行性。 | BD76: 将组织的部分IT功能委托给外部专业公司执行。 | BE76: 安全威胁完全消除，信息安全得到加强。 | BF76: O | BG76: O | BH76: X | BI76: =10*SUMPRODUCT(--(AY76:BH76<>""),--(((AY76:BH76=정답표!$C$10:$L$10)+(AY76:BH76=정답표!$C$11:$L$11))>0)) -> 100 | BJ76: =SUM(Q76,AB76,AM76,AX76,BI76) -> 470 | BK76: =COUNT(Q76,AB76,AM76,AX76,BI76) -> 5 | BL76: =IF(QuizMatchTable[[#This Row],[분반]]=1, QuizMatchTable[[#This Row],[퀴즈합계]]/4 *0.3, QuizMatchTable[[#This Row],[퀴즈합계]]/5*0.3) -> 28.2 | BM76: 30 | BN76: 19.2 | BP76: =SUM(QuizMatchTable[[#This Row],[퀴즈점수(30)]],BM76,BN76,BO76) -> 77.4 | BQ76: =IF(OR(BP76="",BP76=0,BT76="결석초과"),"",COUNTIFS($B$2:$B$109,B76,$BP$2:$BP$109,">"&BP76)+1) -> 6 | BR76: A0 | BS76: 0
A77: 경영학과 | B77: 3 | C77: 20220167 | D77: 원재모 | E77: 010-9689-1623 | F77: 18906191623@163.com | G77: B. 피드백 및 반복 (反馈和迭代) | H77: D. 최소한의 비용과 시간 소모 (最低限度的成本和时间消耗) | I77: C. 운영적 의사결정 (运营性决策) | J77: C. 마케팅 전략 (营销策略) | K77: C. 문제해결 (问题解决) | L77: C. 착수 → 계획 → 실행 → 마무리 (启动 → 计划 → 执行 → 结束) | M77: A. 프로젝트 콘텐츠 (项目内容/产出物), B. 프로젝트 메타데이터 (项目元数据) | N77: B. 비동기적 소통 (Asynchronous Communication / 异步沟通) | O77: X (거짓/错) | P77: O (참/对) | Q77: =10*SUMPRODUCT(--(G77:P77<>""),--(((G77:P77=정답표!$C$2:$L$2)+(G77:P77=정답표!$C$3:$L$3))>0)) -> 100 | R77: BPR | S77: 遵循日常运营的正式化和标准化程序。 | T77: 企业间流程 | U77: 相同数据在多个部门重复存储，导致不一致。 | V77: 引入企业信息系统（EIS） | W77: 减少不必要的审批环节，从而最大限度地减少时间和资源。 | X77: 整合管理与客户的所有互动，最大限度地提高客户终身价值。 | Y77: 将业务运营整合到一个单一且一致的计算平台。 | Z77: O | AA77: O | AB77: =10*SUMPRODUCT(--(R77:AA77<>""),--(((R77:AA77=정답표!$C$4:$L$4)+(R77:AA77=정답표!$C$5:$L$5))>0)) -> 100 | AC77: 硬件、软件、社区、流程、人员 | AD77: 组织战略决定价值链，价值链决定业务流程，业务流程决定 SMIS 需求。 | AE77: 增加物质资本 | AF77: 直接销售用户数据：通过直接销售用户个人数据获取主要收入。 | AG77: 创新 (Innovation) | AH77: 指通过电子邮件、消息应用等难以追踪的渠道进行的社交分享区域，企业应在此处关注建立信任。 | AI77: 基于兴趣形成，一个用户可以同时属于多个社区。 | AJ77: 财务与会计 | AK77: O | AL77: O | AM77: =10*SUMPRODUCT(--(AC77:AL77<>""),--(((AC77:AL77=정답표!$C$6:$L$6)+(AC77:AL77=정답표!$C$7:$L$7))>0)) -> 90 | AY77: 支持IT技术以实现组织目标，并将其与经营目标相结合。 | AZ77: 有效连接信息系统(IS)战略与企业经营战略。 | BA77: 根据组织的目标和优先顺序，综合考虑战略、预算和风险。 | BB77: 谁来做信息系统相关的决策，谁来承担责任？ | BC77: 综合考虑项目的战略适用性和实际可行性。 | BD77: 将组织的部分IT功能委托给外部专业公司执行。 | BE77: 安全威胁完全消除，信息安全得到加强。 | BF77: O | BG77: O | BH77: X | BI77: =10*SUMPRODUCT(--(AY77:BH77<>""),--(((AY77:BH77=정답표!$C$10:$L$10)+(AY77:BH77=정답표!$C$11:$L$11))>0)) -> 100 | BJ77: =SUM(Q77,AB77,AM77,AX77,BI77) -> 390 | BK77: =COUNT(Q77,AB77,AM77,AX77,BI77) -> 4 | BL77: =IF(QuizMatchTable[[#This Row],[분반]]=1, QuizMatchTable[[#This Row],[퀴즈합계]]/4 *0.3, QuizMatchTable[[#This Row],[퀴즈합계]]/5*0.3) -> 23.4 | BM77: 28 | BN77: 18 | BP77: =SUM(QuizMatchTable[[#This Row],[퀴즈점수(30)]],BM77,BN77,BO77) -> 69.4 | BQ77: =IF(OR(BP77="",BP77=0,BT77="결석초과"),"",COUNTIFS($B$2:$B$109,B77,$BP$2:$BP$109,">"&BP77)+1) -> 15 | BR77: B+ | BS77: 3
A78: 경영학과 | B78: 3 | C78: 20220168 | D78: 위자청 | E78: 010-9762-6822 | F78: 2671023289@qq.com | G78: B. 피드백 및 반복 (反馈和迭代) | H78: A. 성공적인 결과물 (目标达成) (成功的产物/成果) | I78: C. 운영적 의사결정 (运营性决策) | J78: C. 마케팅 전략 (营销策略) | K78: C. 문제해결 (问题解决) | L78: C. 착수 → 계획 → 실행 → 마무리 (启动 → 计划 → 执行 → 结束) | M78: A. 프로젝트 콘텐츠 (项目内容/产出物), B. 프로젝트 메타데이터 (项目元数据) | N78: A. 동기적 소통 (Synchronous Communication / 同步沟通) | O78: X (거짓/错) | P78: O (참/对) | Q78: =10*SUMPRODUCT(--(G78:P78<>""),--(((G78:P78=정답표!$C$2:$L$2)+(G78:P78=정답표!$C$3:$L$3))>0)) -> 80 | R78: BPR | S78: 遵循日常运营的正式化和标准化程序。 | T78: 企业间流程 | U78: 相同数据在多个部门重复存储，导致不一致。 | V78: 引入企业信息系统（EIS） | W78: 减少不必要的审批环节，从而最大限度地减少时间和资源。 | X78: 整合管理与客户的所有互动，最大限度地提高客户终身价值。 | Y78: 将业务运营整合到一个单一且一致的计算平台。 | Z78: O | AA78: O | AB78: =10*SUMPRODUCT(--(R78:AA78<>""),--(((R78:AA78=정답표!$C$4:$L$4)+(R78:AA78=정답표!$C$5:$L$5))>0)) -> 100 | AC78: 硬件、软件、数据、流程、人员 | AD78: 组织战略决定价值链，价值链决定业务流程，业务流程决定 SMIS 需求。 | AE78: 增加物质资本 | AF78: 直接销售用户数据：通过直接销售用户个人数据获取主要收入。 | AG78: 创新 (Innovation) | AH78: 指通过电子邮件、消息应用等难以追踪的渠道进行的社交分享区域，企业应在此处关注建立信任。 | AI78: 主要基于地理邻近性形成，成员之间凝聚力强。 | AJ78: 财务与会计 | AK78: O | AL78: O | AM78: =10*SUMPRODUCT(--(AC78:AL78<>""),--(((AC78:AL78=정답표!$C$6:$L$6)+(AC78:AL78=정답표!$C$7:$L$7))>0)) -> 90 | AN78: 在风险、成本和便利性之间找到适当的平衡。 | AO78: 因为将所有安全风险降至零在现实中是不可能且低效的。 | AP78: 未应用安全补丁的旧软件 | AQ78: 威胁能够访问系统或数据并造成损害的弱点。 | AR78: 将数据转换为未经授权的人无法理解的形式以进行保护的技术。 | AS78: 根据预设规则允许或阻止网络流量。 | AT78: 主要是技术部门制定和执行的技术问题。 | AU78: 定期测试备份数据是否能实际恢复非常重要。 | AV78: O | AW78: O | AX78: =10*SUMPRODUCT(--(AN78:AW78<>""),--(((AN78:AW78=정답표!$C$8:$L$8)+(AN78:AW78=정답표!$C$9:$L$9))>0)) -> 100 | AY78: 支持IT技术以实现组织目标，并将其与经营目标相结合。 | AZ78: 有效连接信息系统(IS)战略与企业经营战略。 | BA78: 根据组织的目标和优先顺序，综合考虑战略、预算和风险。 | BB78: 谁来做信息系统相关的决策，谁来承担责任？ | BC78: 综合考虑项目的战略适用性和实际可行性。 | BD78: 将组织的部分IT功能委托给外部专业公司执行。 | BE78: 安全威胁完全消除，信息安全得到加强。 | BF78: O | BG78: O | BH78: X | BI78: =10*SUMPRODUCT(--(AY78:BH78<>""),--(((AY78:BH78=정답표!$C$10:$L$10)+(AY78:BH78=정답표!$C$11:$L$11))>0)) -> 100 | BJ78: =SUM(Q78,AB78,AM78,AX78,BI78) -> 470 | BK78: =COUNT(Q78,AB78,AM78,AX78,BI78) -> 5 | BL78: =IF(QuizMatchTable[[#This Row],[분반]]=1, QuizMatchTable[[#This Row],[퀴즈합계]]/4 *0.3, QuizMatchTable[[#This Row],[퀴즈합계]]/5*0.3) -> 28.2 | BM78: 26.67 | BN78: 18 | BP78: =SUM(QuizMatchTable[[#This Row],[퀴즈점수(30)]],BM78,BN78,BO78) -> 72.87 | BQ78: =IF(OR(BP78="",BP78=0,BT78="결석초과"),"",COUNTIFS($B$2:$B$109,B78,$BP$2:$BP$109,">"&BP78)+1) -> 12 | BR78: B+ | BS78: 5
A79: 경영학과 | B79: 3 | C79: 20220171 | D79: 장서원 | E79: 010-8173-6015 | F79: 13220668660@163.com | R79: BPR | S79: 遵循日常运营的正式化和标准化程序。 | T79: 企业间流程 | U79: 相同数据在多个部门重复存储，导致不一致。 | V79: 引入企业信息系统（EIS） | W79: 减少不必要的审批环节，从而最大限度地减少时间和资源。 | X79: 整合管理与客户的所有互动，最大限度地提高客户终身价值。 | Y79: 将业务运营整合到一个单一且一致的计算平台。 | Z79: O | AA79: X | AB79: =10*SUMPRODUCT(--(R79:AA79<>""),--(((R79:AA79=정답표!$C$4:$L$4)+(R79:AA79=정답표!$C$5:$L$5))>0)) -> 90 | AC79: 硬件、软件、社区、流程、人员 | AD79: 组织战略决定价值链，价值链决定业务流程，业务流程决定 SMIS 需求。 | AE79: 增加物质资本 | AF79: 直接销售用户数据：通过直接销售用户个人数据获取主要收入。 | AG79: 创新 (Innovation) | AH79: 指通过电子邮件、消息应用等难以追踪的渠道进行的社交分享区域，企业应在此处关注建立信任。 | AI79: 通过单向通信传递信息，用户之间的互动有限。 | AJ79: 财务与会计 | AK79: O | AL79: O | AM79: =10*SUMPRODUCT(--(AC79:AL79<>""),--(((AC79:AL79=정답표!$C$6:$L$6)+(AC79:AL79=정답표!$C$7:$L$7))>0)) -> 80 | AN79: 在风险、成本和便利性之间找到适当的平衡。 | AO79: 因为将所有安全风险降至零在现实中是不可能且低效的。 | AP79: 未应用安全补丁的旧软件 | AQ79: 威胁能够访问系统或数据并造成损害的弱点。 | AR79: 将数据转换为未经授权的人无法理解的形式以进行保护的技术。 | AS79: 根据预设规则允许或阻止网络流量。 | AT79: 主要是技术部门制定和执行的技术问题。 | AU79: 定期测试备份数据是否能实际恢复非常重要。 | AV79: O | AW79: O | AX79: =10*SUMPRODUCT(--(AN79:AW79<>""),--(((AN79:AW79=정답표!$C$8:$L$8)+(AN79:AW79=정답표!$C$9:$L$9))>0)) -> 100 | BJ79: =SUM(Q79,AB79,AM79,AX79,BI79) -> 270 | BK79: =COUNT(Q79,AB79,AM79,AX79,BI79) -> 3 | BL79: =IF(QuizMatchTable[[#This Row],[분반]]=1, QuizMatchTable[[#This Row],[퀴즈합계]]/4 *0.3, QuizMatchTable[[#This Row],[퀴즈합계]]/5*0.3) -> 16.2 | BM79: 24.67 | BN79: 19.2 | BP79: =SUM(QuizMatchTable[[#This Row],[퀴즈점수(30)]],BM79,BN79,BO79) -> 60.07 | BQ79: =IF(OR(BP79="",BP79=0,BT79="결석초과"),"",COUNTIFS($B$2:$B$109,B79,$BP$2:$BP$109,">"&BP79)+1) -> 25 | BR79: F | BS79: 8
A80: 경영학과 | B80: 3 | C80: 20220172 | D80: 장양 | E80: 010-6891-5163 | F80: 2747324077@qq.com | G80: B. 피드백 및 반복 (反馈和迭代) | H80: D. 최소한의 비용과 시간 소모 (最低限度的成本和时间消耗) | I80: C. 운영적 의사결정 (运营性决策) | J80: C. 마케팅 전략 (营销策略) | K80: C. 문제해결 (问题解决) | L80: C. 착수 → 계획 → 실행 → 마무리 (启动 → 计划 → 执行 → 结束) | M80: A. 프로젝트 콘텐츠 (项目内容/产出物), B. 프로젝트 메타데이터 (项目元数据) | N80: B. 비동기적 소통 (Asynchronous Communication / 异步沟通) | O80: X (거짓/错) | P80: O (참/对) | Q80: =10*SUMPRODUCT(--(G80:P80<>""),--(((G80:P80=정답표!$C$2:$L$2)+(G80:P80=정답표!$C$3:$L$3))>0)) -> 100 | R80: BPR | S80: 遵循日常运营的正式化和标准化程序。 | T80: 企业间流程 | U80: 相同数据在多个部门重复存储，导致不一致。 | V80: 引入企业信息系统（EIS） | W80: 减少不必要的审批环节，从而最大限度地减少时间和资源。 | X80: 整合管理与客户的所有互动，最大限度地提高客户终身价值。 | Y80: 实现现有分离系统之间的数据共享和通信。 | Z80: O | AA80: O | AB80: =10*SUMPRODUCT(--(R80:AA80<>""),--(((R80:AA80=정답표!$C$4:$L$4)+(R80:AA80=정답표!$C$5:$L$5))>0)) -> 90 | AC80: 硬件、软件、数据、流程、人员 | AD80: 组织战略决定价值链，价值链决定业务流程，业务流程决定 SMIS 需求。 | AE80: 增加物质资本 | AF80: 直接销售用户数据：通过直接销售用户个人数据获取主要收入。 | AG80: 创新 (Innovation) | AH80: 指通过电子邮件、消息应用等难以追踪的渠道进行的社交分享区域，企业应在此处关注建立信任。 | AI80: 基于兴趣形成，一个用户可以同时属于多个社区。 | AJ80: 财务与会计 | AK80: O | AL80: O | AM80: =10*SUMPRODUCT(--(AC80:AL80<>""),--(((AC80:AL80=정답표!$C$6:$L$6)+(AC80:AL80=정답표!$C$7:$L$7))>0)) -> 100 | AN80: 在风险、成本和便利性之间找到适当的平衡。 | AO80: 因为将所有安全风险降至零在现实中是不可能且低效的。 | AP80: 未应用安全补丁的旧软件 | AQ80: 威胁能够访问系统或数据并造成损害的弱点。 | AR80: 将数据转换为未经授权的人无法理解的形式以进行保护的技术。 | AS80: 根据预设规则允许或阻止网络流量。 | AT80: 主要是技术部门制定和执行的技术问题。 | AU80: 定期测试备份数据是否能实际恢复非常重要。 | AV80: O | AW80: O | AX80: =10*SUMPRODUCT(--(AN80:AW80<>""),--(((AN80:AW80=정답표!$C$8:$L$8)+(AN80:AW80=정답표!$C$9:$L$9))>0)) -> 100 | BJ80: =SUM(Q80,AB80,AM80,AX80,BI80) -> 390 | BK80: =COUNT(Q80,AB80,AM80,AX80,BI80) -> 4 | BL80: =IF(QuizMatchTable[[#This Row],[분반]]=1, QuizMatchTable[[#This Row],[퀴즈합계]]/4 *0.3, QuizMatchTable[[#This Row],[퀴즈합계]]/5*0.3) -> 23.4 | BM80: 26.67 | BN80: 17.6 | BP80: =SUM(QuizMatchTable[[#This Row],[퀴즈점수(30)]],BM80,BN80,BO80) -> 67.67 | BQ80: =IF(OR(BP80="",BP80=0,BT80="결석초과"),"",COUNTIFS($B$2:$B$109,B80,$BP$2:$BP$109,">"&BP80)+1) -> 20 | BR80: F | BS80: 5
A81: 경영학과 | B81: 3 | C81: 20220173 | D81: 장우 | E81: 010-9859-8823 | F81: 1084882370@qq.com | R81: CRM | S81: 流程结构会随着组织的变化而迅速适应和改变。 | T81: 企业间流程 | U81: 数据泄露的担忧减少，安全控制变得容易。 | V81: 扩大手动数据输入和管理流程 | W81: 提高决策的准确性，为实现战略目标做出贡献。 | X81: 整合管理与客户的所有互动，最大限度地提高客户终身价值。 | Y81: 自动化特定工作组或单个部门的业务流程。 | Z81: O | AA81: O | AB81: =10*SUMPRODUCT(--(R81:AA81<>""),--(((R81:AA81=정답표!$C$4:$L$4)+(R81:AA81=정답표!$C$5:$L$5))>0)) -> 40 | AC81: 战略、价值链、产业结构、流程、安全 | AD81: 组织战略决定价值链，价值链决定业务流程，业务流程决定 SMIS 需求。 | AE81: 个人赋能 | AF81: 直接销售用户数据：通过直接销售用户个人数据获取主要收入。 | AG81: 常识 (Common Sense) | AH81: 指通过电子邮件、消息应用等难以追踪的渠道进行的社交分享区域，企业应在此处关注建立信任。 | AI81: 基于兴趣形成，一个用户可以同时属于多个社区。 | AJ81: 制造与运营 | AK81: O | AL81: O | AM81: =10*SUMPRODUCT(--(AC81:AL81<>""),--(((AC81:AL81=정답표!$C$6:$L$6)+(AC81:AL81=정답표!$C$7:$L$7))>0)) -> 60 | BJ81: =SUM(Q81,AB81,AM81,AX81,BI81) -> 100 | BK81: =COUNT(Q81,AB81,AM81,AX81,BI81) -> 2 | BL81: =IF(QuizMatchTable[[#This Row],[분반]]=1, QuizMatchTable[[#This Row],[퀴즈합계]]/4 *0.3, QuizMatchTable[[#This Row],[퀴즈합계]]/5*0.3) -> 6 | BM81: 26.67 | BN81: 15.6 | BP81: =SUM(QuizMatchTable[[#This Row],[퀴즈점수(30)]],BM81,BN81,BO81) -> 48.27 | BQ81: =IF(OR(BP81="",BP81=0,BT81="결석초과"),"",COUNTIFS($B$2:$B$109,B81,$BP$2:$BP$109,">"&BP81)+1) -> 29 | BR81: F | BS81: 5
A82: 경영학과 | B82: 3 | C82: 20220174 | D82: 장자가 | E82: 010-9503-8871 | F82: Zzj200408@outlook.com | G82: C. 분업 및 전문화 (分工和专业化) | H82: D. 최소한의 비용과 시간 소모 (最低限度的成本和时间消耗) | I82: C. 운영적 의사결정 (运营性决策) | J82: C. 마케팅 전략 (营销策略) | K82: C. 문제해결 (问题解决) | L82: C. 착수 → 계획 → 실행 → 마무리 (启动 → 计划 → 执行 → 结束) | M82: A. 프로젝트 콘텐츠 (项目内容/产出物), B. 프로젝트 메타데이터 (项目元数据) | N82: B. 비동기적 소통 (Asynchronous Communication / 异步沟通) | O82: X (거짓/错) | P82: O (참/对) | Q82: =10*SUMPRODUCT(--(G82:P82<>""),--(((G82:P82=정답표!$C$2:$L$2)+(G82:P82=정답표!$C$3:$L$3))>0)) -> 90 | R82: BPR | S82: 遵循日常运营的正式化和标准化程序。 | T82: 企业间流程 | U82: 相同数据在多个部门重复存储，导致不一致。 | V82: 引入企业信息系统（EIS） | W82: 减少不必要的审批环节，从而最大限度地减少时间和资源。 | X82: 整合管理与客户的所有互动，最大限度地提高客户终身价值。 | Y82: 将业务运营整合到一个单一且一致的计算平台。 | Z82: O | AA82: O | AB82: =10*SUMPRODUCT(--(R82:AA82<>""),--(((R82:AA82=정답표!$C$4:$L$4)+(R82:AA82=정답표!$C$5:$L$5))>0)) -> 100 | AC82: 硬件、软件、数据、流程、人员 | AD82: 组织战略决定价值链，价值链决定业务流程，业务流程决定 SMIS 需求。 | AE82: 增加物质资本 | AF82: 直接销售用户数据：通过直接销售用户个人数据获取主要收入。 | AG82: 创新 (Innovation) | AH82: 指通过电子邮件、消息应用等难以追踪的渠道进行的社交分享区域，企业应在此处关注建立信任。 | AI82: 基于兴趣形成，一个用户可以同时属于多个社区。 | AJ82: 财务与会计 | AK82: O | AL82: O | AM82: =10*SUMPRODUCT(--(AC82:AL82<>""),--(((AC82:AL82=정답표!$C$6:$L$6)+(AC82:AL82=정답표!$C$7:$L$7))>0)) -> 100 | AN82: 在风险、成本和便利性之间找到适当的平衡。 | AO82: 因为将所有安全风险降至零在现实中是不可能且低效的。 | AP82: 未应用安全补丁的旧软件 | AQ82: 威胁能够访问系统或数据并造成损害的弱点。 | AR82: 将数据转换为未经授权的人无法理解的形式以进行保护的技术。 | AS82: 根据预设规则允许或阻止网络流量。 | AT82: 主要是技术部门制定和执行的技术问题。 | AU82: 定期测试备份数据是否能实际恢复非常重要。 | AV82: O | AW82: O | AX82: =10*SUMPRODUCT(--(AN82:AW82<>""),--(((AN82:AW82=정답표!$C$8:$L$8)+(AN82:AW82=정답표!$C$9:$L$9))>0)) -> 100 | AY82: 支持IT技术以实现组织目标，并将其与经营目标相结合。 | AZ82: 有效连接信息系统(IS)战略与企业经营战略。 | BA82: 根据组织的目标和优先顺序，综合考虑战略、预算和风险。 | BB82: 谁来做信息系统相关的决策，谁来承担责任？ | BC82: 综合考虑项目的战略适用性和实际可行性。 | BD82: 将组织的部分IT功能委托给外部专业公司执行。 | BE82: 安全威胁完全消除，信息安全得到加强。 | BF82: O | BG82: O | BH82: X | BI82: =10*SUMPRODUCT(--(AY82:BH82<>""),--(((AY82:BH82=정답표!$C$10:$L$10)+(AY82:BH82=정답표!$C$11:$L$11))>0)) -> 100 | BJ82: =SUM(Q82,AB82,AM82,AX82,BI82) -> 490 | BK82: =COUNT(Q82,AB82,AM82,AX82,BI82) -> 5 | BL82: =IF(QuizMatchTable[[#This Row],[분반]]=1, QuizMatchTable[[#This Row],[퀴즈합계]]/4 *0.3, QuizMatchTable[[#This Row],[퀴즈합계]]/5*0.3) -> 29.4 | BM82: 30 | BN82: 18.39 | BP82: =SUM(QuizMatchTable[[#This Row],[퀴즈점수(30)]],BM82,BN82,BO82) -> 77.79 | BQ82: =IF(OR(BP82="",BP82=0,BT82="결석초과"),"",COUNTIFS($B$2:$B$109,B82,$BP$2:$BP$109,">"&BP82)+1) -> 4 | BR82: A+ | BS82: 0
A83: 경영학과 | B83: 3 | C83: 20220175 | D83: 장추실 | E83: 010-3916-0311 | F83: 1340505289@qq.com | G83: B. 피드백 및 반복 (反馈和迭代) | H83: D. 최소한의 비용과 시간 소모 (最低限度的成本和时间消耗) | I83: C. 운영적 의사결정 (运营性决策) | J83: C. 마케팅 전략 (营销策略) | K83: C. 문제해결 (问题解决) | L83: C. 착수 → 계획 → 실행 → 마무리 (启动 → 计划 → 执行 → 结束) | M83: A. 프로젝트 콘텐츠 (项目内容/产出物), B. 프로젝트 메타데이터 (项目元数据) | N83: B. 비동기적 소통 (Asynchronous Communication / 异步沟通) | O83: X (거짓/错) | P83: O (참/对) | Q83: =10*SUMPRODUCT(--(G83:P83<>""),--(((G83:P83=정답표!$C$2:$L$2)+(G83:P83=정답표!$C$3:$L$3))>0)) -> 100 | R83: BPR | S83: 遵循日常运营的正式化和标准化程序。 | T83: 企业级流程 | U83: 相同数据在多个部门重复存储，导致不一致。 | V83: 引入企业信息系统（EIS） | W83: 减少不必要的审批环节，从而最大限度地减少时间和资源。 | X83: 整合管理与客户的所有互动，最大限度地提高客户终身价值。 | Y83: 将业务运营整合到一个单一且一致的计算平台。 | Z83: O | AA83: O | AB83: =10*SUMPRODUCT(--(R83:AA83<>""),--(((R83:AA83=정답표!$C$4:$L$4)+(R83:AA83=정답표!$C$5:$L$5))>0)) -> 90 | AC83: 硬件、软件、数据、流程、人员 | AD83: 组织战略决定价值链，价值链决定业务流程，业务流程决定 SMIS 需求。 | AE83: 增加物质资本 | AF83: 直接销售用户数据：通过直接销售用户个人数据获取主要收入。 | AG83: 创新 (Innovation) | AH83: 指通过电子邮件、消息应用等难以追踪的渠道进行的社交分享区域，企业应在此处关注建立信任。 | AI83: 基于兴趣形成，一个用户可以同时属于多个社区。 | AJ83: 财务与会计 | AK83: O | AL83: O | AM83: =10*SUMPRODUCT(--(AC83:AL83<>""),--(((AC83:AL83=정답표!$C$6:$L$6)+(AC83:AL83=정답표!$C$7:$L$7))>0)) -> 100 | AN83: 在风险、成本和便利性之间找到适当的平衡。 | AO83: 因为将所有安全风险降至零在现实中是不可能且低效的。 | AP83: 未应用安全补丁的旧软件 | AQ83: 威胁能够访问系统或数据并造成损害的弱点。 | AR83: 将数据转换为未经授权的人无法理解的形式以进行保护的技术。 | AS83: 根据预设规则允许或阻止网络流量。 | AT83: 主要是技术部门制定和执行的技术问题。 | AU83: 定期测试备份数据是否能实际恢复非常重要。 | AV83: O | AW83: O | AX83: =10*SUMPRODUCT(--(AN83:AW83<>""),--(((AN83:AW83=정답표!$C$8:$L$8)+(AN83:AW83=정답표!$C$9:$L$9))>0)) -> 100 | AY83: 支持IT技术以实现组织目标，并将其与经营目标相结合。 | AZ83: 有效连接信息系统(IS)战略与企业经营战略。 | BA83: 根据组织的目标和优先顺序，综合考虑战略、预算和风险。 | BB83: 谁来做信息系统相关的决策，谁来承担责任？ | BC83: 综合考虑项目的战略适用性和实际可行性。 | BD83: 将组织的部分IT功能委托给外部专业公司执行。 | BE83: 安全威胁完全消除，信息安全得到加强。 | BF83: O | BG83: O | BH83: X | BI83: =10*SUMPRODUCT(--(AY83:BH83<>""),--(((AY83:BH83=정답표!$C$10:$L$10)+(AY83:BH83=정답표!$C$11:$L$11))>0)) -> 100 | BJ83: =SUM(Q83,AB83,AM83,AX83,BI83) -> 490 | BK83: =COUNT(Q83,AB83,AM83,AX83,BI83) -> 5 | BL83: =IF(QuizMatchTable[[#This Row],[분반]]=1, QuizMatchTable[[#This Row],[퀴즈합계]]/4 *0.3, QuizMatchTable[[#This Row],[퀴즈합계]]/5*0.3) -> 29.4 | BM83: 30 | BN83: 19.2 | BP83: =SUM(QuizMatchTable[[#This Row],[퀴즈점수(30)]],BM83,BN83,BO83) -> 78.6 | BQ83: =IF(OR(BP83="",BP83=0,BT83="결석초과"),"",COUNTIFS($B$2:$B$109,B83,$BP$2:$BP$109,">"&BP83)+1) -> 1 | BR83: A+ | BS83: 0
A84: 경영학과 | B84: 3 | C84: 20220176 | D84: 장택호 | E84: 010-2159-3160 | F84: 905090971@qq.com | G84: B. 피드백 및 반복 (反馈和迭代) | H84: D. 최소한의 비용과 시간 소모 (最低限度的成本和时间消耗) | I84: C. 운영적 의사결정 (运营性决策) | J84: C. 마케팅 전략 (营销策略) | K84: C. 문제해결 (问题解决) | L84: C. 착수 → 계획 → 실행 → 마무리 (启动 → 计划 → 执行 → 结束) | M84: A. 프로젝트 콘텐츠 (项目内容/产出物), B. 프로젝트 메타데이터 (项目元数据) | N84: B. 비동기적 소통 (Asynchronous Communication / 异步沟通) | O84: X (거짓/错) | P84: O (참/对) | Q84: =10*SUMPRODUCT(--(G84:P84<>""),--(((G84:P84=정답표!$C$2:$L$2)+(G84:P84=정답표!$C$3:$L$3))>0)) -> 100 | R84: BPR | S84: 遵循日常运营的正式化和标准化程序。 | T84: 企业间流程 | U84: 相同数据在多个部门重复存储，导致不一致。 | V84: 引入企业信息系统（EIS） | W84: 减少不必要的审批环节，从而最大限度地减少时间和资源。 | X84: 整合管理与客户的所有互动，最大限度地提高客户终身价值。 | Y84: 将业务运营整合到一个单一且一致的计算平台。 | Z84: O | AA84: O | AB84: =10*SUMPRODUCT(--(R84:AA84<>""),--(((R84:AA84=정답표!$C$4:$L$4)+(R84:AA84=정답표!$C$5:$L$5))>0)) -> 100 | AC84: 硬件、软件、数据、流程、人员 | AD84: 组织战略决定价值链，价值链决定业务流程，业务流程决定 SMIS 需求。 | AE84: 增加物质资本 | AF84: 直接销售用户数据：通过直接销售用户个人数据获取主要收入。 | AG84: 常识 (Common Sense) | AH84: 指通过电子邮件、消息应用等难以追踪的渠道进行的社交分享区域，企业应在此处关注建立信任。 | AI84: 基于兴趣形成，一个用户可以同时属于多个社区。 | AJ84: 财务与会计 | AK84: O | AL84: O | AM84: =10*SUMPRODUCT(--(AC84:AL84<>""),--(((AC84:AL84=정답표!$C$6:$L$6)+(AC84:AL84=정답표!$C$7:$L$7))>0)) -> 90 | AN84: 在风险、成本和便利性之间找到适当的平衡。 | AO84: 因为将所有安全风险降至零在现实中是不可能且低效的。 | AP84: 将备份数据分离存储在外部存储器中的措施 | AQ84: 威胁能够访问系统或数据并造成损害的弱点。 | AR84: 将数据转换为未经授权的人无法理解的形式以进行保护的技术。 | AT84: 与管理层、管理者、员工等所有组织成员的责任相关。 | AU84: 定期测试备份数据是否能实际恢复非常重要。 | AV84: O | AW84: O | AX84: =10*SUMPRODUCT(--(AN84:AW84<>""),--(((AN84:AW84=정답표!$C$8:$L$8)+(AN84:AW84=정답표!$C$9:$L$9))>0)) -> 70 | AY84: 支持IT技术以实现组织目标，并将其与经营目标相结合。 | AZ84: 有效连接信息系统(IS)战略与企业经营战略。 | BA84: 根据组织的目标和优先顺序，综合考虑战略、预算和风险。 | BB84: 谁来做信息系统相关的决策，谁来承担责任？ | BC84: 综合考虑项目的战略适用性和实际可行性。 | BD84: 将组织的部分IT功能委托给外部专业公司执行。 | BE84: 安全威胁完全消除，信息安全得到加强。 | BF84: O | BG84: O | BH84: X | BI84: =10*SUMPRODUCT(--(AY84:BH84<>""),--(((AY84:BH84=정답표!$C$10:$L$10)+(AY84:BH84=정답표!$C$11:$L$11))>0)) -> 100 | BJ84: =SUM(Q84,AB84,AM84,AX84,BI84) -> 460 | BK84: =COUNT(Q84,AB84,AM84,AX84,BI84) -> 5 | BL84: =IF(QuizMatchTable[[#This Row],[분반]]=1, QuizMatchTable[[#This Row],[퀴즈합계]]/4 *0.3, QuizMatchTable[[#This Row],[퀴즈합계]]/5*0.3) -> 27.6 | BM84: 30 | BN84: 19.6 | BP84: =SUM(QuizMatchTable[[#This Row],[퀴즈점수(30)]],BM84,BN84,BO84) -> 77.2 | BQ84: =IF(OR(BP84="",BP84=0,BT84="결석초과"),"",COUNTIFS($B$2:$B$109,B84,$BP$2:$BP$109,">"&BP84)+1) -> 7 | BR84: A0 | BS84: 0
A85: 경영학과 | B85: 3 | C85: 20220177 | D85: 장항예 | E85: 010-5659-7057 | F85: zhr1660896198@163.com | G85: B. 피드백 및 반복 (反馈和迭代) | H85: D. 최소한의 비용과 시간 소모 (最低限度的成本和时间消耗) | I85: C. 운영적 의사결정 (运营性决策) | J85: C. 마케팅 전략 (营销策略) | K85: C. 문제해결 (问题解决) | L85: C. 착수 → 계획 → 실행 → 마무리 (启动 → 计划 → 执行 → 结束) | M85: A. 프로젝트 콘텐츠 (项目内容/产出物) | N85: B. 비동기적 소통 (Asynchronous Communication / 异步沟通) | O85: X (거짓/错) | P85: O (참/对) | Q85: =10*SUMPRODUCT(--(G85:P85<>""),--(((G85:P85=정답표!$C$2:$L$2)+(G85:P85=정답표!$C$3:$L$3))>0)) -> 90 | AC85: 硬件、软件、数据、流程、人员 | AD85: 组织战略决定价值链，价值链决定业务流程，业务流程决定 SMIS 需求。 | AE85: 增加物质资本 | AF85: 直接销售用户数据：通过直接销售用户个人数据获取主要收入。 | AG85: 创新 (Innovation) | AH85: 指通过电子邮件、消息应用等难以追踪的渠道进行的社交分享区域，企业应在此处关注建立信任。 | AI85: 基于兴趣形成，一个用户可以同时属于多个社区。 | AJ85: 财务与会计 | AK85: O | AL85: O | AM85: =10*SUMPRODUCT(--(AC85:AL85<>""),--(((AC85:AL85=정답표!$C$6:$L$6)+(AC85:AL85=정답표!$C$7:$L$7))>0)) -> 100 | AN85: 在风险、成本和便利性之间找到适当的平衡。 | AO85: 因为将所有安全风险降至零在现实中是不可能且低效的。 | AP85: 未应用安全补丁的旧软件 | AQ85: 威胁能够访问系统或数据并造成损害的弱点。 | AR85: 将数据转换为未经授权的人无法理解的形式以进行保护的技术。 | AS85: 根据预设规则允许或阻止网络流量。 | AT85: 主要是技术部门制定和执行的技术问题。 | AU85: 定期测试备份数据是否能实际恢复非常重要。 | AV85: O | AW85: O | AX85: =10*SUMPRODUCT(--(AN85:AW85<>""),--(((AN85:AW85=정답표!$C$8:$L$8)+(AN85:AW85=정답표!$C$9:$L$9))>0)) -> 100 | AY85: 支持IT技术以实现组织目标，并将其与经营目标相结合。 | AZ85: 有效连接信息系统(IS)战略与企业经营战略。 | BA85: 根据组织的目标和优先顺序，综合考虑战略、预算和风险。 | BB85: 谁来做信息系统相关的决策，谁来承担责任？ | BC85: 综合考虑项目的战略适用性和实际可行性。 | BD85: 将组织的部分IT功能委托给外部专业公司执行。 | BE85: 安全威胁完全消除，信息安全得到加强。 | BF85: O | BG85: O | BH85: X | BI85: =10*SUMPRODUCT(--(AY85:BH85<>""),--(((AY85:BH85=정답표!$C$10:$L$10)+(AY85:BH85=정답표!$C$11:$L$11))>0)) -> 100 | BJ85: =SUM(Q85,AB85,AM85,AX85,BI85) -> 390 | BK85: =COUNT(Q85,AB85,AM85,AX85,BI85) -> 4 | BL85: =IF(QuizMatchTable[[#This Row],[분반]]=1, QuizMatchTable[[#This Row],[퀴즈합계]]/4 *0.3, QuizMatchTable[[#This Row],[퀴즈합계]]/5*0.3) -> 23.4 | BM85: 27.33 | BN85: 18.39 | BP85: =SUM(QuizMatchTable[[#This Row],[퀴즈점수(30)]],BM85,BN85,BO85) -> 69.12 | BQ85: =IF(OR(BP85="",BP85=0,BT85="결석초과"),"",COUNTIFS($B$2:$B$109,B85,$BP$2:$BP$109,">"&BP85)+1) -> 17 | BR85: B0 | BS85: 4
A86: 경영학과 | B86: 3 | C86: 20220179 | D86: 전자의 | E86: 010-8417-8079 | F86: 1799058590@qq.com | G86: B. 피드백 및 반복 (反馈和迭代) | H86: D. 최소한의 비용과 시간 소모 (最低限度的成本和时间消耗) | I86: C. 운영적 의사결정 (运营性决策) | J86: C. 마케팅 전략 (营销策略) | K86: C. 문제해결 (问题解决) | L86: C. 착수 → 계획 → 실행 → 마무리 (启动 → 计划 → 执行 → 结束) | M86: A. 프로젝트 콘텐츠 (项目内容/产出物), B. 프로젝트 메타데이터 (项目元数据) | N86: B. 비동기적 소통 (Asynchronous Communication / 异步沟通) | O86: X (거짓/错) | P86: O (참/对) | Q86: =10*SUMPRODUCT(--(G86:P86<>""),--(((G86:P86=정답표!$C$2:$L$2)+(G86:P86=정답표!$C$3:$L$3))>0)) -> 100 | R86: ERP | S86: 遵循日常运营的正式化和标准化程序。 | T86: 企业间流程 | U86: 相同数据在多个部门重复存储，导致不一致。 | V86: 引入企业信息系统（EIS） | W86: 减少不必要的审批环节，从而最大限度地减少时间和资源。 | X86: 整合管理与客户的所有互动，最大限度地提高客户终身价值。 | Y86: 将业务运营整合到一个单一且一致的计算平台。 | Z86: O | AA86: O | AB86: =10*SUMPRODUCT(--(R86:AA86<>""),--(((R86:AA86=정답표!$C$4:$L$4)+(R86:AA86=정답표!$C$5:$L$5))>0)) -> 90 | AC86: 硬件、软件、数据、流程、人员 | AD86: 组织战略决定价值链，价值链决定业务流程，业务流程决定 SMIS 需求。 | AE86: 增加物质资本 | AF86: 直接销售用户数据：通过直接销售用户个人数据获取主要收入。 | AG86: 创新 (Innovation) | AH86: 指通过电子邮件、消息应用等难以追踪的渠道进行的社交分享区域，企业应在此处关注建立信任。 | AI86: 基于兴趣形成，一个用户可以同时属于多个社区。 | AJ86: 财务与会计 | AK86: O | AL86: O | AM86: =10*SUMPRODUCT(--(AC86:AL86<>""),--(((AC86:AL86=정답표!$C$6:$L$6)+(AC86:AL86=정답표!$C$7:$L$7))>0)) -> 100 | AY86: 支持IT技术以实现组织目标，并将其与经营目标相结合。 | AZ86: 有效连接信息系统(IS)战略与企业经营战略。 | BA86: 根据组织的目标和优先顺序，综合考虑战略、预算和风险。 | BB86: 谁来做信息系统相关的决策，谁来承担责任？ | BC86: 综合考虑项目的战略适用性和实际可行性。 | BD86: 将组织的部分IT功能委托给外部专业公司执行。 | BE86: 安全威胁完全消除，信息安全得到加强。 | BF86: O | BG86: O | BH86: X | BI86: =10*SUMPRODUCT(--(AY86:BH86<>""),--(((AY86:BH86=정답표!$C$10:$L$10)+(AY86:BH86=정답표!$C$11:$L$11))>0)) -> 100 | BJ86: =SUM(Q86,AB86,AM86,AX86,BI86) -> 390 | BK86: =COUNT(Q86,AB86,AM86,AX86,BI86) -> 4 | BL86: =IF(QuizMatchTable[[#This Row],[분반]]=1, QuizMatchTable[[#This Row],[퀴즈합계]]/4 *0.3, QuizMatchTable[[#This Row],[퀴즈합계]]/5*0.3) -> 23.4 | BM86: 28 | BN86: 18 | BP86: =SUM(QuizMatchTable[[#This Row],[퀴즈점수(30)]],BM86,BN86,BO86) -> 69.4 | BQ86: =IF(OR(BP86="",BP86=0,BT86="결석초과"),"",COUNTIFS($B$2:$B$109,B86,$BP$2:$BP$109,">"&BP86)+1) -> 15 | BR86: B+ | BS86: 3
A87: 경영학과 | B87: 3 | C87: 20220183 | D87: 좌영영 | E87: 010-8107-4896 | F87: 3394965226@qq.com | G87: C. 분업 및 전문화 (分工和专业化) | H87: D. 최소한의 비용과 시간 소모 (最低限度的成本和时间消耗) | I87: C. 운영적 의사결정 (运营性决策) | J87: C. 마케팅 전략 (营销策略) | K87: C. 문제해결 (问题解决) | L87: C. 착수 → 계획 → 실행 → 마무리 (启动 → 计划 → 执行 → 结束) | M87: A. 프로젝트 콘텐츠 (项目内容/产出物), B. 프로젝트 메타데이터 (项目元数据) | N87: B. 비동기적 소통 (Asynchronous Communication / 异步沟通) | O87: X (거짓/错) | P87: O (참/对) | Q87: =10*SUMPRODUCT(--(G87:P87<>""),--(((G87:P87=정답표!$C$2:$L$2)+(G87:P87=정답표!$C$3:$L$3))>0)) -> 90 | R87: BPR | S87: 遵循日常运营的正式化和标准化程序。 | T87: 企业间流程 | U87: 相同数据在多个部门重复存储，导致不一致。 | V87: 引入企业信息系统（EIS） | W87: 减少不必要的审批环节，从而最大限度地减少时间和资源。 | X87: 整合管理与客户的所有互动，最大限度地提高客户终身价值。 | Y87: 将业务运营整合到一个单一且一致的计算平台。 | Z87: O | AA87: O | AB87: =10*SUMPRODUCT(--(R87:AA87<>""),--(((R87:AA87=정답표!$C$4:$L$4)+(R87:AA87=정답표!$C$5:$L$5))>0)) -> 100 | AC87: 硬件、软件、数据、流程、人员 | AD87: 组织战略决定价值链，价值链决定业务流程，业务流程决定 SMIS 需求。 | AE87: 增加物质资本 | AF87: 直接销售用户数据：通过直接销售用户个人数据获取主要收入。 | AG87: 创新 (Innovation) | AH87: 指通过电子邮件、消息应用等难以追踪的渠道进行的社交分享区域，企业应在此处关注建立信任。 | AI87: 基于兴趣形成，一个用户可以同时属于多个社区。 | AJ87: 财务与会计 | AK87: O | AL87: O | AM87: =10*SUMPRODUCT(--(AC87:AL87<>""),--(((AC87:AL87=정답표!$C$6:$L$6)+(AC87:AL87=정답표!$C$7:$L$7))>0)) -> 100 | AN87: 在风险、成本和便利性之间找到适当的平衡。 | AO87: 因为将所有安全风险降至零在现实中是不可能且低效的。 | AP87: 未应用安全补丁的旧软件 | AQ87: 威胁能够访问系统或数据并造成损害的弱点。 | AR87: 将数据转换为未经授权的人无法理解的形式以进行保护的技术。 | AS87: 根据预设规则允许或阻止网络流量。 | AT87: 主要是技术部门制定和执行的技术问题。 | AU87: 定期测试备份数据是否能实际恢复非常重要。 | AV87: O | AW87: O | AX87: =10*SUMPRODUCT(--(AN87:AW87<>""),--(((AN87:AW87=정답표!$C$8:$L$8)+(AN87:AW87=정답표!$C$9:$L$9))>0)) -> 100 | AY87: 支持IT技术以实现组织目标，并将其与经营目标相结合。 | AZ87: 有效连接信息系统(IS)战略与企业经营战略。 | BA87: 根据组织的目标和优先顺序，综合考虑战略、预算和风险。 | BB87: 谁来做信息系统相关的决策，谁来承担责任？ | BC87: 综合考虑项目的战略适用性和实际可行性。 | BD87: 将组织的部分IT功能委托给外部专业公司执行。 | BE87: 安全威胁完全消除，信息安全得到加强。 | BF87: O | BG87: O | BH87: X | BI87: =10*SUMPRODUCT(--(AY87:BH87<>""),--(((AY87:BH87=정답표!$C$10:$L$10)+(AY87:BH87=정답표!$C$11:$L$11))>0)) -> 100 | BJ87: =SUM(Q87,AB87,AM87,AX87,BI87) -> 490 | BK87: =COUNT(Q87,AB87,AM87,AX87,BI87) -> 5 | BL87: =IF(QuizMatchTable[[#This Row],[분반]]=1, QuizMatchTable[[#This Row],[퀴즈합계]]/4 *0.3, QuizMatchTable[[#This Row],[퀴즈합계]]/5*0.3) -> 29.4 | BM87: 25.33 | BN87: 18.39 | BP87: =SUM(QuizMatchTable[[#This Row],[퀴즈점수(30)]],BM87,BN87,BO87) -> 73.12 | BQ87: =IF(OR(BP87="",BP87=0,BT87="결석초과"),"",COUNTIFS($B$2:$B$109,B87,$BP$2:$BP$109,">"&BP87)+1) -> 11 | BR87: B+ | BS87: 7
A88: 경영학과 | B88: 3 | C88: 20220186 | D88: 초함지 | E88: 010-5549-8621 | F88: 3504872117@qq.com | G88: B. 피드백 및 반복 (反馈和迭代) | H88: D. 최소한의 비용과 시간 소모 (最低限度的成本和时间消耗) | I88: C. 운영적 의사결정 (运营性决策) | J88: C. 마케팅 전략 (营销策略) | K88: C. 문제해결 (问题解决) | L88: A. 계획 → 착수 → 실행 → 마무리 (计划 → 启动 → 执行 → 结束) | M88: A. 프로젝트 콘텐츠 (项目内容/产出物), D. 팀원들의 개인정보 (团队成员的个人信息) | N88: B. 비동기적 소통 (Asynchronous Communication / 异步沟通) | O88: X (거짓/错) | P88: O (참/对) | Q88: =10*SUMPRODUCT(--(G88:P88<>""),--(((G88:P88=정답표!$C$2:$L$2)+(G88:P88=정답표!$C$3:$L$3))>0)) -> 80 | AC88: 硬件、软件、数据、流程、人员 | AD88: 组织战略决定价值链，价值链决定业务流程，业务流程决定 SMIS 需求。 | AE88: 增加物质资本 | AF88: 直接销售用户数据：通过直接销售用户个人数据获取主要收入。 | AG88: 创新 (Innovation) | AH88: 指通过电子邮件、消息应用等难以追踪的渠道进行的社交分享区域，企业应在此处关注建立信任。 | AI88: 基于兴趣形成，一个用户可以同时属于多个社区。 | AJ88: 财务与会计 | AK88: O | AL88: O | AM88: =10*SUMPRODUCT(--(AC88:AL88<>""),--(((AC88:AL88=정답표!$C$6:$L$6)+(AC88:AL88=정답표!$C$7:$L$7))>0)) -> 100 | AN88: 在风险、成本和便利性之间找到适当的平衡。 | AO88: 因为将所有安全风险降至零在现实中是不可能且低效的。 | AP88: 未应用安全补丁的旧软件 | AQ88: 威胁能够访问系统或数据并造成损害的弱点。 | AR88: 验证用户身份并授予系统访问权限的技术。 | AS88: 根据预设规则允许或阻止网络流量。 | AT88: 主要是技术部门制定和执行的技术问题。 | AU88: 定期测试备份数据是否能实际恢复非常重要。 | AV88: O | AW88: O | AX88: =10*SUMPRODUCT(--(AN88:AW88<>""),--(((AN88:AW88=정답표!$C$8:$L$8)+(AN88:AW88=정답표!$C$9:$L$9))>0)) -> 90 | AY88: 支持IT技术以实现组织目标，并将其与经营目标相结合。 | AZ88: 有效连接信息系统(IS)战略与企业经营战略。 | BA88: 根据组织的目标和优先顺序，综合考虑战略、预算和风险。 | BB88: 谁来做信息系统相关的决策，谁来承担责任？ | BC88: 综合考虑项目的战略适用性和实际可行性。 | BD88: 将组织的所有核心能力完全转移给外部公司。 | BE88: 安全威胁完全消除，信息安全得到加强。 | BF88: O | BG88: O | BH88: X | BI88: =10*SUMPRODUCT(--(AY88:BH88<>""),--(((AY88:BH88=정답표!$C$10:$L$10)+(AY88:BH88=정답표!$C$11:$L$11))>0)) -> 90 | BJ88: =SUM(Q88,AB88,AM88,AX88,BI88) -> 360 | BK88: =COUNT(Q88,AB88,AM88,AX88,BI88) -> 4 | BL88: =IF(QuizMatchTable[[#This Row],[분반]]=1, QuizMatchTable[[#This Row],[퀴즈합계]]/4 *0.3, QuizMatchTable[[#This Row],[퀴즈합계]]/5*0.3) -> 21.6 | BM88: 27.33 | BN88: 18.39 | BP88: =SUM(QuizMatchTable[[#This Row],[퀴즈점수(30)]],BM88,BN88,BO88) -> 67.32 | BQ88: =IF(OR(BP88="",BP88=0,BT88="결석초과"),"",COUNTIFS($B$2:$B$109,B88,$BP$2:$BP$109,">"&BP88)+1) -> 21 | BR88: F | BS88: 4
A89: 경영학과 | B89: 3 | C89: 20220187 | D89: 하완명 | E89: 010-5163-8532 | F89: 1652269355@qq.com | G89: B. 피드백 및 반복 (反馈和迭代) | H89: D. 최소한의 비용과 시간 소모 (最低限度的成本和时间消耗) | I89: C. 운영적 의사결정 (运营性决策) | J89: C. 마케팅 전략 (营销策略) | K89: C. 문제해결 (问题解决) | L89: C. 착수 → 계획 → 실행 → 마무리 (启动 → 计划 → 执行 → 结束) | M89: A. 프로젝트 콘텐츠 (项目内容/产出物), B. 프로젝트 메타데이터 (项目元数据) | N89: B. 비동기적 소통 (Asynchronous Communication / 异步沟通) | O89: X (거짓/错) | P89: O (참/对) | Q89: =10*SUMPRODUCT(--(G89:P89<>""),--(((G89:P89=정답표!$C$2:$L$2)+(G89:P89=정답표!$C$3:$L$3))>0)) -> 100 | AN89: 在风险、成本和便利性之间找到适当的平衡。 | AO89: 因为将所有安全风险降至零在现实中是不可能且低效的。 | AP89: 未应用安全补丁的旧软件 | AQ89: 威胁能够访问系统或数据并造成损害的弱点。 | AR89: 将数据转换为未经授权的人无法理解的形式以进行保护的技术。 | AS89: 根据预设规则允许或阻止网络流量。 | AT89: 主要是技术部门制定和执行的技术问题。 | AU89: 定期测试备份数据是否能实际恢复非常重要。 | AV89: O | AW89: O | AX89: =10*SUMPRODUCT(--(AN89:AW89<>""),--(((AN89:AW89=정답표!$C$8:$L$8)+(AN89:AW89=정답표!$C$9:$L$9))>0)) -> 100 | BJ89: =SUM(Q89,AB89,AM89,AX89,BI89) -> 200 | BK89: =COUNT(Q89,AB89,AM89,AX89,BI89) -> 2 | BL89: =IF(QuizMatchTable[[#This Row],[분반]]=1, QuizMatchTable[[#This Row],[퀴즈합계]]/4 *0.3, QuizMatchTable[[#This Row],[퀴즈합계]]/5*0.3) -> 12 | BM89: 24.67 | BN89: 19.2 | BP89: =SUM(QuizMatchTable[[#This Row],[퀴즈점수(30)]],BM89,BN89,BO89) -> 55.87 | BQ89: =IF(OR(BP89="",BP89=0,BT89="결석초과"),"",COUNTIFS($B$2:$B$109,B89,$BP$2:$BP$109,">"&BP89)+1) -> 27 | BR89: F | BS89: 8
A90: 경영학과 | B90: 3 | C90: 20220189 | D90: 협일주 | E90: 010-7659-2898 | F90: 1109291893@qq.com | G90: B. 피드백 및 반복 (反馈和迭代) | H90: D. 최소한의 비용과 시간 소모 (最低限度的成本和时间消耗) | I90: C. 운영적 의사결정 (运营性决策) | K90: C. 문제해결 (问题解决) | L90: C. 착수 → 계획 → 실행 → 마무리 (启动 → 计划 → 执行 → 结束) | M90: A. 프로젝트 콘텐츠 (项目内容/产出物), B. 프로젝트 메타데이터 (项目元数据) | N90: B. 비동기적 소통 (Asynchronous Communication / 异步沟通) | O90: X (거짓/错) | P90: O (참/对) | Q90: =10*SUMPRODUCT(--(G90:P90<>""),--(((G90:P90=정답표!$C$2:$L$2)+(G90:P90=정답표!$C$3:$L$3))>0)) -> 90 | R90: BPR | S90: 遵循日常运营的正式化和标准化程序。 | T90: 企业间流程 | U90: 相同数据在多个部门重复存储，导致不一致。 | V90: 引入企业信息系统（EIS） | W90: 减少不必要的审批环节，从而最大限度地减少时间和资源。 | X90: 整合管理与客户的所有互动，最大限度地提高客户终身价值。 | Y90: 实现现有分离系统之间的数据共享和通信。 | Z90: O | AA90: O | AB90: =10*SUMPRODUCT(--(R90:AA90<>""),--(((R90:AA90=정답표!$C$4:$L$4)+(R90:AA90=정답표!$C$5:$L$5))>0)) -> 90 | AC90: 硬件、软件、数据、流程、人员 | AD90: 组织战略决定价值链，价值链决定业务流程，业务流程决定 SMIS 需求。 | AE90: 增加物质资本 | AF90: 直接销售用户数据：通过直接销售用户个人数据获取主要收入。 | AG90: 创新 (Innovation) | AH90: 指通过电子邮件、消息应用等难以追踪的渠道进行的社交分享区域，企业应在此处关注建立信任。 | AI90: 基于兴趣形成，一个用户可以同时属于多个社区。 | AJ90: 财务与会计 | AK90: O | AL90: O | AM90: =10*SUMPRODUCT(--(AC90:AL90<>""),--(((AC90:AL90=정답표!$C$6:$L$6)+(AC90:AL90=정답표!$C$7:$L$7))>0)) -> 100 | AN90: 在风险、成本和便利性之间找到适当的平衡。 | AO90: 因为将所有安全风险降至零在现实中是不可能且低效的。 | AP90: 未应用安全补丁的旧软件 | AQ90: 威胁能够访问系统或数据并造成损害的弱点。 | AR90: 将数据转换为未经授权的人无法理解的形式以进行保护的技术。 | AS90: 根据预设规则允许或阻止网络流量。 | AT90: 主要是技术部门制定和执行的技术问题。 | AU90: 定期测试备份数据是否能实际恢复非常重要。 | AV90: O | AW90: O | AX90: =10*SUMPRODUCT(--(AN90:AW90<>""),--(((AN90:AW90=정답표!$C$8:$L$8)+(AN90:AW90=정답표!$C$9:$L$9))>0)) -> 100 | AY90: 支持IT技术以实现组织目标，并将其与经营目标相结合。 | AZ90: 有效连接信息系统(IS)战略与企业经营战略。 | BA90: 根据组织的目标和优先顺序，综合考虑战略、预算和风险。 | BB90: 谁来做信息系统相关的决策，谁来承担责任？ | BC90: 综合考虑项目的战略适用性和实际可行性。 | BD90: 将组织的部分IT功能委托给外部专业公司执行。 | BE90: 安全威胁完全消除，信息安全得到加强。 | BF90: O | BG90: O | BH90: X | BI90: =10*SUMPRODUCT(--(AY90:BH90<>""),--(((AY90:BH90=정답표!$C$10:$L$10)+(AY90:BH90=정답표!$C$11:$L$11))>0)) -> 100 | BJ90: =SUM(Q90,AB90,AM90,AX90,BI90) -> 480 | BK90: =COUNT(Q90,AB90,AM90,AX90,BI90) -> 5 | BL90: =IF(QuizMatchTable[[#This Row],[분반]]=1, QuizMatchTable[[#This Row],[퀴즈합계]]/4 *0.3, QuizMatchTable[[#This Row],[퀴즈합계]]/5*0.3) -> 28.8 | BM90: 30 | BN90: 18.8 | BP90: =SUM(QuizMatchTable[[#This Row],[퀴즈점수(30)]],BM90,BN90,BO90) -> 77.6 | BQ90: =IF(OR(BP90="",BP90=0,BT90="결석초과"),"",COUNTIFS($B$2:$B$109,B90,$BP$2:$BP$109,">"&BP90)+1) -> 5 | BR90: A+ | BS90: 0
A91: 경영학과 | B91: 4 | C91: 20230479 | D91: 무정정 | E91: 010-5856-4606 | F91: wutingting040406@naver.com | G91: B. 피드백 및 반복 (反馈和迭代) | H91: D. 최소한의 비용과 시간 소모 (最低限度的成本和时间消耗) | I91: C. 운영적 의사결정 (运营性决策) | J91: C. 마케팅 전략 (营销策略) | K91: C. 문제해결 (问题解决) | L91: C. 착수 → 계획 → 실행 → 마무리 (启动 → 计划 → 执行 → 结束) | M91: A. 프로젝트 콘텐츠 (项目内容/产出物), B. 프로젝트 메타데이터 (项目元数据) | N91: B. 비동기적 소통 (Asynchronous Communication / 异步沟通) | O91: X (거짓/错) | P91: O (참/对) | Q91: =10*SUMPRODUCT(--(G91:P91<>""),--(((G91:P91=정답표!$C$2:$L$2)+(G91:P91=정답표!$C$3:$L$3))>0)) -> 100 | R91: BPR | S91: 遵循日常运营的正式化和标准化程序。 | T91: 企业间流程 | U91: 相同数据在多个部门重复存储，导致不一致。 | V91: 引入企业信息系统（EIS） | W91: 减少不必要的审批环节，从而最大限度地减少时间和资源。 | X91: 整合管理与客户的所有互动，最大限度地提高客户终身价值。 | Y91: 将业务运营整合到一个单一且一致的计算平台。 | Z91: O | AA91: O | AB91: =10*SUMPRODUCT(--(R91:AA91<>""),--(((R91:AA91=정답표!$C$4:$L$4)+(R91:AA91=정답표!$C$5:$L$5))>0)) -> 100 | AC91: 硬件、软件、数据、流程、人员 | AD91: 组织战略决定价值链，价值链决定业务流程，业务流程决定 SMIS 需求。 | AE91: 增加物质资本 | AF91: 直接销售用户数据：通过直接销售用户个人数据获取主要收入。 | AG91: 创新 (Innovation) | AH91: 指通过电子邮件、消息应用等难以追踪的渠道进行的社交分享区域，企业应在此处关注建立信任。 | AI91: 基于兴趣形成，一个用户可以同时属于多个社区。 | AJ91: 财务与会计 | AK91: O | AL91: O | AM91: =10*SUMPRODUCT(--(AC91:AL91<>""),--(((AC91:AL91=정답표!$C$6:$L$6)+(AC91:AL91=정답표!$C$7:$L$7))>0)) -> 100 | AN91: 在风险、成本和便利性之间找到适当的平衡。 | AO91: 因为将所有安全风险降至零在现实中是不可能且低效的。 | AP91: 未应用安全补丁的旧软件 | AQ91: 威胁能够访问系统或数据并造成损害的弱点。 | AR91: 将数据转换为未经授权的人无法理解的形式以进行保护的技术。 | AS91: 根据预设规则允许或阻止网络流量。 | AT91: 主要是技术部门制定和执行的技术问题。 | AU91: 定期测试备份数据是否能实际恢复非常重要。 | AV91: O | AX91: =10*SUMPRODUCT(--(AN91:AW91<>""),--(((AN91:AW91=정답표!$C$8:$L$8)+(AN91:AW91=정답표!$C$9:$L$9))>0)) -> 90 | AY91: 支持IT技术以实现组织目标，并将其与经营目标相结合。 | AZ91: 有效连接信息系统(IS)战略与企业经营战略。 | BA91: 根据组织的目标和优先顺序，综合考虑战略、预算和风险。 | BB91: 谁来做信息系统相关的决策，谁来承担责任？ | BC91: 综合考虑项目的战略适用性和实际可行性。 | BD91: 将组织的部分IT功能委托给外部专业公司执行。 | BE91: 安全威胁完全消除，信息安全得到加强。 | BF91: O | BG91: O | BH91: X | BI91: =10*SUMPRODUCT(--(AY91:BH91<>""),--(((AY91:BH91=정답표!$C$10:$L$10)+(AY91:BH91=정답표!$C$11:$L$11))>0)) -> 100 | BJ91: =SUM(Q91,AB91,AM91,AX91,BI91) -> 490 | BK91: =COUNT(Q91,AB91,AM91,AX91,BI91) -> 5 | BL91: =IF(QuizMatchTable[[#This Row],[분반]]=1, QuizMatchTable[[#This Row],[퀴즈합계]]/4 *0.3, QuizMatchTable[[#This Row],[퀴즈합계]]/5*0.3) -> 29.4 | BM91: 30 | BN91: 2.4 | BP91: =SUM(QuizMatchTable[[#This Row],[퀴즈점수(30)]],BM91,BN91,BO91) -> 61.8 | BQ91: =IF(OR(BP91="",BP91=0,BT91="결석초과"),"",COUNTIFS($B$2:$B$109,B91,$BP$2:$BP$109,">"&BP91)+1) -> 18 | BR91: F | BS91: 0
A92: 경영학과 | B92: 4 | C92: 20230480 | D92: 부일소 | E92: 010-7641-9026 | F92: 2199262853@qq.com | R92: BPR | S92: 遵循日常运营的正式化和标准化程序。 | T92: 企业间流程 | U92: 相同数据在多个部门重复存储，导致不一致。 | V92: 引入企业信息系统（EIS） | W92: 减少不必要的审批环节，从而最大限度地减少时间和资源。 | X92: 整合管理与客户的所有互动，最大限度地提高客户终身价值。 | Y92: 将业务运营整合到一个单一且一致的计算平台。 | Z92: O | AA92: O | AB92: =10*SUMPRODUCT(--(R92:AA92<>""),--(((R92:AA92=정답표!$C$4:$L$4)+(R92:AA92=정답표!$C$5:$L$5))>0)) -> 100 | AC92: 硬件、软件、数据、流程、人员 | AD92: 组织战略决定价值链，价值链决定业务流程，业务流程决定 SMIS 需求。 | AE92: 增加物质资本 | AF92: 直接销售用户数据：通过直接销售用户个人数据获取主要收入。 | AG92: 创新 (Innovation) | AH92: 指通过电子邮件、消息应用等难以追踪的渠道进行的社交分享区域，企业应在此处关注建立信任。 | AI92: 基于兴趣形成，一个用户可以同时属于多个社区。 | AJ92: 财务与会计 | AK92: O | AL92: O | AM92: =10*SUMPRODUCT(--(AC92:AL92<>""),--(((AC92:AL92=정답표!$C$6:$L$6)+(AC92:AL92=정답표!$C$7:$L$7))>0)) -> 100 | AN92: 在风险、成本和便利性之间找到适当的平衡。 | AO92: 因为将所有安全风险降至零在现实中是不可能且低效的。 | AP92: 未应用安全补丁的旧软件 | AQ92: 威胁能够访问系统或数据并造成损害的弱点。 | AR92: 将数据转换为未经授权的人无法理解的形式以进行保护的技术。 | AS92: 根据预设规则允许或阻止网络流量。 | AT92: 主要是技术部门制定和执行的技术问题。 | AU92: 定期测试备份数据是否能实际恢复非常重要。 | AV92: O | AW92: O | AX92: =10*SUMPRODUCT(--(AN92:AW92<>""),--(((AN92:AW92=정답표!$C$8:$L$8)+(AN92:AW92=정답표!$C$9:$L$9))>0)) -> 100 | AY92: 支持IT技术以实现组织目标，并将其与经营目标相结合。 | AZ92: 有效连接信息系统(IS)战略与企业经营战略。 | BA92: 根据组织的目标和优先顺序，综合考虑战略、预算和风险。 | BB92: 谁来做信息系统相关的决策，谁来承担责任？ | BC92: 综合考虑项目的战略适用性和实际可行性。 | BD92: 将组织的部分IT功能委托给外部专业公司执行。 | BE92: 安全威胁完全消除，信息安全得到加强。 | BF92: O | BG92: O | BH92: X | BI92: =10*SUMPRODUCT(--(AY92:BH92<>""),--(((AY92:BH92=정답표!$C$10:$L$10)+(AY92:BH92=정답표!$C$11:$L$11))>0)) -> 100 | BJ92: =SUM(Q92,AB92,AM92,AX92,BI92) -> 400 | BK92: =COUNT(Q92,AB92,AM92,AX92,BI92) -> 4 | BL92: =IF(QuizMatchTable[[#This Row],[분반]]=1, QuizMatchTable[[#This Row],[퀴즈합계]]/4 *0.3, QuizMatchTable[[#This Row],[퀴즈합계]]/5*0.3) -> 24 | BM92: 30 | BN92: 19.6 | BP92: =SUM(QuizMatchTable[[#This Row],[퀴즈점수(30)]],BM92,BN92,BO92) -> 73.6 | BQ92: =IF(OR(BP92="",BP92=0,BT92="결석초과"),"",COUNTIFS($B$2:$B$109,B92,$BP$2:$BP$109,">"&BP92)+1) -> 9 | BR92: B+ | BS92: 0
A93: 경영학과 | B93: 4 | C93: 20230481 | D93: 서문옥 | E93: 010-5709-6027 | F93: xuwenyu0627@124mail.cn | G93: B. 피드백 및 반복 (反馈和迭代) | H93: D. 최소한의 비용과 시간 소모 (最低限度的成本和时间消耗) | I93: C. 운영적 의사결정 (运营性决策) | J93: C. 마케팅 전략 (营销策略) | K93: C. 문제해결 (问题解决) | L93: C. 착수 → 계획 → 실행 → 마무리 (启动 → 计划 → 执行 → 结束) | M93: A. 프로젝트 콘텐츠 (项目内容/产出物), B. 프로젝트 메타데이터 (项目元数据) | N93: B. 비동기적 소통 (Asynchronous Communication / 异步沟通) | O93: X (거짓/错) | P93: O (참/对) | Q93: =10*SUMPRODUCT(--(G93:P93<>""),--(((G93:P93=정답표!$C$2:$L$2)+(G93:P93=정답표!$C$3:$L$3))>0)) -> 100 | R93: BPR | S93: 遵循日常运营的正式化和标准化程序。 | T93: 企业间流程 | U93: 相同数据在多个部门重复存储，导致不一致。 | V93: 引入企业信息系统（EIS） | W93: 减少不必要的审批环节，从而最大限度地减少时间和资源。 | X93: 整合管理与客户的所有互动，最大限度地提高客户终身价值。 | Y93: 将业务运营整合到一个单一且一致的计算平台。 | Z93: O | AA93: O | AB93: =10*SUMPRODUCT(--(R93:AA93<>""),--(((R93:AA93=정답표!$C$4:$L$4)+(R93:AA93=정답표!$C$5:$L$5))>0)) -> 100 | AC93: 硬件、软件、数据、流程、人员 | AD93: 组织战略决定价值链，价值链决定业务流程，业务流程决定 SMIS 需求。 | AE93: 增加物质资本 | AF93: 直接销售用户数据：通过直接销售用户个人数据获取主要收入。 | AG93: 创新 (Innovation) | AH93: 指通过电子邮件、消息应用等难以追踪的渠道进行的社交分享区域，企业应在此处关注建立信任。 | AI93: 基于兴趣形成，一个用户可以同时属于多个社区。 | AJ93: 财务与会计 | AK93: O | AL93: O | AM93: =10*SUMPRODUCT(--(AC93:AL93<>""),--(((AC93:AL93=정답표!$C$6:$L$6)+(AC93:AL93=정답표!$C$7:$L$7))>0)) -> 100 | AN93: 在风险、成本和便利性之间找到适当的平衡。 | AO93: 因为将所有安全风险降至零在现实中是不可能且低效的。 | AP93: 未应用安全补丁的旧软件 | AQ93: 威胁能够访问系统或数据并造成损害的弱点。 | AR93: 将数据转换为未经授权的人无法理解的形式以进行保护的技术。 | AS93: 根据预设规则允许或阻止网络流量。 | AT93: 主要是技术部门制定和执行的技术问题。 | AU93: 定期测试备份数据是否能实际恢复非常重要。 | AV93: O | AW93: O | AX93: =10*SUMPRODUCT(--(AN93:AW93<>""),--(((AN93:AW93=정답표!$C$8:$L$8)+(AN93:AW93=정답표!$C$9:$L$9))>0)) -> 100 | AY93: 支持IT技术以实现组织目标，并将其与经营目标相结合。 | AZ93: 有效连接信息系统(IS)战略与企业经营战略。 | BA93: 根据组织的目标和优先顺序，综合考虑战略、预算和风险。 | BB93: 谁来做信息系统相关的决策，谁来承担责任？ | BC93: 综合考虑项目的战略适用性和实际可行性。 | BD93: 将组织的所有核心能力完全转移给外部公司。 | BE93: 安全威胁完全消除，信息安全得到加强。 | BF93: O | BG93: O | BH93: X | BI93: =10*SUMPRODUCT(--(AY93:BH93<>""),--(((AY93:BH93=정답표!$C$10:$L$10)+(AY93:BH93=정답표!$C$11:$L$11))>0)) -> 90 | BJ93: =SUM(Q93,AB93,AM93,AX93,BI93) -> 490 | BK93: =COUNT(Q93,AB93,AM93,AX93,BI93) -> 5 | BL93: =IF(QuizMatchTable[[#This Row],[분반]]=1, QuizMatchTable[[#This Row],[퀴즈합계]]/4 *0.3, QuizMatchTable[[#This Row],[퀴즈합계]]/5*0.3) -> 29.4 | BM93: 30 | BN93: 20 | BP93: =SUM(QuizMatchTable[[#This Row],[퀴즈점수(30)]],BM93,BN93,BO93) -> 79.4 | BQ93: =IF(OR(BP93="",BP93=0,BT93="결석초과"),"",COUNTIFS($B$2:$B$109,B93,$BP$2:$BP$109,">"&BP93)+1) -> 2 | BR93: A+ | BS93: 0
A94: 경영학과 | B94: 4 | C94: 20230482 | D94: 섭청문 | E94: 010-2197-5039 | F94: 550888150@qq.com | G94: B. 피드백 및 반복 (反馈和迭代) | H94: D. 최소한의 비용과 시간 소모 (最低限度的成本和时间消耗) | I94: C. 운영적 의사결정 (运营性决策) | J94: C. 마케팅 전략 (营销策略) | K94: C. 문제해결 (问题解决) | L94: C. 착수 → 계획 → 실행 → 마무리 (启动 → 计划 → 执行 → 结束) | M94: A. 프로젝트 콘텐츠 (项目内容/产出物) | N94: B. 비동기적 소통 (Asynchronous Communication / 异步沟通) | O94: X (거짓/错) | P94: O (참/对) | Q94: =10*SUMPRODUCT(--(G94:P94<>""),--(((G94:P94=정답표!$C$2:$L$2)+(G94:P94=정답표!$C$3:$L$3))>0)) -> 90 | R94: BPR | S94: 遵循日常运营的正式化和标准化程序。 | T94: 企业间流程 | U94: 相同数据在多个部门重复存储，导致不一致。 | V94: 引入企业信息系统（EIS） | W94: 减少不必要的审批环节，从而最大限度地减少时间和资源。 | X94: 整合管理与客户的所有互动，最大限度地提高客户终身价值。 | Y94: 将业务运营整合到一个单一且一致的计算平台。 | Z94: O | AA94: O | AB94: =10*SUMPRODUCT(--(R94:AA94<>""),--(((R94:AA94=정답표!$C$4:$L$4)+(R94:AA94=정답표!$C$5:$L$5))>0)) -> 100 | AC94: 硬件、软件、数据、流程、人员 | AD94: 组织战略决定价值链，价值链决定业务流程，业务流程决定 SMIS 需求。 | AE94: 增加物质资本 | AF94: 直接销售用户数据：通过直接销售用户个人数据获取主要收入。 | AG94: 创新 (Innovation) | AH94: 指通过电子邮件、消息应用等难以追踪的渠道进行的社交分享区域，企业应在此处关注建立信任。 | AI94: 基于兴趣形成，一个用户可以同时属于多个社区。 | AJ94: 财务与会计 | AK94: O | AL94: O | AM94: =10*SUMPRODUCT(--(AC94:AL94<>""),--(((AC94:AL94=정답표!$C$6:$L$6)+(AC94:AL94=정답표!$C$7:$L$7))>0)) -> 100 | AN94: 在风险、成本和便利性之间找到适当的平衡。 | AO94: 因为将所有安全风险降至零在现实中是不可能且低效的。 | AP94: 未应用安全补丁的旧软件 | AQ94: 威胁能够访问系统或数据并造成损害的弱点。 | AR94: 将数据转换为未经授权的人无法理解的形式以进行保护的技术。 | AS94: 根据预设规则允许或阻止网络流量。 | AT94: 主要是技术部门制定和执行的技术问题。 | AU94: 定期测试备份数据是否能实际恢复非常重要。 | AV94: O | AW94: O | AX94: =10*SUMPRODUCT(--(AN94:AW94<>""),--(((AN94:AW94=정답표!$C$8:$L$8)+(AN94:AW94=정답표!$C$9:$L$9))>0)) -> 100 | AY94: 支持IT技术以实现组织目标，并将其与经营目标相结合。 | AZ94: 有效连接信息系统(IS)战略与企业经营战略。 | BA94: 根据组织的目标和优先顺序，综合考虑战略、预算和风险。 | BB94: 谁来做信息系统相关的决策，谁来承担责任？ | BC94: 综合考虑项目的战略适用性和实际可行性。 | BD94: 将组织的部分IT功能委托给外部专业公司执行。 | BE94: 安全威胁完全消除，信息安全得到加强。 | BF94: O | BG94: O | BH94: X | BI94: =10*SUMPRODUCT(--(AY94:BH94<>""),--(((AY94:BH94=정답표!$C$10:$L$10)+(AY94:BH94=정답표!$C$11:$L$11))>0)) -> 100 | BJ94: =SUM(Q94,AB94,AM94,AX94,BI94) -> 490 | BK94: =COUNT(Q94,AB94,AM94,AX94,BI94) -> 5 | BL94: =IF(QuizMatchTable[[#This Row],[분반]]=1, QuizMatchTable[[#This Row],[퀴즈합계]]/4 *0.3, QuizMatchTable[[#This Row],[퀴즈합계]]/5*0.3) -> 29.4 | BM94: 28 | BN94: 19.2 | BP94: =SUM(QuizMatchTable[[#This Row],[퀴즈점수(30)]],BM94,BN94,BO94) -> 76.6 | BQ94: =IF(OR(BP94="",BP94=0,BT94="결석초과"),"",COUNTIFS($B$2:$B$109,B94,$BP$2:$BP$109,">"&BP94)+1) -> 8 | BR94: B+ | BS94: 3
A95: 경영학과 | B95: 4 | C95: 20230483 | D95: 왕악침 | E95: 010-4366-9257 | F95: 418629596@qq.com | G95: C. 분업 및 전문화 (分工和专业化) | H95: D. 최소한의 비용과 시간 소모 (最低限度的成本和时间消耗) | I95: C. 운영적 의사결정 (运营性决策) | J95: C. 마케팅 전략 (营销策略) | K95: C. 문제해결 (问题解决) | L95: C. 착수 → 계획 → 실행 → 마무리 (启动 → 计划 → 执行 → 结束) | M95: A. 프로젝트 콘텐츠 (项目内容/产出物), B. 프로젝트 메타데이터 (项目元数据) | N95: B. 비동기적 소통 (Asynchronous Communication / 异步沟通) | O95: X (거짓/错) | P95: O (참/对) | Q95: =10*SUMPRODUCT(--(G95:P95<>""),--(((G95:P95=정답표!$C$2:$L$2)+(G95:P95=정답표!$C$3:$L$3))>0)) -> 90 | R95: BPR | S95: 일상적인 운영을 위한 공식적이고 표준화된 절차를 따릅니다. | T95: 기업 간 프로세스 | U95: 동일한 데이터가 여러 부서에 중복 저장되어 불일치가 발생합니다. | V95: 전사적 정보시스템(EIS) 도입 | W95: 불필요한 승인 단계를 축소하여 시간과 자원을 최소화합니다. | X95: 고객과의 모든 상호작용을 통합 관리하여 고객 평생 가치를 극대화하는 것입니다. | Y95: 비즈니스 운영을 단일하고 일관된 컴퓨팅 플랫폼에 통합하는 것입니다. | Z95: O | AA95: O | AB95: =10*SUMPRODUCT(--(R95:AA95<>""),--(((R95:AA95=정답표!$C$4:$L$4)+(R95:AA95=정답표!$C$5:$L$5))>0)) -> 100 | AC95: 硬件、软件、数据、流程、人员 | AD95: 组织战略决定价值链，价值链决定业务流程，业务流程决定 SMIS 需求。 | AE95: 增加物质资本 | AF95: 直接销售用户数据：通过直接销售用户个人数据获取主要收入。 | AG95: 创新 (Innovation) | AH95: 指通过电子邮件、消息应用等难以追踪的渠道进行的社交分享区域，企业应在此处关注建立信任。 | AI95: 基于兴趣形成，一个用户可以同时属于多个社区。 | AJ95: 财务与会计 | AK95: O | AL95: O | AM95: =10*SUMPRODUCT(--(AC95:AL95<>""),--(((AC95:AL95=정답표!$C$6:$L$6)+(AC95:AL95=정답표!$C$7:$L$7))>0)) -> 100 | AN95: 在风险、成本和便利性之间找到适当的平衡。 | AO95: 因为将所有安全风险降至零在现实中是不可能且低效的。 | AP95: 未应用安全补丁的旧软件 | AQ95: 威胁能够访问系统或数据并造成损害的弱点。 | AR95: 将数据转换为未经授权的人无法理解的形式以进行保护的技术。 | AS95: 根据预设规则允许或阻止网络流量。 | AT95: 主要是技术部门制定和执行的技术问题。 | AU95: 定期测试备份数据是否能实际恢复非常重要。 | AV95: O | AW95: O | AX95: =10*SUMPRODUCT(--(AN95:AW95<>""),--(((AN95:AW95=정답표!$C$8:$L$8)+(AN95:AW95=정답표!$C$9:$L$9))>0)) -> 100 | AY95: 支持IT技术以实现组织目标，并将其与经营目标相结合。 | AZ95: 有效连接信息系统(IS)战略与企业经营战略。 | BA95: 根据组织的目标和优先顺序，综合考虑战略、预算和风险。 | BB95: 谁来做信息系统相关的决策，谁来承担责任？ | BC95: 综合考虑项目的战略适用性和实际可行性。 | BD95: 将组织的部分IT功能委托给外部专业公司执行。 | BE95: 安全威胁完全消除，信息安全得到加强。 | BF95: O | BG95: O | BH95: X | BI95: =10*SUMPRODUCT(--(AY95:BH95<>""),--(((AY95:BH95=정답표!$C$10:$L$10)+(AY95:BH95=정답표!$C$11:$L$11))>0)) -> 100 | BJ95: =SUM(Q95,AB95,AM95,AX95,BI95) -> 490 | BK95: =COUNT(Q95,AB95,AM95,AX95,BI95) -> 5 | BL95: =IF(QuizMatchTable[[#This Row],[분반]]=1, QuizMatchTable[[#This Row],[퀴즈합계]]/4 *0.3, QuizMatchTable[[#This Row],[퀴즈합계]]/5*0.3) -> 29.4 | BM95: 30 | BN95: 19.2 | BP95: =SUM(QuizMatchTable[[#This Row],[퀴즈점수(30)]],BM95,BN95,BO95) -> 78.6 | BQ95: =IF(OR(BP95="",BP95=0,BT95="결석초과"),"",COUNTIFS($B$2:$B$109,B95,$BP$2:$BP$109,">"&BP95)+1) -> 4 | BR95: A0 | BS95: 0
A96: 경영학과 | B96: 4 | C96: 20230484 | D96: 왕예 | E96: 010-9607-8986 | F96: wangye19980908@gmail.com | G96: B. 피드백 및 반복 (反馈和迭代) | H96: D. 최소한의 비용과 시간 소모 (最低限度的成本和时间消耗) | I96: C. 운영적 의사결정 (运营性决策) | J96: C. 마케팅 전략 (营销策略) | K96: C. 문제해결 (问题解决) | L96: C. 착수 → 계획 → 실행 → 마무리 (启动 → 计划 → 执行 → 结束) | M96: A. 프로젝트 콘텐츠 (项目内容/产出物), B. 프로젝트 메타데이터 (项目元数据) | N96: B. 비동기적 소통 (Asynchronous Communication / 异步沟通) | O96: X (거짓/错) | P96: O (참/对) | Q96: =10*SUMPRODUCT(--(G96:P96<>""),--(((G96:P96=정답표!$C$2:$L$2)+(G96:P96=정답표!$C$3:$L$3))>0)) -> 100 | AC96: 硬件、软件、数据、流程、人员 | AD96: 组织战略决定价值链，价值链决定业务流程，业务流程决定 SMIS 需求。 | AE96: 增加物质资本 | AF96: 直接销售用户数据：通过直接销售用户个人数据获取主要收入。 | AG96: 创新 (Innovation) | AH96: 指通过电子邮件、消息应用等难以追踪的渠道进行的社交分享区域，企业应在此处关注建立信任。 | AI96: 基于兴趣形成，一个用户可以同时属于多个社区。 | AJ96: 财务与会计 | AK96: O | AL96: O | AM96: =10*SUMPRODUCT(--(AC96:AL96<>""),--(((AC96:AL96=정답표!$C$6:$L$6)+(AC96:AL96=정답표!$C$7:$L$7))>0)) -> 100 | AN96: 在风险、成本和便利性之间找到适当的平衡。 | AO96: 因为将所有安全风险降至零在现实中是不可能且低效的。 | AP96: 未应用安全补丁的旧软件 | AQ96: 威胁能够访问系统或数据并造成损害的弱点。 | AR96: 将数据转换为未经授权的人无法理解的形式以进行保护的技术。 | AS96: 根据预设规则允许或阻止网络流量。 | AT96: 主要是技术部门制定和执行的技术问题。 | AU96: 定期测试备份数据是否能实际恢复非常重要。 | AV96: O | AW96: O | AX96: =10*SUMPRODUCT(--(AN96:AW96<>""),--(((AN96:AW96=정답표!$C$8:$L$8)+(AN96:AW96=정답표!$C$9:$L$9))>0)) -> 100 | AY96: 支持IT技术以实现组织目标，并将其与经营目标相结合。 | AZ96: 有效连接信息系统(IS)战略与企业经营战略。 | BA96: 根据组织的目标和优先顺序，综合考虑战略、预算和风险。 | BB96: 谁来做信息系统相关的决策，谁来承担责任？ | BC96: 综合考虑项目的战略适用性和实际可行性。 | BD96: 将组织的部分IT功能委托给外部专业公司执行。 | BE96: 安全威胁完全消除，信息安全得到加强。 | BF96: O | BG96: O | BH96: X | BI96: =10*SUMPRODUCT(--(AY96:BH96<>""),--(((AY96:BH96=정답표!$C$10:$L$10)+(AY96:BH96=정답표!$C$11:$L$11))>0)) -> 100 | BJ96: =SUM(Q96,AB96,AM96,AX96,BI96) -> 400 | BK96: =COUNT(Q96,AB96,AM96,AX96,BI96) -> 4 | BL96: =IF(QuizMatchTable[[#This Row],[분반]]=1, QuizMatchTable[[#This Row],[퀴즈합계]]/4 *0.3, QuizMatchTable[[#This Row],[퀴즈합계]]/5*0.3) -> 24 | BM96: 30 | BN96: 19.2 | BP96: =SUM(QuizMatchTable[[#This Row],[퀴즈점수(30)]],BM96,BN96,BO96) -> 73.2 | BQ96: =IF(OR(BP96="",BP96=0,BT96="결석초과"),"",COUNTIFS($B$2:$B$109,B96,$BP$2:$BP$109,">"&BP96)+1) -> 10 | BR96: B0 | BS96: 0
A97: 경영학과 | B97: 4 | C97: 20230485 | D97: 왕우상 | E97: 010-7486-9190 | F97: 1278012014@qq.com | G97: B. 피드백 및 반복 (反馈和迭代) | H97: D. 최소한의 비용과 시간 소모 (最低限度的成本和时间消耗) | I97: C. 운영적 의사결정 (运营性决策) | J97: C. 마케팅 전략 (营销策略) | K97: C. 문제해결 (问题解决) | L97: C. 착수 → 계획 → 실행 → 마무리 (启动 → 计划 → 执行 → 结束) | M97: A. 프로젝트 콘텐츠 (项目内容/产出物), B. 프로젝트 메타데이터 (项目元数据) | N97: B. 비동기적 소통 (Asynchronous Communication / 异步沟通) | O97: X (거짓/错) | P97: O (참/对) | Q97: =10*SUMPRODUCT(--(G97:P97<>""),--(((G97:P97=정답표!$C$2:$L$2)+(G97:P97=정답표!$C$3:$L$3))>0)) -> 100 | AC97: 硬件、软件、数据、流程、人员 | AD97: 组织战略决定价值链，价值链决定业务流程，业务流程决定 SMIS 需求。 | AE97: 增加物质资本 | AF97: 直接销售用户数据：通过直接销售用户个人数据获取主要收入。 | AG97: 创新 (Innovation) | AH97: 指通过电子邮件、消息应用等难以追踪的渠道进行的社交分享区域，企业应在此处关注建立信任。 | AI97: 基于兴趣形成，一个用户可以同时属于多个社区。 | AJ97: 财务与会计 | AK97: O | AL97: O | AM97: =10*SUMPRODUCT(--(AC97:AL97<>""),--(((AC97:AL97=정답표!$C$6:$L$6)+(AC97:AL97=정답표!$C$7:$L$7))>0)) -> 100 | AN97: 在风险、成本和便利性之间找到适当的平衡。 | AO97: 因为将所有安全风险降至零在现实中是不可能且低效的。 | AP97: 未应用安全补丁的旧软件 | AQ97: 威胁能够访问系统或数据并造成损害的弱点。 | AR97: 将数据转换为未经授权的人无法理解的形式以进行保护的技术。 | AS97: 根据预设规则允许或阻止网络流量。 | AT97: 主要是技术部门制定和执行的技术问题。 | AU97: 定期测试备份数据是否能实际恢复非常重要。 | AV97: O | AW97: O | AX97: =10*SUMPRODUCT(--(AN97:AW97<>""),--(((AN97:AW97=정답표!$C$8:$L$8)+(AN97:AW97=정답표!$C$9:$L$9))>0)) -> 100 | BJ97: =SUM(Q97,AB97,AM97,AX97,BI97) -> 300 | BK97: =COUNT(Q97,AB97,AM97,AX97,BI97) -> 3 | BL97: =IF(QuizMatchTable[[#This Row],[분반]]=1, QuizMatchTable[[#This Row],[퀴즈합계]]/4 *0.3, QuizMatchTable[[#This Row],[퀴즈합계]]/5*0.3) -> 18 | BM97: 26 | BN97: 19.2 | BP97: =SUM(QuizMatchTable[[#This Row],[퀴즈점수(30)]],BM97,BN97,BO97) -> 63.2 | BQ97: =IF(OR(BP97="",BP97=0,BT97="결석초과"),"",COUNTIFS($B$2:$B$109,B97,$BP$2:$BP$109,">"&BP97)+1) -> 16 | BR97: F | BS97: 6
A98: 경영학과 | B98: 4 | C98: 20230486 | D98: 우국강 | E98: 010-3465-8546 | F98: niunovo@gmail.com | G98: B. 피드백 및 반복 (反馈和迭代) | H98: D. 최소한의 비용과 시간 소모 (最低限度的成本和时间消耗) | I98: C. 운영적 의사결정 (运营性决策) | J98: C. 마케팅 전략 (营销策略) | K98: C. 문제해결 (问题解决) | L98: C. 착수 → 계획 → 실행 → 마무리 (启动 → 计划 → 执行 → 结束) | M98: A. 프로젝트 콘텐츠 (项目内容/产出物), B. 프로젝트 메타데이터 (项目元数据) | N98: B. 비동기적 소통 (Asynchronous Communication / 异步沟通) | O98: X (거짓/错) | P98: O (참/对) | Q98: =10*SUMPRODUCT(--(G98:P98<>""),--(((G98:P98=정답표!$C$2:$L$2)+(G98:P98=정답표!$C$3:$L$3))>0)) -> 100 | AC98: 硬件、软件、数据、流程、人员 | AD98: 组织战略决定价值链，价值链决定业务流程，业务流程决定 SMIS 需求。 | AE98: 增加物质资本 | AF98: 直接销售用户数据：通过直接销售用户个人数据获取主要收入。 | AG98: 创新 (Innovation) | AH98: 指通过电子邮件、消息应用等难以追踪的渠道进行的社交分享区域，企业应在此处关注建立信任。 | AI98: 基于兴趣形成，一个用户可以同时属于多个社区。 | AJ98: 财务与会计 | AK98: O | AL98: O | AM98: =10*SUMPRODUCT(--(AC98:AL98<>""),--(((AC98:AL98=정답표!$C$6:$L$6)+(AC98:AL98=정답표!$C$7:$L$7))>0)) -> 100 | AN98: 在风险、成本和便利性之间找到适当的平衡。 | AO98: 因为将所有安全风险降至零在现实中是不可能且低效的。 | AP98: 未应用安全补丁的旧软件 | AQ98: 威胁能够访问系统或数据并造成损害的弱点。 | AR98: 将数据转换为未经授权的人无法理解的形式以进行保护的技术。 | AS98: 根据预设规则允许或阻止网络流量。 | AT98: 主要是技术部门制定和执行的技术问题。 | AU98: 定期测试备份数据是否能实际恢复非常重要。 | AV98: X | AW98: O | AX98: =10*SUMPRODUCT(--(AN98:AW98<>""),--(((AN98:AW98=정답표!$C$8:$L$8)+(AN98:AW98=정답표!$C$9:$L$9))>0)) -> 90 | AY98: 支持IT技术以实现组织目标，并将其与经营目标相结合。 | AZ98: 有效连接信息系统(IS)战略与企业经营战略。 | BA98: 根据组织的目标和优先顺序，综合考虑战略、预算和风险。 | BB98: 谁来做信息系统相关的决策，谁来承担责任？ | BC98: 综合考虑项目的战略适用性和实际可行性。 | BD98: 将组织的部分IT功能委托给外部专业公司执行。 | BE98: 安全威胁完全消除，信息安全得到加强。 | BF98: X | BG98: O | BH98: O | BI98: =10*SUMPRODUCT(--(AY98:BH98<>""),--(((AY98:BH98=정답표!$C$10:$L$10)+(AY98:BH98=정답표!$C$11:$L$11))>0)) -> 80 | BJ98: =SUM(Q98,AB98,AM98,AX98,BI98) -> 370 | BK98: =COUNT(Q98,AB98,AM98,AX98,BI98) -> 4 | BL98: =IF(QuizMatchTable[[#This Row],[분반]]=1, QuizMatchTable[[#This Row],[퀴즈합계]]/4 *0.3, QuizMatchTable[[#This Row],[퀴즈합계]]/5*0.3) -> 22.2 | BM98: 27.33 | BN98: 18.8 | BP98: =SUM(QuizMatchTable[[#This Row],[퀴즈점수(30)]],BM98,BN98,BO98) -> 68.33 | BQ98: =IF(OR(BP98="",BP98=0,BT98="결석초과"),"",COUNTIFS($B$2:$B$109,B98,$BP$2:$BP$109,">"&BP98)+1) -> 12 | BR98: F | BS98: 4
A99: 경영학과 | B99: 4 | C99: 20230487 | D99: 육희 | E99: 010-8481-0239 | F99: 2022461873@qq.com | G99: B. 피드백 및 반복 (反馈和迭代) | H99: D. 최소한의 비용과 시간 소모 (最低限度的成本和时间消耗) | I99: C. 운영적 의사결정 (运营性决策) | J99: C. 마케팅 전략 (营销策略) | K99: C. 문제해결 (问题解决) | L99: C. 착수 → 계획 → 실행 → 마무리 (启动 → 计划 → 执行 → 结束) | M99: C. 경영진 보고서 (管理层报告) | N99: B. 비동기적 소통 (Asynchronous Communication / 异步沟通) | O99: X (거짓/错) | P99: O (참/对) | Q99: =10*SUMPRODUCT(--(G99:P99<>""),--(((G99:P99=정답표!$C$2:$L$2)+(G99:P99=정답표!$C$3:$L$3))>0)) -> 90 | R99: BPR | S99: 遵循日常运营的正式化和标准化程序。 | T99: 企业间流程 | U99: 相同数据在多个部门重复存储，导致不一致。 | V99: 引入企业信息系统（EIS） | W99: 减少不必要的审批环节，从而最大限度地减少时间和资源。 | X99: 整合管理与客户的所有互动，最大限度地提高客户终身价值。 | Y99: 将业务运营整合到一个单一且一致的计算平台。 | Z99: O | AA99: O | AB99: =10*SUMPRODUCT(--(R99:AA99<>""),--(((R99:AA99=정답표!$C$4:$L$4)+(R99:AA99=정답표!$C$5:$L$5))>0)) -> 100 | AC99: 硬件、软件、数据、流程、人员 | AD99: 组织战略决定价值链，价值链决定业务流程，业务流程决定 SMIS 需求。 | AE99: 增加物质资本 | AF99: 直接销售用户数据：通过直接销售用户个人数据获取主要收入。 | AG99: 创新 (Innovation) | AH99: 指通过电子邮件、消息应用等难以追踪的渠道进行的社交分享区域，企业应在此处关注建立信任。 | AI99: 基于兴趣形成，一个用户可以同时属于多个社区。 | AJ99: 销售与营销 | AK99: O | AL99: O | AM99: =10*SUMPRODUCT(--(AC99:AL99<>""),--(((AC99:AL99=정답표!$C$6:$L$6)+(AC99:AL99=정답표!$C$7:$L$7))>0)) -> 90 | AN99: 在风险、成本和便利性之间找到适当的平衡。 | AO99: 因为将所有安全风险降至零在现实中是不可能且低效的。 | AP99: 未应用安全补丁的旧软件 | AQ99: 威胁能够访问系统或数据并造成损害的弱点。 | AR99: 将数据转换为未经授权的人无法理解的形式以进行保护的技术。 | AS99: 根据预设规则允许或阻止网络流量。 | AT99: 主要是技术部门制定和执行的技术问题。 | AU99: 定期测试备份数据是否能实际恢复非常重要。 | AV99: O | AW99: O | AX99: =10*SUMPRODUCT(--(AN99:AW99<>""),--(((AN99:AW99=정답표!$C$8:$L$8)+(AN99:AW99=정답표!$C$9:$L$9))>0)) -> 100 | AY99: 支持IT技术以实现组织目标，并将其与经营目标相结合。 | AZ99: 有效连接信息系统(IS)战略与企业经营战略。 | BA99: 根据组织的目标和优先顺序，综合考虑战略、预算和风险。 | BB99: 谁来做信息系统相关的决策，谁来承担责任？ | BC99: 综合考虑项目的战略适用性和实际可行性。 | BD99: 将组织的部分IT功能委托给外部专业公司执行。 | BE99: 安全威胁完全消除，信息安全得到加强。 | BF99: O | BG99: O | BH99: X | BI99: =10*SUMPRODUCT(--(AY99:BH99<>""),--(((AY99:BH99=정답표!$C$10:$L$10)+(AY99:BH99=정답표!$C$11:$L$11))>0)) -> 100 | BJ99: =SUM(Q99,AB99,AM99,AX99,BI99) -> 480 | BK99: =COUNT(Q99,AB99,AM99,AX99,BI99) -> 5 | BL99: =IF(QuizMatchTable[[#This Row],[분반]]=1, QuizMatchTable[[#This Row],[퀴즈합계]]/4 *0.3, QuizMatchTable[[#This Row],[퀴즈합계]]/5*0.3) -> 28.8 | BM99: 30 | BN99: 19.2 | BP99: =SUM(QuizMatchTable[[#This Row],[퀴즈점수(30)]],BM99,BN99,BO99) -> 78 | BQ99: =IF(OR(BP99="",BP99=0,BT99="결석초과"),"",COUNTIFS($B$2:$B$109,B99,$BP$2:$BP$109,">"&BP99)+1) -> 6 | BR99: B+ | BS99: 0
